{"Title": ["Grand Theft Parsons", "   "], "Author": ["\u00a0\u00a0Jeremy Drysdale"], "Genre": ["\u00a0\u00a0Drama\u00a0\u00a0Comedy"], "Characters": [{"Character": "GRAND THEFT PARSONS", "Replies": [{"Reply": "Written by  Jeremy Drysdale     June 2003    OPENING TITLE. ", "Didascalie": "", "Start": 83, "End": 268}]}, {"Character": "PHIL", "Replies": [{"Reply": "Hello? ", "Didascalie": "", "Start": 3283, "End": 3290}, {"Reply": "Okay. I'd like to see Gram Parsons. ", "Didascalie": "", "Start": 6643, "End": 6704}, {"Reply": "Yes. Alone, if possible. And would you have a gurney standing by in case I need to move him? ", "Didascalie": "", "Start": 7035, "End": 7178}, {"Reply": "Actually, I'm his road manager. ", "Didascalie": "", "Start": 7676, "End": 7708}, {"Reply": "No. ", "Didascalie": "", "Start": 8019, "End": 8023}, {"Reply": "Sheesh! ", "Didascalie": "", "Start": 9867, "End": 9875}, {"Reply": "Hello buddy. How you been? ", "Didascalie": "", "Start": 10080, "End": 10107}, {"Reply": "Well, I can't stand around here chatting with you all day. ", "Didascalie": "", "Start": 10314, "End": 10393}, {"Reply": "Naw, I'm cool thanks. ", "Didascalie": "", "Start": 10850, "End": 10872}, {"Reply": "Just taking some stiff down to neurology. ", "Didascalie": "", "Start": 11092, "End": 11154}, {"Reply": "Urology. ", "Didascalie": "", "Start": 11475, "End": 11484}, {"Reply": "Okay. Just hold your horses - ", "Didascalie": "", "Start": 11749, "End": 11779}, {"Reply": "No. You have your paperwork. I need to go check my paperwork. ", "Didascalie": "", "Start": 12054, "End": 12141}, {"Reply": "Martin Luther King. ", "Didascalie": "", "Start": 13950, "End": 13970}, {"Reply": "Yeah, out of a job again. ", "Didascalie": "", "Start": 14933, "End": 14959}, {"Reply": "How do you know I wasn't? ", "Didascalie": "", "Start": 15157, "End": 15183}, {"Reply": "I was still 'on staff'. He was still my responsibility. ", "Didascalie": "", "Start": 15386, "End": 15462}, {"Reply": "So where have you been, anyway? ", "Didascalie": "", "Start": 15717, "End": 15749}, {"Reply": "How long this time? Two weeks? ", "Didascalie": "", "Start": 15881, "End": 15912}, {"Reply": "Yeah, but I usually leave a note. ", "Didascalie": "", "Start": 16223, "End": 16257}, {"Reply": "What's this? ", "Didascalie": "", "Start": 16956, "End": 16969}, {"Reply": "Hello. ", "Didascalie": "", "Start": 21105, "End": 21112}, {"Reply": "When you're here, I spend my time wondering when you're going. And when you're back, I wonder where you've been. ", "Didascalie": "", "Start": 22067, "End": 22255}, {"Reply": "You mean there's more than that? ", "Didascalie": "", "Start": 22596, "End": 22629}, {"Reply": "There's dull, boring, normal. ", "Didascalie": "", "Start": 23007, "End": 23037}, {"Reply": "I represent the combined forces of charm, enchantment and exuberance. ", "Didascalie": "", "Start": 23876, "End": 23996}, {"Reply": "Long time, no see, Barbara. ", "Didascalie": "", "Start": 25293, "End": 25321}, {"Reply": "Meet Barbara. ", "Didascalie": "", "Start": 25946, "End": 25960}, {"Reply": "Gram's ex-girlfriend. ", "Didascalie": "", "Start": 26373, "End": 26395}, {"Reply": "What do you want, Barbara? ", "Didascalie": "", "Start": 26799, "End": 26826}, {"Reply": "That's nice. I have no idea what you're talking about. ", "Didascalie": "", "Start": 27139, "End": 27219}, {"Reply": "Did he write that with joined up writing or was it before he knew how? ", "Didascalie": "", "Start": 28170, "End": 28283}, {"Reply": "That's not a will Barbara, and you know it. ", "Didascalie": "", "Start": 28541, "End": 28606}, {"Reply": "Guitar? ", "Didascalie": "", "Start": 29099, "End": 29107}, {"Reply": "It's been a while since you were around, Barbara. ", "Didascalie": "", "Start": 29313, "End": 29384}, {"Reply": "  14. ", "Didascalie": "(MOR E)", "Start": 29422, "End": 29501}, {"Reply": "Hey, well done. You found the only unbroken thing. ", "Didascalie": "", "Start": 30673, "End": 30745}, {"Reply": "It's all part of the grieving process. ", "Didascalie": "", "Start": 30906, "End": 30966}, {"Reply": "Nothing. ", "Didascalie": "", "Start": 31336, "End": 31345}, {"Reply": "Do me a favor and get the guitar, sweetheart. ", "Didascalie": "", "Start": 31565, "End": 31632}, {"Reply": " I gotta make a call. ", "Didascalie": "(O.S)", "Start": 31969, "End": 32016}, {"Reply": "These things aren't that big. ", "Didascalie": "", "Start": 35625, "End": 35655}, {"Reply": "Not really. ", "Didascalie": "", "Start": 35838, "End": 35850}, {"Reply": "It's best you don't know. ", "Didascalie": "", "Start": 36374, "End": 36400}, {"Reply": "Well, that's the point. ", "Didascalie": "", "Start": 36886, "End": 36910}, {"Reply": "Right. ", "Didascalie": "", "Start": 37200, "End": 37207}, {"Reply": "Again. ", "Didascalie": "", "Start": 37366, "End": 37373}, {"Reply": " Hello? Anyone there? ", "Didascalie": "(O.S)", "Start": 38959, "End": 39001}, {"Reply": " There you are. I'm looking for Larry Osterberg. ", "Didascalie": "(CONT'D) (O.S)", "Start": 39205, "End": 39294}, {"Reply": "You Larry Osterberg? ", "Didascalie": "", "Start": 39730, "End": 39751}, {"Reply": "Very nice.     What's that noise? ", "Didascalie": "", "Start": 40046, "End": 40080}, {"Reply": " Okay. ", "Didascalie": "(carefully)", "Start": 40546, "End": 40578}, {"Reply": "Right. ", "Didascalie": "", "Start": 40957, "End": 40964}, {"Reply": "Oh, I'm Phil Kaufman. ", "Didascalie": "", "Start": 41127, "End": 41149}, {"Reply": "I'd like to hire your car. ", "Didascalie": "", "Start": 41365, "End": 41392}, {"Reply": "Well, I need to pick someone up at the airport. ", "Didascalie": "", "Start": 41550, "End": 41623}, {"Reply": "Yes, of course. It's just that I'm told your car is more suitable. ", "Didascalie": "", "Start": 41799, "End": 41916}, {"Reply": "A prank.   A surprise. ", "Didascalie": "", "Start": 42939, "End": 42962}, {"Reply": "No, it's more of a fifty dollar surprise. ", "Didascalie": "", "Start": 43166, "End": 43229}, {"Reply": "Booked how? ", "Didascalie": "", "Start": 43441, "End": 43453}, {"Reply": "Well, here's two hundred dollars to unbook it. Let 'em carry their own trombones. ", "Didascalie": "", "Start": 43730, "End": 43854}, {"Reply": "You don't need to count it.   You could trust me. ", "Didascalie": "", "Start": 44008, "End": 44079}, {"Reply": "That last twenty is for gas. ", "Didascalie": "", "Start": 44736, "End": 44765}, {"Reply": "Bernice? ", "Didascalie": "", "Start": 45586, "End": 45595}, {"Reply": "It's yellow. ", "Didascalie": "", "Start": 46474, "End": 46487}, {"Reply": "It's supposed to be black. ", "Didascalie": "", "Start": 46692, "End": 46719}, {"Reply": "That might be my point. ", "Didascalie": "", "Start": 46993, "End": 47017}, {"Reply": "I paid you two hundred dollars for a black hearse. ", "Didascalie": "", "Start": 47307, "End": 47383}, {"Reply": "Okay.   Where are the keys? ", "Didascalie": "", "Start": 48133, "End": 48161}, {"Reply": "I gotta go. ", "Didascalie": "", "Start": 48320, "End": 48332}, {"Reply": "Okay.   Well, let's boogie. ", "Didascalie": "", "Start": 48658, "End": 48686}, {"Reply": "You are famous throughout the greater Los Angeles area. ", "Didascalie": "", "Start": 49817, "End": 49898}, {"Reply": "Pull over. ", "Didascalie": "", "Start": 51061, "End": 51072}, {"Reply": "Shit. ", "Didascalie": "", "Start": 51223, "End": 51229}, {"Reply": "Nothing. ", "Didascalie": "", "Start": 51508, "End": 51517}, {"Reply": "We'll wait here. ", "Didascalie": "", "Start": 51703, "End": 51720}, {"Reply": "Soon. ", "Didascalie": "", "Start": 51930, "End": 51936}, {"Reply": "Why do you ask so many damn questions? ", "Didascalie": "", "Start": 52109, "End": 52173}, {"Reply": "Look, will you please shut up asking me stuff? ", "Didascalie": "", "Start": 52516, "End": 52588}, {"Reply": "Morning. ", "Didascalie": "", "Start": 53109, "End": 53118}, {"Reply": "We'll make the pick-up in the morning. ", "Didascalie": "", "Start": 53480, "End": 53540}, {"Reply": "Yes I am. ", "Didascalie": "", "Start": 61622, "End": 61632}, {"Reply": "Okay.   A casket. ", "Didascalie": "", "Start": 61890, "End": 61908}, {"Reply": "It   was due out on the next flight to   New Orleans, but I'm driving it   now. The stiff doesn't like to   fly. ", "Didascalie": "", "Start": 62184, "End": 62372}, {"Reply": "Yeah, but it's my day off. ", "Didascalie": "", "Start": 62635, "End": 62662}, {"Reply": "Parsons. ", "Didascalie": "", "Start": 63053, "End": 63062}, {"Reply": "They'll be along. With this being a rush job, they said you'd understand. ", "Didascalie": "", "Start": 67932, "End": 68056}, {"Reply": "Yup.   That's a she. ", "Didascalie": "", "Start": 72419, "End": 72440}, {"Reply": "Gone?    Whaddya mean, gone? ", "Didascalie": "", "Start": 72994, "End": 73023}, {"Reply": "Nice work.     So how do I get my box back? ", "Didascalie": "", "Start": 73257, "End": 73326}, {"Reply": "You're a damn thief. ", "Didascalie": "", "Start": 73488, "End": 73509}, {"Reply": "Can you speed things up? ", "Didascalie": "", "Start": 75540, "End": 75565}, {"Reply": "I'd like to get to the Joshua Tree while it's still light. ", "Didascalie": "", "Start": 75822, "End": 75906}, {"Reply": "What? ", "Didascalie": "", "Start": 76173, "End": 76179}, {"Reply": "Joshua Tree, yeah. ", "Didascalie": "", "Start": 76602, "End": 76621}, {"Reply": "Joshua Tree, Louisiana. Just outside the city. ", "Didascalie": "", "Start": 76766, "End": 76838}, {"Reply": "It's small. Just another local community struggling to get by. ", "Didascalie": "", "Start": 77113, "End": 77201}, {"Reply": "Use your phone? ", "Didascalie": "", "Start": 77381, "End": 77397}, {"Reply": "Yeah.   I'm a real lucky guy. ", "Didascalie": "", "Start": 78906, "End": 78936}, {"Reply": "Well, I don't care if it is first thing in the morning - but I sure need a coffee. I tell you, I've never seen so many darned bits of paper to sign! It's paperwork which is slowing this great country down. We're drowning in triplicate! ", "Didascalie": "", "Start": 82028, "End": 82439}, {"Reply": "Good morning officer. ", "Didascalie": "", "Start": 82642, "End": 82664}, {"Reply": "I was just saying how people with work to do - people like yourself, officer - are just getting engulfed by paper. Grab the end, will you? Doesn't that just drive you plain crazy? ", "Didascalie": "", "Start": 82882, "End": 83187}, {"Reply": "One casket, six sheets to sign. ", "Didascalie": "", "Start": 83645, "End": 83677}, {"Reply": "And the very last thing I want to do is to hold you up further with my chatter. Thank you for your help, officer. You have a good day, now. ", "Didascalie": "", "Start": 84011, "End": 84235}, {"Reply": "Yessir? ", "Didascalie": "", "Start": 84504, "End": 84512}, {"Reply": "And there you have it, officer. ", "Didascalie": "", "Start": 84976, "End": 85008}, {"Reply": "Yeah. We're doing it this way for the avoidance of doubt. ", "Didascalie": "", "Start": 85662, "End": 85741}, {"Reply": "Thanks for everything, officer. ", "Didascalie": "", "Start": 86489, "End": 86521}, {"Reply": "Yes!    We did it!! ", "Didascalie": "", "Start": 86969, "End": 86989}, {"Reply": "What was all that babbling about earlier? ", "Didascalie": "", "Start": 87204, "End": 87267}, {"Reply": "What the hell does that mean? ", "Didascalie": "", "Start": 87592, "End": 87622}, {"Reply": "Well of course they make you feel uneasy. They're supposed to make you feel uneasy. ", "Didascalie": "", "Start": 87907, "End": 88041}, {"Reply": "You hit the wall. ", "Didascalie": "", "Start": 88572, "End": 88590}, {"Reply": " There's a gap fifty yards wide! ", "Didascalie": "(shouts)", "Start": 88814, "End": 88872}, {"Reply": "Fantastic.     Well done. ", "Didascalie": "", "Start": 91213, "End": 91239}, {"Reply": "Well? ", "Didascalie": "", "Start": 92191, "End": 92197}, {"Reply": "Well, what are we doing now? ", "Didascalie": "", "Start": 92348, "End": 92377}, {"Reply": "Nice going, hippie. Went right through the gap that time. ", "Didascalie": "", "Start": 92727, "End": 92806}, {"Reply": "Well, we got it. Whoooh!!! ", "Didascalie": "", "Start": 92957, "End": 92984}, {"Reply": "What are you talking about? ", "Didascalie": "", "Start": 93363, "End": 93391}, {"Reply": "C'mon, we gotta keep moving. ", "Didascalie": "", "Start": 93532, "End": 93561}, {"Reply": " Stop saying that!    I can't get out. ", "Didascalie": "(shouts)", "Start": 94145, "End": 94226}, {"Reply": "Thank God. ", "Didascalie": "", "Start": 94632, "End": 94643}, {"Reply": "What the hell are you doing? ", "Didascalie": "", "Start": 94763, "End": 94792}, {"Reply": "You can't do that. ", "Didascalie": "", "Start": 94963, "End": 94982}, {"Reply": "What talk? ", "Didascalie": "", "Start": 95472, "End": 95483}, {"Reply": "Can we please talk about this later? This is not a great place to be right now. ", "Didascalie": "", "Start": 98635, "End": 98765}, {"Reply": "You think there's a body in the coffin! ", "Didascalie": "", "Start": 99174, "End": 99239}, {"Reply": "I can fully understand why you'd think that. I mean, it is a coffin and all. But would I - ", "Didascalie": "", "Start": 99427, "End": 99568}, {"Reply": "Absolutely, completely, totally. ", "Didascalie": "", "Start": 101457, "End": 101490}, {"Reply": "Look, I'm not going to argue with you now. Poplar is very well suited to the making of coffins. ", "Didascalie": "", "Start": 102022, "End": 102168}, {"Reply": "Fifty-fifty? That baby's worth two grand. ", "Didascalie": "", "Start": 103348, "End": 103415}, {"Reply": "So then Bobby transfers 'em into hardboard boxes just prior to the cremation and I drive the caskets over to a guy I know in Palm Springs who resells them. ", "Didascalie": "", "Start": 104440, "End": 104696}, {"Reply": "Well I'm not sure the 'one careful owner' thing works with coffins. ", "Didascalie": "", "Start": 104972, "End": 105090}, {"Reply": "Yeah, well. I saw how outraged you were back there, when I mentioned money. Just think of it as recycling. ", "Didascalie": "", "Start": 105307, "End": 105489}, {"Reply": "Why? ", "Didascalie": "", "Start": 105677, "End": 105682}, {"Reply": "Well, while I acknowledge the power of your argument, we have to be somewhere else. So just settle back and enjoy the ride. ", "Didascalie": "", "Start": 105889, "End": 106088}, {"Reply": "What now? ", "Didascalie": "", "Start": 106211, "End": 106221}, {"Reply": "Sure am. ", "Didascalie": "", "Start": 106695, "End": 106704}, {"Reply": "Nope. We're special rock 'n roll undertakers. Musical morticians. ", "Didascalie": "", "Start": 107024, "End": 107115}, {"Reply": " C'mon, hippie - let's roll. ", "Didascalie": "(O.S)", "Start": 107435, "End": 107489}, {"Reply": "High test. ", "Didascalie": "", "Start": 107908, "End": 107919}, {"Reply": "Who says it's for the car? ", "Didascalie": "", "Start": 108187, "End": 108214}, {"Reply": "Nope. ", "Didascalie": "", "Start": 108580, "End": 108586}, {"Reply": "Why would we want to do that? ", "Didascalie": "", "Start": 109175, "End": 109205}, {"Reply": "You want to go home to pick up fresh clothes? ", "Didascalie": "", "Start": 109556, "End": 109627}, {"Reply": "And then drive back out tomorrow? ", "Didascalie": "", "Start": 109824, "End": 109858}, {"Reply": "Just drive the car, okay? ", "Didascalie": "", "Start": 110029, "End": 110055}, {"Reply": "No. ", "Didascalie": "", "Start": 110228, "End": 110232}, {"Reply": "No. ", "Didascalie": "", "Start": 110389, "End": 110393}, {"Reply": "No. ", "Didascalie": "", "Start": 110557, "End": 110561}, {"Reply": "Well, I do everything. ", "Didascalie": "", "Start": 111586, "End": 111609}, {"Reply": "This little number is for drinking money. By trade I'm a Road Manager. ", "Didascalie": "", "Start": 111774, "End": 111895}, {"Reply": "No, not like a well-paid gopher. ", "Didascalie": "", "Start": 112119, "End": 112152}, {"Reply": "Hello baby, it's the love machine. How are ya? ", "Didascalie": "", "Start": 117587, "End": 117659}, {"Reply": "Sorry Barb, gotta go. ", "Didascalie": "", "Start": 118969, "End": 118991}, {"Reply": "It's been real, though. ", "Didascalie": "", "Start": 119173, "End": 119197}, {"Reply": "So what's that about? ", "Didascalie": "", "Start": 120872, "End": 120894}, {"Reply": "You've hardly left the car since we met. How can you have sunstroke? ", "Didascalie": "", "Start": 121085, "End": 121194}, {"Reply": "Turn off here. ", "Didascalie": "", "Start": 121807, "End": 121822}, {"Reply": "It is if you're a coffin smuggler. ", "Didascalie": "", "Start": 122065, "End": 122125}, {"Reply": "It would be really nice if we could get through a couple of hours without crashing the car. ", "Didascalie": "", "Start": 127302, "End": 127434}, {"Reply": "Of course you were. ", "Didascalie": "", "Start": 127688, "End": 127708}, {"Reply": "Pretend we're having a conversation. ", "Didascalie": "", "Start": 128695, "End": 128757}, {"Reply": "I don't know what about! Ever since I met you, you've talked. ", "Didascalie": "", "Start": 129077, "End": 129164}, {"Reply": "Whatever your damn fool religion is called, I think it works. ", "Didascalie": "", "Start": 129645, "End": 129732}, {"Reply": "Oh, well done. Good work. ", "Didascalie": "", "Start": 130026, "End": 130052}, {"Reply": "Afternoon, officer.    How's it going today? ", "Didascalie": "", "Start": 130582, "End": 130652}, {"Reply": "Anything. ", "Didascalie": "", "Start": 133538, "End": 133548}, {"Reply": "I think he's onto us, Larry. ", "Didascalie": "", "Start": 134979, "End": 135008}, {"Reply": "God damn! ", "Didascalie": "", "Start": 135712, "End": 135722}, {"Reply": "He meant a coffin. ", "Didascalie": "", "Start": 135963, "End": 135982}, {"Reply": "Look, the place that I get the coffins from probably haven't filed a report yet. It'll all be sorted out within the hour. ", "Didascalie": "", "Start": 136357, "End": 136554}, {"Reply": "Jesus! ", "Didascalie": "", "Start": 137295, "End": 137302}, {"Reply": "Time. ", "Didascalie": "", "Start": 137650, "End": 137656}, {"Reply": " We're going to be arrested, that's what we're going to do. ", "Didascalie": "(bitterly)", "Start": 137818, "End": 137928}, {"Reply": "Yeah, that would be great. Then we could suspend you from a bridge in a straitjacket and set the rope on fire. ", "Didascalie": "", "Start": 138526, "End": 138700}, {"Reply": "Okay.   Show me. ", "Didascalie": "", "Start": 138952, "End": 138969}, {"Reply": "Yes, I think we should go. ", "Didascalie": "", "Start": 139343, "End": 139370}, {"Reply": "Nicely done. ", "Didascalie": "", "Start": 139850, "End": 139863}, {"Reply": "We'll be moving on, now that your sign no longer appears to be impeding our forward progress. ", "Didascalie": "", "Start": 140072, "End": 140208}, {"Reply": "What the hell are you doing? ", "Didascalie": "", "Start": 140515, "End": 140544}, {"Reply": "So, we've escaped but we can only drive in a circle? ", "Didascalie": "", "Start": 141095, "End": 141173}, {"Reply": "Can we please go? ", "Didascalie": "", "Start": 141992, "End": 142010}, {"Reply": "Why would they do that? ", "Didascalie": "", "Start": 147204, "End": 147228}, {"Reply": "You worry too much. ", "Didascalie": "", "Start": 147663, "End": 147683}, {"Reply": "Jesus - what the hell is that? ", "Didascalie": "", "Start": 148008, "End": 148039}, {"Reply": "Very perceptive.   What's it doing? ", "Didascalie": "", "Start": 148270, "End": 148331}, {"Reply": "We need to stop. I'm starting to get hungry. I'm not nice hungry. ", "Didascalie": "", "Start": 149717, "End": 149804}, {"Reply": "What gave you the impression this was a democracy? ", "Didascalie": "", "Start": 150004, "End": 150076}, {"Reply": "You frighten him. ", "Didascalie": "", "Start": 151527, "End": 151545}, {"Reply": "Everyone else, he announces the food when he brings it. ", "Didascalie": "", "Start": 151694, "End": 151771}, {"Reply": "It's probably the rabbit food. ", "Didascalie": "", "Start": 152170, "End": 152201}, {"Reply": "I understand. Really I do. That stuff'll mess you right up every time. ", "Didascalie": "", "Start": 152443, "End": 152564}, {"Reply": "Gotta make a call. ", "Didascalie": "", "Start": 153304, "End": 153323}, {"Reply": "Hey man, where's the phone? ", "Didascalie": "", "Start": 153468, "End": 153496}, {"Reply": "Who? ", "Didascalie": "", "Start": 155568, "End": 155573}, {"Reply": "None of your damn business. ", "Didascalie": "", "Start": 155759, "End": 155787}, {"Reply": "No. ", "Didascalie": "", "Start": 155987, "End": 155991}, {"Reply": "Yeah, that'll be it.     Shopping. ", "Didascalie": "", "Start": 156455, "End": 156490}, {"Reply": " We gotta go. ", "Didascalie": "(to Larry)", "Start": 158315, "End": 158350}, {"Reply": "All gone.     C'mon. ", "Didascalie": "", "Start": 158781, "End": 158802}, {"Reply": "Better get going. ", "Didascalie": "", "Start": 160119, "End": 160137}, {"Reply": "Yeah, he was a real blabbermouth. ", "Didascalie": "", "Start": 160370, "End": 160404}, {"Reply": "Well, I think we should just make our delivery as soon as possible, don't you? Get our package to Palm Springs. Remember? ", "Didascalie": "", "Start": 160861, "End": 161058}, {"Reply": "We've really got to go. ", "Didascalie": "", "Start": 161921, "End": 161945}, {"Reply": "Okay, then. Well, if you're satisfied, let's go. ", "Didascalie": "", "Start": 162336, "End": 162406}, {"Reply": "Heavy, yes. Well, it is made of wood. Wood is heavy. Actually. ", "Didascalie": "", "Start": 162562, "End": 162646}, {"Reply": "Well, technically, we stole Gram Parsons. ", "Didascalie": "", "Start": 163585, "End": 163648}, {"Reply": "I'd save that line for court. ", "Didascalie": "", "Start": 163862, "End": 163892}, {"Reply": "What are you doing now? ", "Didascalie": "", "Start": 164098, "End": 164122}, {"Reply": "Calm down. ", "Didascalie": "", "Start": 164591, "End": 164602}, {"Reply": "Well, when you've quite finished, we should go. ", "Didascalie": "", "Start": 164867, "End": 164936}, {"Reply": "Shit! ", "Didascalie": "", "Start": 165717, "End": 165723}, {"Reply": "Welcome back, hippie. ", "Didascalie": "", "Start": 170000, "End": 170022}, {"Reply": "Do what? ", "Didascalie": "", "Start": 170195, "End": 170204}, {"Reply": "Well, I gave my word.   This is what Gram wanted. ", "Didascalie": "", "Start": 170421, "End": 170496}, {"Reply": "Do you have friends? ", "Didascalie": "", "Start": 170922, "End": 170943}, {"Reply": "Well, what would you do for them? ", "Didascalie": "", "Start": 171122, "End": 171156}, {"Reply": "That's what I hate about people like you. Everything's 'within reason'. There are always boundaries, provisos. You only operate with a safety net. ", "Didascalie": "", "Start": 171375, "End": 171622}, {"Reply": "You've missed the point. See, it doesn't matter what he would do, or what you and your tie-dyed friends think is the correct way to behave. To me, it only matters what I do. Where you have boundaries and limits and thresholds - I only have right and wrong. If I make a promise, I keep it - that's right. If I break that promise - that's wrong. ", "Didascalie": "", "Start": 172130, "End": 172749}, {"Reply": "A hippie hit it.   I thought you'd gone. ", "Didascalie": "", "Start": 178133, "End": 178194}, {"Reply": "What the hell does that mean? ", "Didascalie": "", "Start": 178346, "End": 178376}, {"Reply": "Dolls? ", "Didascalie": "", "Start": 178889, "End": 178896}, {"Reply": "What the hell are you talking about? ", "Didascalie": "", "Start": 179053, "End": 179110}, {"Reply": "Enough of this shit. ", "Didascalie": "", "Start": 179298, "End": 179319}, {"Reply": "They've gotta be in here.    It's fate. ", "Didascalie": "", "Start": 179573, "End": 179638}, {"Reply": "Whatever happened to peace, love and understanding, hippie? ", "Didascalie": "", "Start": 179944, "End": 180029}, {"Reply": "Yup. ", "Didascalie": "", "Start": 180189, "End": 180194}, {"Reply": "I'm going to cremate him, here in the desert where he felt most at home. That's what he wanted. ", "Didascalie": "", "Start": 181427, "End": 181573}, {"Reply": "I know you have to. ", "Didascalie": "", "Start": 181936, "End": 181956}, {"Reply": "It's too late to claim him now. ", "Didascalie": "", "Start": 182426, "End": 182458}, {"Reply": "It means that you were never there when it mattered to Gram. ", "Didascalie": "", "Start": 182698, "End": 182784}, {"Reply": "Not to me, no. ", "Didascalie": "", "Start": 183296, "End": 183311}, {"Reply": "No - he gave it his all, but in a way you could never understand. ", "Didascalie": "", "Start": 183982, "End": 184069}, {"Reply": "It's no good telling me.   You should have told him. ", "Didascalie": "", "Start": 184450, "End": 184524}, {"Reply": "I was both, yes. ", "Didascalie": "", "Start": 184986, "End": 185003}, {"Reply": "Yes.    That's right. ", "Didascalie": "", "Start": 185276, "End": 185298}, {"Reply": "I guess not. ", "Didascalie": "", "Start": 185493, "End": 185506}, {"Reply": "I only failed because I couldn't save him from himself. You failed him all his life. You never believed. I never doubted. ", "Didascalie": "", "Start": 188104, "End": 188289}, {"Reply": "I was his road manager and his friend. We loved it out here in the desert, and we made a pact that whoever died first, the other would come down here and set them free. Gram gave his word and I gave mine. ", "Didascalie": "", "Start": 188527, "End": 188858}, {"Reply": "I don't take drugs. ", "Didascalie": "", "Start": 189177, "End": 189197}, {"Reply": " Nice work. Let's go. ", "Didascalie": "(to Larry)", "Start": 190060, "End": 190107}, {"Reply": "God damn! ", "Didascalie": "", "Start": 190598, "End": 190608}, {"Reply": "Did you call them? ", "Didascalie": "", "Start": 190922, "End": 190941}, {"Reply": "Are you going to call them? ", "Didascalie": "", "Start": 191102, "End": 191130}, {"Reply": "There isn't a reason. If someone tried to steal my son's body, I'd stop them. For sure. ", "Didascalie": "", "Start": 191449, "End": 191587}, {"Reply": "I'm expecting to. ", "Didascalie": "", "Start": 191863, "End": 191881}, {"Reply": "Better make the point. ", "Didascalie": "", "Start": 193718, "End": 193741}, {"Reply": "Are we sure that this is helping? ", "Didascalie": "", "Start": 194292, "End": 194326}, {"Reply": "What's that for? ", "Didascalie": "", "Start": 195775, "End": 195792}, {"Reply": "Did you really take all those drugs? ", "Didascalie": "", "Start": 196230, "End": 196288}, {"Reply": "Just checking. ", "Didascalie": "", "Start": 197201, "End": 197216}, {"Reply": "Are you coming? ", "Didascalie": "", "Start": 197622, "End": 197638}, {"Reply": "Cap Rock. This is perfect. ", "Didascalie": "", "Start": 200976, "End": 201003}, {"Reply": "You wanna give me a hand here? ", "Didascalie": "", "Start": 201500, "End": 201531}, {"Reply": "Sorry, Gram. ", "Didascalie": "", "Start": 201843, "End": 201856}, {"Reply": "Take the top off. ", "Didascalie": "", "Start": 202337, "End": 202355}, {"Reply": "Flesh burns easier than wood. ", "Didascalie": "", "Start": 202515, "End": 202545}, {"Reply": "Right. ", "Didascalie": "", "Start": 203319, "End": 203326}, {"Reply": "Do you think that's enough? ", "Didascalie": "", "Start": 203472, "End": 203500}, {"Reply": "Enough? ", "Didascalie": "", "Start": 203890, "End": 203898}, {"Reply": "Only a little left. ", "Didascalie": "", "Start": 204374, "End": 204394}, {"Reply": "I'm sorry I wasn't there for you when it mattered, but I was there before, and I've been there ever since. Gram, good luck to you, wherever you are. ", "Didascalie": "", "Start": 204619, "End": 204868}, {"Reply": "That's my last one, man. ", "Didascalie": "", "Start": 205175, "End": 205200}, {"Reply": "I think our work here is done. ", "Didascalie": "", "Start": 206862, "End": 206893}, {"Reply": "Go! ", "Didascalie": "", "Start": 207191, "End": 207195}, {"Reply": "Hello, Gram. ", "Didascalie": "", "Start": 209918, "End": 209931}, {"Reply": "Do you think you should? ", "Didascalie": "", "Start": 210279, "End": 210304}, {"Reply": "They're very handy for transporting dead people around. ", "Didascalie": "", "Start": 210654, "End": 210735}, {"Reply": "You're more than dead, Gram. You and the box are down to bones and brass. ", "Didascalie": "", "Start": 210945, "End": 211069}, {"Reply": "What can I do for you, Gram? ", "Didascalie": "", "Start": 211363, "End": 211392}, {"Reply": "Well, you're here. And seeing as I just burned you to a cinder, you shouldn't be. ", "Didascalie": "", "Start": 211573, "End": 211705}, {"Reply": "  99. ", "Didascalie": "(MOR E)", "Start": 211747, "End": 211826}, {"Reply": "What for? ", "Didascalie": "", "Start": 212190, "End": 212200}, {"Reply": "Well, that's okay, Gram.    But I don't need thanking. ", "Didascalie": "", "Start": 212454, "End": 212530}, {"Reply": "I'm just taking care of business. ", "Didascalie": "", "Start": 212680, "End": 212714}, {"Reply": "Actually, I just quit. ", "Didascalie": "", "Start": 212999, "End": 213022}, {"Reply": "Goodbye, Gram. I'm glad it all worked out. ", "Didascalie": "", "Start": 213289, "End": 213353}, {"Reply": "I said I'm glad it all worked out. ", "Didascalie": "", "Start": 213498, "End": 213554}, {"Reply": "Doesn't matter. Can we go now? ", "Didascalie": "", "Start": 214001, "End": 214032}, {"Reply": "Singed my damn mustache, that's for sure. ", "Didascalie": "", "Start": 214906, "End": 214969}, {"Reply": "Yeah.    Let's roll, hippie. ", "Didascalie": "", "Start": 215364, "End": 215393}, {"Reply": "Where d'you think you might be when I'm done? ", "Didascalie": "", "Start": 215603, "End": 215670}, {"Reply": "Yeah, but where? ", "Didascalie": "", "Start": 215941, "End": 215958}]}, {"Character": "NURSE", "Replies": [{"Reply": "You wanna run that by me again, sir? ", "Didascalie": "", "Start": 6506, "End": 6568}, {"Reply": "You want to see Gram Parsons? ", "Didascalie": "", "Start": 6929, "End": 6959}, {"Reply": "So you're not his physician or a close relative? ", "Didascalie": "", "Start": 7840, "End": 7914}, {"Reply": "Mister Parsons is awaiting a post mortem. He will then be delivered to his family. I suggest you speak to them if you wish to pick through his personal effects. Sir. ", "Didascalie": "", "Start": 8100, "End": 8391}, {"Reply": "No, you listen here. Mister Parsons is dead and no longer appears to need a road manager. ", "Didascalie": "", "Start": 8600, "End": 8740}]}, {"Character": "DOCTOR", "Replies": [{"Reply": "Can I help you? ", "Didascalie": "", "Start": 10768, "End": 10784}, {"Reply": "What are you doing? ", "Didascalie": "", "Start": 11005, "End": 11025}, {"Reply": "We don't have a neurology department. ", "Didascalie": "", "Start": 11335, "End": 11398}, {"Reply": "I have the paperwork. ", "Didascalie": "", "Start": 11956, "End": 11978}]}, {"Character": "SUSIE", "Replies": [{"Reply": "Guess who? ", "Didascalie": "", "Start": 13873, "End": 13884}, {"Reply": "God damn!     I'm so sorry, baby. ", "Didascalie": "", "Start": 14833, "End": 14867}, {"Reply": "Would never have happened if you were there. ", "Didascalie": "", "Start": 15026, "End": 15091}, {"Reply": "Well, if you were, you wouldn't have let him die. ", "Didascalie": "", "Start": 15250, "End": 15320}, {"Reply": "This is a remembrance. ", "Didascalie": "", "Start": 17046, "End": 17069}, {"Reply": "Hi. ", "Didascalie": "", "Start": 21189, "End": 21193}, {"Reply": "Phil, you give me laughs and a great time. But I'm not sure if that's enough. ", "Didascalie": "", "Start": 22392, "End": 22520}, {"Reply": "Yes, there's more than that! ", "Didascalie": "", "Start": 22706, "End": 22735}, {"Reply": "I don't mind loving a crazy bastard, Phil. But you've got to be for something and not just against everything. You have to choose something to represent. ", "Didascalie": "", "Start": 23546, "End": 23800}, {"Reply": "Your job is to arrange other people's lives. Maybe it's time to put a little thought into your own. ", "Didascalie": "", "Start": 24073, "End": 24248}, {"Reply": "Who the hell is she? ", "Didascalie": "", "Start": 26276, "End": 26297}, {"Reply": "Girlfriend? Isn't he married? ", "Didascalie": "", "Start": 26544, "End": 26574}, {"Reply": "Why did you let her in? ", "Didascalie": "", "Start": 30814, "End": 30838}, {"Reply": "How can she behave that way? ", "Didascalie": "", "Start": 31035, "End": 31064}, {"Reply": "What? ", "Didascalie": "", "Start": 31261, "End": 31267}, {"Reply": "Don't you freak out on me. ", "Didascalie": "", "Start": 31470, "End": 31497}, {"Reply": "Where are you going? ", "Didascalie": "", "Start": 31863, "End": 31884}, {"Reply": " Phil? ", "Didascalie": "(O.S)", "Start": 35066, "End": 35098}, {"Reply": "What are you doing? ", "Didascalie": "", "Start": 35529, "End": 35549}, {"Reply": "Okay.    Is that a problem? ", "Didascalie": "", "Start": 35734, "End": 35762}, {"Reply": "Well, that's good. ", "Didascalie": "", "Start": 36072, "End": 36091}, {"Reply": "So what are you up to? ", "Didascalie": "", "Start": 36275, "End": 36298}, {"Reply": "I don't know what this madness is, but I'm not getting involved. ", "Didascalie": "", "Start": 36720, "End": 36810}, {"Reply": "I mean, I don't know what it is you're planning, but I'm not bailing you out again. ", "Didascalie": "", "Start": 36987, "End": 37121}, {"Reply": "I'm going. ", "Didascalie": "", "Start": 37287, "End": 37298}, {"Reply": "This time, I'm not coming back. ", "Didascalie": "", "Start": 37642, "End": 37674}, {"Reply": "I'm going to find a man who buys his ties in bulk. ", "Didascalie": "", "Start": 37815, "End": 37891}, {"Reply": "The son of a bitch isn't here. ", "Didascalie": "", "Start": 114440, "End": 114471}, {"Reply": "Stolen Gram? ", "Didascalie": "", "Start": 114693, "End": 114706}, {"Reply": "Why? ", "Didascalie": "", "Start": 115040, "End": 115045}, {"Reply": "Don't be ridiculous. ", "Didascalie": "", "Start": 115420, "End": 115441}, {"Reply": "I didn't ask you. ", "Didascalie": "", "Start": 115735, "End": 115753}, {"Reply": "And you know him? ", "Didascalie": "", "Start": 116370, "End": 116388}, {"Reply": "I don't need to listen to this garbage. ", "Didascalie": "", "Start": 116609, "End": 116674}, {"Reply": "Generally, it's best to answer the phone to discover who's calling. ", "Didascalie": "", "Start": 116986, "End": 117104}, {"Reply": "You don't know shit about him. ", "Didascalie": "", "Start": 120334, "End": 120365}, {"Reply": "If you hate Phil so much, why are you chasing him across California? ", "Didascalie": "", "Start": 142447, "End": 142566}, {"Reply": "Well, that's really touching. ", "Didascalie": "", "Start": 142851, "End": 142881}, {"Reply": "I don't understand. ", "Didascalie": "", "Start": 143414, "End": 143434}, {"Reply": "This is all about money, isn't it? ", "Didascalie": "", "Start": 143649, "End": 143709}, {"Reply": "Why do you think you deserve anything? ", "Didascalie": "", "Start": 143883, "End": 143947}, {"Reply": "Phil's not responsible for your problems with Gram. ", "Didascalie": "", "Start": 144232, "End": 144309}, {"Reply": "I know that he can be a pain in the ass, but when it came to Gram, Phil only ever did the right thing. ", "Didascalie": "", "Start": 144483, "End": 144661}, {"Reply": "Maybe that's what I like about him. ", "Didascalie": "", "Start": 145168, "End": 145225}, {"Reply": "Have you any idea what it's like to really love someone? ", "Didascalie": "", "Start": 145439, "End": 145517}, {"Reply": "I don't have to listen to this. ", "Didascalie": "", "Start": 145864, "End": 145896}, {"Reply": "Okay, you vindictive bitch. I'm going with you to Joshua Tree because my life seems to have been turned upside down and I want to know why. But you don't know me and I won't let you judge me. Do it again and I'll smash that pretty little face of yours off the fucking road. Got it? ", "Didascalie": "", "Start": 146105, "End": 146555}, {"Reply": "You're not a very nice person, are you? ", "Didascalie": "", "Start": 166605, "End": 166665}, {"Reply": "It might get you further. ", "Didascalie": "", "Start": 166910, "End": 166936}, {"Reply": "So what do you want from us? ", "Didascalie": "", "Start": 167344, "End": 167373}, {"Reply": "Why do you hate Phil so much? ", "Didascalie": "", "Start": 167707, "End": 167737}, {"Reply": "Surely Phil was just looking after Gram? ", "Didascalie": "", "Start": 168465, "End": 168526}, {"Reply": "Except that now he's dead. ", "Didascalie": "", "Start": 168857, "End": 168884}, {"Reply": "I don't like you much, Barbara. ", "Didascalie": "", "Start": 169165, "End": 169197}, {"Reply": "Phil?    Phil! ", "Didascalie": "", "Start": 177194, "End": 177209}, {"Reply": "What happened to your head? ", "Didascalie": "", "Start": 177891, "End": 177919}, {"Reply": "Hold that thought. ", "Didascalie": "", "Start": 178261, "End": 178280}, {"Reply": "I need to know what it is you're doing. ", "Didascalie": "", "Start": 178443, "End": 178503}, {"Reply": "Dolls to stick pins in. ", "Didascalie": "", "Start": 178963, "End": 178987}, {"Reply": "I'm with him. ", "Didascalie": "", "Start": 180471, "End": 180485}, {"Reply": "Just do whatever feels right to you. ", "Didascalie": "", "Start": 190469, "End": 190531}, {"Reply": "That's for failing to reinforce my expectations. ", "Didascalie": "", "Start": 195861, "End": 195931}, {"Reply": "I reckon I am. ", "Didascalie": "", "Start": 197736, "End": 197751}, {"Reply": "Some decorum would be nice. ", "Didascalie": "", "Start": 203215, "End": 203243}, {"Reply": "I'm not having a conversation with you about how much gasoline you need to burn a body. ", "Didascalie": "", "Start": 203975, "End": 204113}, {"Reply": "I'll be waiting. ", "Didascalie": "", "Start": 215848, "End": 215865}, {"Reply": "Get out of here.   Finish it. ", "Didascalie": "", "Start": 216139, "End": 216169}]}, {"Character": "GIRL", "Replies": [{"Reply": "  9. ", "Didascalie": "(MOR E)", "Start": 17811, "End": 17892}]}, {"Character": "GIR L", "Replies": [{"Reply": "never laugh again. My inner joy has gone. It evaporated when Gram departed. ", "Didascalie": "", "Start": 17990, "End": 18116}]}, {"Character": "EXPERT", "Replies": [{"Reply": "He sang country music in a way that it had never been sung before. It was 'country rock', if you like. And it was kinda catchy. At least, the young people seemed to lap it up. It's fair to say that when Gram Parsons died, he died a star. ", "Didascalie": "", "Start": 18246, "End": 18659}]}, {"Character": "REPORTER", "Replies": [{"Reply": "And another light burns out in the desert. Gram Parsons - the standard bearer of the new country music movement - is dead, following an overdose of drugs. ", "Didascalie": "", "Start": 19170, "End": 19425}]}, {"Character": "MAN", "Replies": [{"Reply": "Airport, please. ", "Didascalie": "", "Start": 24880, "End": 24897}, {"Reply": "I use it to carry equipment for a band. ", "Didascalie": "", "Start": 43520, "End": 43581}]}, {"Character": "BARBARA", "Replies": [{"Reply": "Don't try and schmooze me, Kaufman, you repellent slimeball. ", "Didascalie": "", "Start": 25505, "End": 25591}, {"Reply": "The latest victim? ", "Didascalie": "", "Start": 25740, "End": 25759}, {"Reply": "It's a lot tidier than I remember. ", "Didascalie": "", "Start": 26085, "End": 26145}, {"Reply": "Welcome to the seventies. ", "Didascalie": "", "Start": 26697, "End": 26723}, {"Reply": "I'm here to fulfill Gram's wishes. ", "Didascalie": "", "Start": 26954, "End": 27014}, {"Reply": "Do you know what this is? ", "Didascalie": "", "Start": 27460, "End": 27486}, {"Reply": "It's Gram's will. ", "Didascalie": "", "Start": 27638, "End": 27656}, {"Reply": "To whom it may concern: I would like it to be known that it is my wish to leave Barbara Mansfield my assets and belongings in the event of my death. Signed: Ingram Cecil Parsons. ", "Didascalie": "", "Start": 27775, "End": 28059}, {"Reply": "Still the jester Kaufman, and still very unfunny. ", "Didascalie": "", "Start": 28402, "End": 28473}, {"Reply": "It's better than a will, actually. It's a signed promise from Gram to leave me all his assets and belongings. And anyway, it's really none of your business what this is. I've come for the guitar. ", "Didascalie": "", "Start": 28666, "End": 28988}, {"Reply": "Yes. Gram's guitar.   He always kept it here. ", "Didascalie": "", "Start": 29178, "End": 29245}, {"Reply": "I don't believe you, Kaufman. ", "Didascalie": "", "Start": 29828, "End": 29858}, {"Reply": "Yes? ", "Didascalie": "", "Start": 56219, "End": 56224}, {"Reply": "I'd like to see the manager, please. ", "Didascalie": "", "Start": 59368, "End": 59430}, {"Reply": "The manager? ", "Didascalie": "", "Start": 60380, "End": 60393}, {"Reply": "It's not a piece of paper. It's a promise from Gram to leave me all his money. ", "Didascalie": "", "Start": 63651, "End": 63780}, {"Reply": "You don't seem to understand. ", "Didascalie": "", "Start": 64771, "End": 64801}, {"Reply": "Please tell me how I'm supposed to get my money. ", "Didascalie": "", "Start": 65225, "End": 65299}, {"Reply": "Are you saying that I'm lying? ", "Didascalie": "", "Start": 65594, "End": 65625}, {"Reply": "Parsons. ", "Didascalie": "", "Start": 97177, "End": 97186}, {"Reply": "Was.   He was a musician. ", "Didascalie": "", "Start": 97444, "End": 97470}, {"Reply": "You might need to repeat that. ", "Didascalie": "", "Start": 110780, "End": 110811}, {"Reply": "Stolen? What the hell do you mean, stolen? Who steals a body? ", "Didascalie": "", "Start": 111077, "End": 111164}, {"Reply": "Where's the son of a bitch? ", "Didascalie": "", "Start": 114346, "End": 114374}, {"Reply": "Well, he's stolen Gram. ", "Didascalie": "", "Start": 114550, "End": 114574}, {"Reply": "They had some kind of weird pact. ", "Didascalie": "", "Start": 114834, "End": 114868}, {"Reply": "Some kind of voodoo thing with hot wax and dolls to stick pins in. ", "Didascalie": "", "Start": 115226, "End": 115343}, {"Reply": "Now that is a wise move, if you ask me. ", "Didascalie": "", "Start": 115593, "End": 115658}, {"Reply": "You'll learn about Phil Kaufman. ", "Didascalie": "", "Start": 116202, "End": 116235}, {"Reply": "I know he's a brainless, interfering asshole, yes. ", "Didascalie": "", "Start": 116456, "End": 116532}, {"Reply": "That's him, isn't it? ", "Didascalie": "", "Start": 116887, "End": 116909}, {"Reply": "Fine. ", "Didascalie": "", "Start": 117343, "End": 117349}, {"Reply": "Sonofabitch! ", "Didascalie": "", "Start": 119684, "End": 119697}, {"Reply": "Okay, honey. Do you want to see who Phil Kaufman really is? Do you want to see what he's capable of? ", "Didascalie": "", "Start": 119868, "End": 120029}, {"Reply": "Or maybe you already know I'm right. ", "Didascalie": "", "Start": 120147, "End": 120204}, {"Reply": "Well why don't we find out? ", "Didascalie": "", "Start": 120434, "End": 120462}, {"Reply": "He's got Gram and I need him. ", "Didascalie": "", "Start": 142645, "End": 142675}, {"Reply": "I know he's dead, Honey. But he hasn't been officially identified, and there's no certificate of death. ", "Didascalie": "", "Start": 143158, "End": 143337}, {"Reply": "Let's just say I'm overly sentimental, okay? ", "Didascalie": "", "Start": 143502, "End": 143572}, {"Reply": "Isn't everything? ", "Didascalie": "", "Start": 143788, "End": 143806}, {"Reply": "I was a great support to Gram before Kaufman came along and spoiled the party. ", "Didascalie": "", "Start": 144026, "End": 144155}, {"Reply": "What do you know? ", "Didascalie": "", "Start": 144388, "End": 144406}, {"Reply": "In his whole life, Phil Kaufman didn't do anything because it was the right thing to do. You can bet the ranch that wherever he is, he's having some fun. ", "Didascalie": "", "Start": 144740, "End": 144994}, {"Reply": "Sure it is, honey. That's why your bags were packed. ", "Didascalie": "", "Start": 145296, "End": 145370}, {"Reply": "You might exclusively love Phil Kaufman - but unfortunately, so does he. You're just handy to have around. ", "Didascalie": "", "Start": 145625, "End": 145795}, {"Reply": "The truth can hurt, can't it? ", "Didascalie": "", "Start": 146702, "End": 146732}, {"Reply": "Nice? No, I suppose not.    Does it matter? ", "Didascalie": "", "Start": 166735, "End": 166799}, {"Reply": "I do okay. Listen, I was an orphan at fourteen and a waitress at fifteen. I do what I do because it puts food on my table, and because if I don't look after myself, no-one else will. ", "Didascalie": "", "Start": 166994, "End": 167277}, {"Reply": "I don't want anything from you. ", "Didascalie": "", "Start": 167442, "End": 167474}, {"Reply": "Gram was the first good guy I ever hooked up with. He wasn't perfect, but it worked between us. We just seemed to fit together. But Gram was already wild, and I made him wilder. ", "Didascalie": "", "Start": 167861, "End": 168139}, {"Reply": "Gram was an adult.   He didn't need a nursemaid. ", "Didascalie": "", "Start": 168706, "End": 168780}, {"Reply": "Yeah. Without my help and while Kaufman was babysitting. ", "Didascalie": "", "Start": 168963, "End": 169045}, {"Reply": "That's fine. I just want what's mine and then I'm gone. Gone real fast. ", "Didascalie": "", "Start": 169266, "End": 169388}, {"Reply": "Where's the catch on this piece of shit? ", "Didascalie": "", "Start": 176987, "End": 177053}, {"Reply": " I want my man back! ", "Didascalie": "(shouts)", "Start": 179191, "End": 179232}, {"Reply": "Hello Stanley. Remember me?     The psychotic girlfriend? ", "Didascalie": "", "Start": 180605, "End": 180688}, {"Reply": "The hell you are, Kaufman. ", "Didascalie": "", "Start": 181652, "End": 181679}, {"Reply": "Can we just cut through this? ", "Didascalie": "", "Start": 186175, "End": 186205}, {"Reply": "You two stole the body. Theft. ", "Didascalie": "", "Start": 186338, "End": 186369}, {"Reply": "Sweetie, I'm sorry, but you seem to be in the whole thing up to your neck. Accessory. ", "Didascalie": "", "Start": 186476, "End": 186604}, {"Reply": "And you are an old fool who should have called the police, but hasn't. Stupidity. ", "Didascalie": "", "Start": 186730, "End": 186854}, {"Reply": "Now, let's just call the cops and get it done. The sooner we get us a death certificate and bury him, the sooner his soul will be properly laid to rest. ", "Didascalie": "", "Start": 186984, "End": 187221}, {"Reply": "Hey! What the hell are you doing? ", "Didascalie": "", "Start": 187407, "End": 187462}, {"Reply": " Bastard! ", "Didascalie": "(O.S)", "Start": 188005, "End": 188036}, {"Reply": " Don't you worry - it's gonna happen! ", "Didascalie": "(O.S)", "Start": 192068, "End": 192156}, {"Reply": "Thank God! ", "Didascalie": "", "Start": 198376, "End": 198387}, {"Reply": "Please help me, they've got my boyfriend's corpse and they're going to perform a ritual with his body. ", "Didascalie": "", "Start": 198860, "End": 199038}, {"Reply": "My driving license? ", "Didascalie": "", "Start": 199336, "End": 199356}, {"Reply": "I've just told you that they've stolen a body and you want to see my driving license? ", "Didascalie": "", "Start": 199526, "End": 199662}, {"Reply": "You people are supposed to be on the lookout for a hearse. A hearse is a big long car. You can usually tell which ones are the hearses, because they have coffins in the back. The one we're looking for is painted yellow. Does this look like a yellow hearse to you, asshole? ", "Didascalie": "", "Start": 199821, "End": 200294}, {"Reply": "Is that a ticket? Are you writing me a ticket? ", "Didascalie": "", "Start": 200505, "End": 200577}, {"Reply": "That'll be Gram Parsons, on fire. ", "Didascalie": "", "Start": 205890, "End": 205924}, {"Reply": " I recognize that birthmark on his shoulder. Look, can I make an observation? ", "Didascalie": "(sarcastically)", "Start": 208081, "End": 208234}, {"Reply": "We're in the desert. It is dark. ", "Didascalie": "", "Start": 208409, "End": 208442}, {"Reply": "No. But I'm really, really keen to find out. ", "Didascalie": "", "Start": 208882, "End": 208952}]}, {"Character": "PHI L", "Replies": [{"Reply": "Gretchen, his wife, took it back six months ago. ", "Didascalie": "", "Start": 29595, "End": 29665}, {"Reply": "So I'm guessing you've got some kind of reason. ", "Didascalie": "", "Start": 211920, "End": 211989}]}, {"Character": "UNDERTAKER", "Replies": [{"Reply": "Afternoon.     Joshua Tree Obsequies. ", "Didascalie": "", "Start": 32409, "End": 32472}, {"Reply": "It's Latin. It means burial. Is there anything I can help with? ", "Didascalie": "", "Start": 33020, "End": 33109}, {"Reply": "Mister Parsons? I'm sorry, I'll take a look immediately. ", "Didascalie": "", "Start": 33680, "End": 33762}, {"Reply": "Yeah, he was here. ", "Didascalie": "", "Start": 34153, "End": 34172}, {"Reply": "New Orleans. Although he only just went, so he'll still be on his way to Los Angeles Airport. ", "Didascalie": "", "Start": 34292, "End": 34436}]}, {"Character": "LARRY", "Replies": [{"Reply": "The door is unlocked. ", "Didascalie": "", "Start": 39531, "End": 39553}, {"Reply": "Yes.   Welcome to my house. ", "Didascalie": "", "Start": 39819, "End": 39847}, {"Reply": "Manomanjari on the sitar by Nikhil Banerjee. ", "Didascalie": "", "Start": 40147, "End": 40212}, {"Reply": " Phil stares at him. ", "Didascalie": "(NB. Similar music may be used in this scene)", "Start": 40306, "End": 40347}, {"Reply": "There's no smoking in here, I'm afraid. ", "Didascalie": "", "Start": 40708, "End": 40773}, {"Reply": "Who are you, please? ", "Didascalie": "", "Start": 41030, "End": 41051}, {"Reply": "And how may I help you, Phil Kaufman? ", "Didascalie": "", "Start": 41226, "End": 41289}, {"Reply": "Why? ", "Didascalie": "", "Start": 41469, "End": 41474}, {"Reply": "Don't you know anyone with a car? ", "Didascalie": "", "Start": 41689, "End": 41723}, {"Reply": "I see. In what way is my car more suitable? ", "Didascalie": "", "Start": 41993, "End": 42062}, {"Reply": "Yes. ", "Didascalie": "", "Start": 42238, "End": 42243}, {"Reply": "And how is a hearse going to be suitable for picking someone up from the airport? ", "Didascalie": "", "Start": 42527, "End": 42651}, {"Reply": "A joke? ", "Didascalie": "", "Start": 42805, "End": 42813}, {"Reply": "Well, okay. Is it two hundred dollars worth of surprise? ", "Didascalie": "", "Start": 43020, "End": 43098}, {"Reply": "I can lend you a bicycle. ", "Didascalie": "", "Start": 43298, "End": 43324}, {"Reply": "  21. ", "Didascalie": "(MOR E)", "Start": 44419, "End": 44497}, {"Reply": "It's a hearse. What else do you need to know? ", "Didascalie": "", "Start": 44977, "End": 45044}, {"Reply": "Meet Bernice. ", "Didascalie": "", "Start": 45503, "End": 45517}, {"Reply": "Bernice is a Cadillac Superior Royale Tiara Limousine Funeral Coach. We've got a Seven gallon V8 engine offering three hundred and forty bhp at four thousand six hundred revolutions per minute. You're looking at a twenty one feet beauty with a one hundred and fifty six inch wheelbase containing a four barrel Rochester Quadrajet carburetor with Turbo Hydramatic transmission. Bernice weighs over six thousand pounds. ", "Didascalie": "", "Start": 45664, "End": 46355}, {"Reply": "Yes, it's yellow.    Bernice comes in yellow. ", "Didascalie": "", "Start": 46557, "End": 46624}, {"Reply": "But they're all black. ", "Didascalie": "", "Start": 46788, "End": 46811}, {"Reply": "So how is a yellow hearse covered with flowers less of a surprise than a black hearse? ", "Didascalie": "", "Start": 47094, "End": 47231}, {"Reply": " No, you paid me a hundred and eighty dollars for a hearse, and a hearse is what you've got. If you take a long, hard look at Bernice, you'll see that she's one of a kind. She's big, she's fast, she's comfortable, and she's beautiful. But she's not black. ", "Didascalie": "(patiently)", "Start": 47475, "End": 47956}, {"Reply": "Why? ", "Didascalie": "", "Start": 48239, "End": 48244}, {"Reply": "Oh, no. She doesn't go anywhere without me. ", "Didascalie": "", "Start": 48468, "End": 48537}, {"Reply": "Someone stole her last summer. ", "Didascalie": "", "Start": 49374, "End": 49405}, {"Reply": "How did you hear of Bernice and me? ", "Didascalie": "", "Start": 49680, "End": 49741}, {"Reply": "What's the matter? ", "Didascalie": "", "Start": 51411, "End": 51430}, {"Reply": "Okay. Well, what time is the flight due? ", "Didascalie": "", "Start": 51797, "End": 51863}, {"Reply": "Okay.   How soon? ", "Didascalie": "", "Start": 52014, "End": 52032}, {"Reply": "Shouldn't we be at arrivals? ", "Didascalie": "", "Start": 52411, "End": 52440}, {"Reply": "Okay. ", "Didascalie": "", "Start": 52667, "End": 52673}, {"Reply": "So how long are we going to wait? ", "Didascalie": "", "Start": 52870, "End": 52904}, {"Reply": "Morning?   What do you mean, morning? ", "Didascalie": "", "Start": 53353, "End": 53412}, {"Reply": "You wait till morning.   I'm going home. ", "Didascalie": "", "Start": 53780, "End": 53842}, {"Reply": "I'm only back because I don't trust you with Bernice. I don't even know you, and if you think I'm going to leave my car with you and just walk away, then you've got another thought on the way. ", "Didascalie": "", "Start": 54227, "End": 54546}, {"Reply": "Hearse? ", "Didascalie": "", "Start": 70210, "End": 70218}, {"Reply": "That hearse? ", "Didascalie": "", "Start": 70479, "End": 70492}, {"Reply": "Doing?    Here? ", "Didascalie": "", "Start": 74152, "End": 74168}, {"Reply": " No. Fair enough. ", "Didascalie": "(miserably)", "Start": 79444, "End": 79482}, {"Reply": "Right.   Good saying. ", "Didascalie": "", "Start": 79776, "End": 79798}, {"Reply": "We're meeting someone off a flight. ", "Didascalie": "", "Start": 80019, "End": 80075}, {"Reply": "Yes. ", "Didascalie": "", "Start": 80265, "End": 80270}, {"Reply": "Going on? ", "Didascalie": "", "Start": 81636, "End": 81646}, {"Reply": "Ignition's a bit temperamental. ", "Didascalie": "", "Start": 86048, "End": 86080}, {"Reply": "Have to use a screwdriver. ", "Didascalie": "", "Start": 86278, "End": 86305}, {"Reply": "Did what?    What did we do? ", "Didascalie": "", "Start": 87060, "End": 87089}, {"Reply": "I don't like them and I don't know what to say to them. They make me feel uneasy. ", "Didascalie": "", "Start": 87699, "End": 87831}, {"Reply": "I clipped it. I clipped the wall. ", "Didascalie": "", "Start": 88667, "End": 88726}, {"Reply": "Uh, not at this time, no sir. ", "Didascalie": "", "Start": 90022, "End": 90052}, {"Reply": "Oh, right.     So it's all my fault? ", "Didascalie": "", "Start": 91319, "End": 91356}, {"Reply": "Well what? ", "Didascalie": "", "Start": 92269, "End": 92280}, {"Reply": "He said to wait. ", "Didascalie": "", "Start": 92446, "End": 92463}, {"Reply": "Get out. ", "Didascalie": "", "Start": 93286, "End": 93295}, {"Reply": "Get out and take your friend with you. ", "Didascalie": "", "Start": 93630, "End": 93690}, {"Reply": "Get out. ", "Didascalie": "", "Start": 94054, "End": 94063}, {"Reply": "Why not? ", "Didascalie": "", "Start": 94298, "End": 94307}, {"Reply": "I'm driving back to the mortuary. ", "Didascalie": "", "Start": 94861, "End": 94895}, {"Reply": "Talk. ", "Didascalie": "", "Start": 95395, "End": 95401}, {"Reply": "Who's the stiff? ", "Didascalie": "", "Start": 95617, "End": 95634}, {"Reply": "Empty? ", "Didascalie": "", "Start": 101374, "End": 101381}, {"Reply": "It looked pretty heavy, for an empty casket. ", "Didascalie": "", "Start": 101567, "End": 101637}, {"Reply": "Okay. So why have we got an empty coffin in the back of the car? ", "Didascalie": "", "Start": 102518, "End": 102633}, {"Reply": "As new? ", "Didascalie": "", "Start": 104888, "End": 104896}, {"Reply": "The whole thing is completely immoral. ", "Didascalie": "", "Start": 105167, "End": 105231}, {"Reply": "Look, I really need to get home. ", "Didascalie": "", "Start": 105566, "End": 105599}, {"Reply": "Gas now. ", "Didascalie": "", "Start": 106300, "End": 106309}, {"Reply": "We could go back. ", "Didascalie": "", "Start": 109081, "End": 109099}, {"Reply": "I wasn't expecting a long trip. ", "Didascalie": "", "Start": 109282, "End": 109314}, {"Reply": "Well, yes. ", "Didascalie": "", "Start": 109696, "End": 109707}, {"Reply": "We could do that. ", "Didascalie": "", "Start": 109935, "End": 109953}, {"Reply": "I still don't fully understand what you do. ", "Didascalie": "", "Start": 111452, "End": 111521}, {"Reply": "Everything? ", "Didascalie": "", "Start": 111686, "End": 111698}, {"Reply": "Oh, one of those.   Like a well- ", "Didascalie": "", "Start": 111972, "End": 112005}, {"Reply": "An executive nanny, not a gopher. ", "Didascalie": "", "Start": 112653, "End": 112687}, {"Reply": "Sunstroke. ", "Didascalie": "", "Start": 120964, "End": 120975}, {"Reply": "I'm susceptible. ", "Didascalie": "", "Start": 121261, "End": 121278}, {"Reply": "This isn't the way to Palm Springs. ", "Didascalie": "", "Start": 121899, "End": 121960}, {"Reply": "See, the Yin is the negative - ", "Didascalie": "", "Start": 124439, "End": 124470}, {"Reply": "The Yin Yang symbol is really evocative about the whole concept. As you travel around the circle, white or black will increase until the opposite color is almost gone. But never totally gone, right? And this cycle then repeats for the opposite color. ", "Didascalie": "", "Start": 124963, "End": 125414}, {"Reply": "I was distracted. ", "Didascalie": "", "Start": 127501, "End": 127519}, {"Reply": "What now? ", "Didascalie": "", "Start": 128609, "End": 128619}, {"Reply": "Okay.   What about? ", "Didascalie": "", "Start": 128981, "End": 129001}, {"Reply": "Ooooh, I'm well. Really well, actually. Thank you. ", "Didascalie": "", "Start": 132033, "End": 132109}, {"Reply": "Oh. ", "Didascalie": "", "Start": 132733, "End": 132737}, {"Reply": "A body?     Stole a body? ", "Didascalie": "", "Start": 133849, "End": 133875}, {"Reply": "That's an empty coffin, officer. ", "Didascalie": "", "Start": 134096, "End": 134129}, {"Reply": "Hearse.   Flowers. ", "Didascalie": "", "Start": 134826, "End": 134845}, {"Reply": "He said a body. He said we stole a body. ", "Didascalie": "", "Start": 135791, "End": 135853}, {"Reply": "He didn't say 'coffin'. He said 'body'. Tell me we haven't stolen a real person. ", "Didascalie": "", "Start": 136051, "End": 136174}, {"Reply": "I'm gonna check inside that box just as soon as we're out of here. ", "Didascalie": "", "Start": 136989, "End": 137106}, {"Reply": "What are we going to do? ", "Didascalie": "", "Start": 137549, "End": 137574}, {"Reply": "What? ", "Didascalie": "", "Start": 137722, "End": 137728}, {"Reply": "What about if I could slip out of these cuffs? ", "Didascalie": "", "Start": 138204, "End": 138276}, {"Reply": "No, really. I really can slip these cuffs. ", "Didascalie": "", "Start": 138769, "End": 138833}, {"Reply": "Do you think we should go? ", "Didascalie": "", "Start": 139248, "End": 139275}, {"Reply": "Oh shit. ", "Didascalie": "", "Start": 139773, "End": 139782}, {"Reply": "The steering lock is on. ", "Didascalie": "", "Start": 140724, "End": 140749}, {"Reply": "I can't - he's got the keys. ", "Didascalie": "", "Start": 140926, "End": 140955}, {"Reply": "Yes. ", "Didascalie": "", "Start": 141251, "End": 141256}, {"Reply": "Okay. ", "Didascalie": "", "Start": 142077, "End": 142083}, {"Reply": "Well, that's it! They're going to lock me up and throw away the key. ", "Didascalie": "", "Start": 147025, "End": 147136}, {"Reply": "You saw what happened. I drove over that cop's bike. That's destruction of police property, or something. ", "Didascalie": "", "Start": 147406, "End": 147587}, {"Reply": "It's a dinosaur. ", "Didascalie": "", "Start": 148177, "End": 148194}, {"Reply": " 'The Polyonax Place'. ", "Didascalie": "(reads)", "Start": 148523, "End": 148571}, {"Reply": " 'Dinoburgers, Reptile Steaks and Primeval Soup. Titanosaurion portions, prehistoric pricing. ", "Didascalie": "(CONT'D) (reads)", "Start": 148855, "End": 149024}, {"Reply": "You surprise me.    I vote we keep going. ", "Didascalie": "", "Start": 149873, "End": 149936}, {"Reply": "I do not. ", "Didascalie": "", "Start": 151616, "End": 151626}, {"Reply": "Look, I'm a vegetarian. I have a problem with dead flesh. Okay? ", "Didascalie": "", "Start": 152278, "End": 152367}, {"Reply": "I thought you were hungry. ", "Didascalie": "", "Start": 153162, "End": 153189}, {"Reply": "Speak to her? ", "Didascalie": "", "Start": 155476, "End": 155490}, {"Reply": "Your girlfriend?      Your wife? ", "Didascalie": "", "Start": 155650, "End": 155683}, {"Reply": "So you didn't? ", "Didascalie": "", "Start": 155864, "End": 155879}, {"Reply": "Maybe she's out.      Shopping, or something. ", "Didascalie": "", "Start": 156178, "End": 156249}, {"Reply": "Haven't finished my drink. ", "Didascalie": "", "Start": 158480, "End": 158507}, {"Reply": "Gram Parsons? ", "Didascalie": "", "Start": 159520, "End": 159534}, {"Reply": "Gram Parsons? Is Gram Parsons dead? ", "Didascalie": "", "Start": 159982, "End": 160043}, {"Reply": "Package?   We've stolen that man's son. ", "Didascalie": "", "Start": 161180, "End": 161245}, {"Reply": "I don't know what you take me for. I want to see in that box. ", "Didascalie": "", "Start": 161695, "End": 161782}, {"Reply": "It's heavy. ", "Didascalie": "", "Start": 162102, "End": 162114}, {"Reply": "I said it's heavy. ", "Didascalie": "", "Start": 162475, "End": 162494}, {"Reply": "Yeah, I remember.    Finest poplar. ", "Didascalie": "", "Start": 162715, "End": 162751}, {"Reply": "Oh my God.     You stole Gram Parsons. ", "Didascalie": "", "Start": 163421, "End": 163481}, {"Reply": "I stole a coffin, I didn't know there was a body in it. ", "Didascalie": "", "Start": 163717, "End": 163794}, {"Reply": "I don't know! What am I doing? ", "Didascalie": "", "Start": 164347, "End": 164378}, {"Reply": "I thought it was bad enough when I ran over the cop's bike, but now I'm a fucking body snatcher. ", "Didascalie": "", "Start": 164671, "End": 164810}, {"Reply": "So why d'ya do it? ", "Didascalie": "", "Start": 170099, "End": 170118}, {"Reply": "Have a guess. ", "Didascalie": "", "Start": 170281, "End": 170295}, {"Reply": "What, cruise around the desert until he starts to smell? Were you - both bombed? ", "Didascalie": "", "Start": 170573, "End": 170704}, {"Reply": "Of course I have friends. ", "Didascalie": "", "Start": 171020, "End": 171046}, {"Reply": "Anything, within reason. ", "Didascalie": "", "Start": 171233, "End": 171258}, {"Reply": "Tell me something - if it was the other way round, would Gram be sitting here, driving your bones out into the desert? ", "Didascalie": "", "Start": 171739, "End": 171933}, {"Reply": "Well? ", "Didascalie": "", "Start": 172059, "End": 172065}, {"Reply": "Ohmygod. ", "Didascalie": "", "Start": 173522, "End": 173531}, {"Reply": "You made me do it, you bastard! ", "Didascalie": "", "Start": 173721, "End": 173753}, {"Reply": "Shit. ", "Didascalie": "", "Start": 174391, "End": 174397}, {"Reply": "Shit.   Shitshitshit. ", "Didascalie": "", "Start": 174672, "End": 174694}, {"Reply": "Hi. ", "Didascalie": "", "Start": 175984, "End": 175988}, {"Reply": "Um. I'm one of the guys that took your son. ", "Didascalie": "", "Start": 176200, "End": 176269}, {"Reply": "Well, I didn't even know he was in the box. ", "Didascalie": "", "Start": 181180, "End": 181249}, {"Reply": "Yes.    Yes I am. ", "Didascalie": "", "Start": 189518, "End": 189536}, {"Reply": "I can't do this.      This isn't right. ", "Didascalie": "", "Start": 190239, "End": 190304}, {"Reply": "Mister Parsons? ", "Didascalie": "", "Start": 192233, "End": 192249}, {"Reply": "I've taken heroin, speed, uppers, downers, blues, morphine, methadone, mushrooms, quaaludes, acid, valium, barbiturates, straight LSD, marijuana, marijuana laced with opium, nembutal, mescalin of course, and medical methaqualone, which made me shake uncontrollably for six weeks and vomit every hour. ", "Didascalie": "", "Start": 192891, "End": 193417}, {"Reply": "Not my point. ", "Didascalie": "", "Start": 193628, "End": 193642}, {"Reply": "I started working my way through that list on June 5th 1969, and since then there hasn't been a day when I didn't at least smoke one joint. ", "Didascalie": "", "Start": 193819, "End": 194059}, {"Reply": "And now I've stopped. I stopped because it seems that I had something more important to do. ", "Didascalie": "", "Start": 194435, "End": 194569}, {"Reply": "He's doing this because he gave his word. I'm prepared to do this now because I think it's right. And because I believe that each body has a soul. And Gram's soul doesn't belong in a family plot surrounded by strangers. It belongs here, where he was happiest. ", "Didascalie": "", "Start": 194713, "End": 195141}, {"Reply": "Of course not. ", "Didascalie": "", "Start": 196357, "End": 196372}, {"Reply": "Yeah, he took the body and stuffed it in the trunk of his car before escaping into the night. ", "Didascalie": "", "Start": 197285, "End": 197442}, {"Reply": "What now? ", "Didascalie": "", "Start": 202063, "End": 202073}, {"Reply": "Why? ", "Didascalie": "", "Start": 202434, "End": 202439}, {"Reply": "I can't believe you just said that. I'm not taking the top off. ", "Didascalie": "", "Start": 202622, "End": 202736}, {"Reply": "Well, I don't know.   Maybe a little more. ", "Didascalie": "", "Start": 203661, "End": 203729}, {"Reply": "I think that'll do it. ", "Didascalie": "", "Start": 204215, "End": 204238}, {"Reply": "Maybe too much fuel. ", "Didascalie": "", "Start": 206467, "End": 206488}, {"Reply": "All what worked out? ", "Didascalie": "", "Start": 213689, "End": 213710}, {"Reply": "Well, we did it.    We saved a soul. ", "Didascalie": "", "Start": 214664, "End": 214722}, {"Reply": "Well, shall we? ", "Didascalie": "", "Start": 215231, "End": 215247}]}, {"Character": "LAR RY", "Replies": [{"Reply": "you're twenty dollars short.   Why should I trust you? ", "Didascalie": "", "Start": 44592, "End": 44668}]}, {"Character": "DRIVER", "Replies": [{"Reply": "Hey, lady! ", "Didascalie": "", "Start": 55934, "End": 55945}]}, {"Character": "STANLEY", "Replies": [{"Reply": "Parsons. ", "Didascalie": "", "Start": 56856, "End": 56865}, {"Reply": "Yes. ", "Didascalie": "", "Start": 57165, "End": 57170}, {"Reply": "That is correct. ", "Didascalie": "", "Start": 57452, "End": 57469}, {"Reply": "Thank you. ", "Didascalie": "", "Start": 57978, "End": 57989}, {"Reply": "I've come to pick up my son's body. ", "Didascalie": "", "Start": 58136, "End": 58197}, {"Reply": "My son died out here, you see? ", "Didascalie": "", "Start": 58417, "End": 58448}, {"Reply": "I'm wondering if that's enough information for you? ", "Didascalie": "", "Start": 58669, "End": 58746}, {"Reply": "Most kind. ", "Didascalie": "", "Start": 59056, "End": 59067}, {"Reply": "I'm sorry? ", "Didascalie": "", "Start": 66821, "End": 66832}, {"Reply": "Stanley Parsons. ", "Didascalie": "", "Start": 67391, "End": 67408}, {"Reply": "Yes.   I suppose so. ", "Didascalie": "", "Start": 67651, "End": 67672}, {"Reply": "Yes. ", "Didascalie": "", "Start": 71310, "End": 71315}, {"Reply": "Right. ", "Didascalie": "", "Start": 71631, "End": 71638}, {"Reply": "I see. ", "Didascalie": "", "Start": 71855, "End": 71862}, {"Reply": "What the hell? ", "Didascalie": "", "Start": 74577, "End": 74592}, {"Reply": "Excuse me. ", "Didascalie": "", "Start": 74743, "End": 74754}, {"Reply": "I need to get off the plane. ", "Didascalie": "", "Start": 75025, "End": 75054}, {"Reply": "Parsons. ", "Didascalie": "", "Start": 96019, "End": 96028}, {"Reply": "What's a Berkeley? ", "Didascalie": "", "Start": 96489, "End": 96508}, {"Reply": "You just gave the body away? ", "Didascalie": "", "Start": 99857, "End": 99886}, {"Reply": "Why did you give it to him? ", "Didascalie": "", "Start": 100229, "End": 100257}, {"Reply": "Who signed for it? ", "Didascalie": "", "Start": 100547, "End": 100566}, {"Reply": "And where do I find this John Nobody? ", "Didascalie": "", "Start": 100849, "End": 100912}, {"Reply": "So where are the cops? ", "Didascalie": "", "Start": 113203, "End": 113226}, {"Reply": "There's supposed to be a funeral in New Orleans. I need to find my boy. ", "Didascalie": "", "Start": 113518, "End": 113640}, {"Reply": "Joshua Tree? ", "Didascalie": "", "Start": 114013, "End": 114026}, {"Reply": "Good afternoon. ", "Didascalie": "", "Start": 122873, "End": 122889}, {"Reply": "I'll take that one, please. ", "Didascalie": "", "Start": 123099, "End": 123127}, {"Reply": "Good afternoon. ", "Didascalie": "", "Start": 153797, "End": 153813}, {"Reply": "Do you have a telephone I might use? ", "Didascalie": "", "Start": 153977, "End": 154039}, {"Reply": "In a minute? ", "Didascalie": "", "Start": 154327, "End": 154340}, {"Reply": "I'd better order, then. ", "Didascalie": "", "Start": 154607, "End": 154631}, {"Reply": " Beer. ", "Didascalie": "(to barman)", "Start": 156709, "End": 156741}, {"Reply": "Would you put a scotch in there, please? ", "Didascalie": "", "Start": 156874, "End": 156940}, {"Reply": "Yeaaaaah.    Yeah, a real bad day. ", "Didascalie": "", "Start": 157305, "End": 157340}, {"Reply": "My boy died out here the other day, and some punks have stolen his body. ", "Didascalie": "", "Start": 157501, "End": 157624}, {"Reply": "Thanks. ", "Didascalie": "", "Start": 158011, "End": 158019}, {"Reply": "Gram Parsons. ", "Didascalie": "", "Start": 159236, "End": 159250}, {"Reply": "Son of a bitch! ", "Didascalie": "", "Start": 166165, "End": 166181}, {"Reply": "Yeah? ", "Didascalie": "", "Start": 175910, "End": 175916}, {"Reply": "Hello. ", "Didascalie": "", "Start": 176069, "End": 176076}, {"Reply": "You'd better come in. ", "Didascalie": "", "Start": 176424, "End": 176446}, {"Reply": "You're Kaufman? ", "Didascalie": "", "Start": 180097, "End": 180113}, {"Reply": "And you are? ", "Didascalie": "", "Start": 180381, "End": 180394}, {"Reply": "Hello Barbara. Nothing wrong with your memory. ", "Didascalie": "", "Start": 180767, "End": 180839}, {"Reply": "Did you sell tickets or something? Now, you boys want to tell me why you stole my son? ", "Didascalie": "", "Start": 180966, "End": 181103}, {"Reply": "You know I can't let you do that? ", "Didascalie": "", "Start": 181826, "End": 181860}, {"Reply": "I don't have to do anything, Mister Kaufman. This is MY loss! ", "Didascalie": "", "Start": 182123, "End": 182210}, {"Reply": "What the hell does that mean? ", "Didascalie": "", "Start": 182537, "End": 182567}, {"Reply": "I don't have to justify my relationship with Gram to you. ", "Didascalie": "", "Start": 183137, "End": 183220}, {"Reply": "It's true that when Gram left college, we drifted apart. ", "Didascalie": "", "Start": 183430, "End": 183512}, {"Reply": "  86. ", "Didascalie": "(MOR E)", "Start": 183554, "End": 183635}, {"Reply": "I kept everything. Every record, every article, every photo. ", "Didascalie": "", "Start": 184300, "End": 184382}, {"Reply": "I loved him. ", "Didascalie": "", "Start": 184595, "End": 184608}, {"Reply": "I understand that you were his right-hand man, as well as his friend? ", "Didascalie": "", "Start": 184806, "End": 184918}, {"Reply": "And that you weren't there when he died? When he needed you most? ", "Didascalie": "", "Start": 185063, "End": 185171}, {"Reply": "So the guilt isn't all mine, then? ", "Didascalie": "", "Start": 185369, "End": 185425}, {"Reply": "You boys took away my son. I lost him once in life, and now you're trying to take him from me again. ", "Didascalie": "", "Start": 185818, "End": 185982}, {"Reply": "Son, you had your chance to look after Gram, and now he's dead. ", "Didascalie": "", "Start": 187653, "End": 187738}, {"Reply": "Okay. You tell me why I should let you take my boy. ", "Didascalie": "", "Start": 188397, "End": 188470}, {"Reply": "You're a couple of druggies.   Why should I believe you? ", "Didascalie": "", "Start": 188977, "End": 189055}, {"Reply": "What about you? Are you a druggie? ", "Didascalie": "", "Start": 189338, "End": 189394}, {"Reply": "No. ", "Didascalie": "", "Start": 191022, "End": 191026}, {"Reply": "Well, you haven't given me a reason not to. ", "Didascalie": "", "Start": 191198, "End": 191267}, {"Reply": "So you are prepared to go to jail? ", "Didascalie": "", "Start": 191727, "End": 191787}, {"Reply": "What is it, son? ", "Didascalie": "", "Start": 192375, "End": 192392}, {"Reply": " That's very impressive, son. ", "Didascalie": "(dryly)", "Start": 193496, "End": 193551}, {"Reply": "I'm going to go say goodbye to my son. ", "Didascalie": "", "Start": 195333, "End": 195393}]}, {"Character": "CHECK-IN CLERK", "Replies": [{"Reply": "You've just arrived from New Orleans, mister Parsons? ", "Didascalie": "", "Start": 57004, "End": 57083}, {"Reply": "And you're flying directly back to New Orleans? On the same plane? ", "Didascalie": "", "Start": 57256, "End": 57373}, {"Reply": "Okay. Well, enjoy your stay at Los Angeles Airport, Mister Parsons. ", "Didascalie": "", "Start": 57667, "End": 57785}]}, {"Character": "CUSTOMER", "Replies": [{"Reply": "Wait your turn. ", "Didascalie": "", "Start": 59510, "End": 59526}]}, {"Character": "CLERK", "Replies": [{"Reply": "Can I help you? ", "Didascalie": "", "Start": 61123, "End": 61139}, {"Reply": "No you're not. ", "Didascalie": "", "Start": 61529, "End": 61544}, {"Reply": "No. You're here to pick up a casket. ", "Didascalie": "", "Start": 61708, "End": 61770}, {"Reply": "What flight number? ", "Didascalie": "", "Start": 61985, "End": 62005}, {"Reply": "You're one of those funny guys, right. ", "Didascalie": "", "Start": 62495, "End": 62559}, {"Reply": "Name? ", "Didascalie": "", "Start": 62741, "End": 62747}, {"Reply": "The deceased. ", "Didascalie": "", "Start": 62916, "End": 62930}, {"Reply": "Barney - bring up Parsons. ", "Didascalie": "", "Start": 63206, "End": 63233}, {"Reply": "Papers? ", "Didascalie": "", "Start": 67848, "End": 67856}, {"Reply": "Well, you'd better tell them that we've got rules. ", "Didascalie": "", "Start": 68247, "End": 68323}, {"Reply": "And this is the exception which proves that particular rule. ", "Didascalie": "", "Start": 68577, "End": 68663}, {"Reply": "Although you don't need to tell them that. ", "Didascalie": "", "Start": 68787, "End": 68855}, {"Reply": "Good luck with her. ", "Didascalie": "", "Start": 69687, "End": 69707}, {"Reply": "And yours is supposed to be male? ", "Didascalie": "", "Start": 72507, "End": 72541}, {"Reply": "We got the wrong box.      Your box is being loaded. ", "Didascalie": "", "Start": 73100, "End": 73178}, {"Reply": "That's very hurtful. ", "Didascalie": "", "Start": 73586, "End": 73607}, {"Reply": "Barney.    You receiving? ", "Didascalie": "", "Start": 73802, "End": 73828}, {"Reply": "What's the hurry? ", "Didascalie": "", "Start": 75631, "End": 75649}, {"Reply": "I thought you were taking him to New Orleans? ", "Didascalie": "", "Start": 76024, "End": 76095}, {"Reply": "Never heard of that. ", "Didascalie": "", "Start": 76915, "End": 76936}, {"Reply": " Hello there. We was looking for you. ", "Didascalie": "(into casket)", "Start": 78345, "End": 78433}, {"Reply": "Need you to sign for it again. ", "Didascalie": "", "Start": 78600, "End": 78631}, {"Reply": "Looks like it's your lucky day after all. ", "Didascalie": "", "Start": 78762, "End": 78829}, {"Reply": "Parsons? ", "Didascalie": "", "Start": 95828, "End": 95837}, {"Reply": "Long blond hair, blue eyes, mid- ", "Didascalie": "", "Start": 96151, "End": 96184}, {"Reply": "Was he in a Berkeley? ", "Didascalie": "", "Start": 96388, "End": 96410}, {"Reply": "A luxury casket of solid mahogany, finished with a split- ", "Didascalie": "", "Start": 96585, "End": 96668}, {"Reply": "Well, it's not like this is a bank. People round here don't generally take dead bodies they're not entitled to. ", "Didascalie": "", "Start": 99963, "End": 100150}, {"Reply": "Well, he signed for it. ", "Didascalie": "", "Start": 100444, "End": 100468}, {"Reply": "John Nobody. ", "Didascalie": "", "Start": 100757, "End": 100770}, {"Reply": "There. ", "Didascalie": "", "Start": 101182, "End": 101189}, {"Reply": "I called them. ", "Didascalie": "", "Start": 113424, "End": 113439}, {"Reply": "New Orleans? ", "Didascalie": "", "Start": 113717, "End": 113730}, {"Reply": "The man said he's going to Joshua Tree, Louisiana. ", "Didascalie": "", "Start": 113858, "End": 113934}]}, {"Character": "BANK MANAGER", "Replies": [{"Reply": "I simply can't give you any money based on this piece of paper. ", "Didascalie": "", "Start": 63437, "End": 63526}, {"Reply": "Well, I'm sorry, but it's highly likely that the estate will go to probate and be divided up accordingly, subject to a valid will existing. ", "Didascalie": "", "Start": 63864, "End": 64104}, {"Reply": "Well I imagine that you first need to prove that mister Parsons is actually dead. ", "Didascalie": "", "Start": 65383, "End": 65515}, {"Reply": "No, absolutely not. But getting a copy of the death certificate would probably be a good first step. ", "Didascalie": "", "Start": 65698, "End": 65874}]}, {"Character": "COP", "Replies": [{"Reply": "Excuse me, sir.    Is that your hearse? ", "Didascalie": "", "Start": 70026, "End": 70091}, {"Reply": "That hearse. ", "Didascalie": "", "Start": 70330, "End": 70343}, {"Reply": "Are you okay, sir? ", "Didascalie": "", "Start": 70620, "End": 70639}, {"Reply": "So, whatcha doin' here? ", "Didascalie": "", "Start": 74060, "End": 74084}, {"Reply": "I don't like the look of you. ", "Didascalie": "", "Start": 79332, "End": 79362}, {"Reply": "Wherever there's a hippie there's a crime, even if it hasn't happened yet. That's what I always say. ", "Didascalie": "", "Start": 79547, "End": 79708}, {"Reply": "So whatcha doing here? ", "Didascalie": "", "Start": 79929, "End": 79952}, {"Reply": "You're meeting someone off a flight? ", "Didascalie": "", "Start": 80140, "End": 80197}, {"Reply": "In a hearse? ", "Didascalie": "", "Start": 80335, "End": 80348}, {"Reply": "Which parts the surprise: The fact that you're in a bright yellow hearse, the fact that you're dressed like something out of a horror film, or the fact that you're half a mile from the terminal and they're gonna have to walk across two runways to reach you? ", "Didascalie": "", "Start": 80509, "End": 80927}, {"Reply": "The first part. ", "Didascalie": "", "Start": 81327, "End": 81343}, {"Reply": "Okay, now why don't you tell me what the hell's going on? ", "Didascalie": "", "Start": 81474, "End": 81557}, {"Reply": "Mornin'. ", "Didascalie": "", "Start": 82797, "End": 82806}, {"Reply": "I guess it does. ", "Didascalie": "", "Start": 83480, "End": 83497}, {"Reply": "Nope.   Sure don't. ", "Didascalie": "", "Start": 83923, "End": 83943}, {"Reply": "Just a moment, boys. ", "Didascalie": "", "Start": 84370, "End": 84391}, {"Reply": "Your sidekick here has just finished telling me that you're gonna pick someone up from the terminal. A surprise, he said. ", "Didascalie": "", "Start": 84579, "End": 84764}, {"Reply": "And you're gonna meet him off his flight with her coffin? ", "Didascalie": "", "Start": 85265, "End": 85344}, {"Reply": "That's a real nice touch. ", "Didascalie": "", "Start": 85568, "End": 85594}, {"Reply": "Right. ", "Didascalie": "", "Start": 86149, "End": 86156}, {"Reply": "I see that. ", "Didascalie": "", "Start": 86372, "End": 86384}, {"Reply": "Are you on drugs, boy? ", "Didascalie": "", "Start": 89880, "End": 89903}, {"Reply": "Not at this time. Okay, well let's see. You just missed a gap of fifty yards and hit a wall in broad daylight. Why was that? ", "Didascalie": "", "Start": 90127, "End": 90327}, {"Reply": "Wait. ", "Didascalie": "", "Start": 91049, "End": 91055}]}, {"Character": "PJ GAMBRELL", "Replies": [{"Reply": "Jes sayin' 'bout the space. ", "Didascalie": "", "Start": 71152, "End": 71180}, {"Reply": "Space ma game, kinda. ", "Didascalie": "", "Start": 71446, "End": 71468}, {"Reply": "Always say. Why have one room? ", "Didascalie": "", "Start": 71711, "End": 71742}, {"Reply": "What's your bidness? ", "Didascalie": "", "Start": 72050, "End": 72071}, {"Reply": "Why? ", "Didascalie": "", "Start": 74840, "End": 74845}, {"Reply": "Sheesh.    Only jes' got settled. ", "Didascalie": "", "Start": 75249, "End": 75283}]}, {"Character": "OFFICIAL", "Replies": [{"Reply": "I'm afraid we have no official notification of death. ", "Didascalie": "", "Start": 97666, "End": 97745}, {"Reply": "At this current time, the Greater Los Angeles registrar of Births, Marriages and Deaths does not regard the local newspaper as an official recorder of record. ", "Didascalie": "", "Start": 98178, "End": 98437}, {"Reply": "Notification of death. ", "Didascalie": "", "Start": 104112, "End": 104135}]}, {"Character": "ATTENDANT", "Replies": [{"Reply": "You an undertaker? ", "Didascalie": "", "Start": 106598, "End": 106617}, {"Reply": "Ain't yer surposed to be in black? ", "Didascalie": "", "Start": 106888, "End": 106948}, {"Reply": "This car runs on regular. ", "Didascalie": "", "Start": 108000, "End": 108026}, {"Reply": "Ain't fer the car? ", "Didascalie": "", "Start": 108482, "End": 108501}]}, {"Character": "START TIME", "Replies": [{"Reply": "LAPSE:  We stay on the old woman and her melon stall as the light rapidly changes, cars and pedestrians whizz by, and an hour passes in moments. ", "Didascalie": "", "Start": 122348, "End": 122533}]}, {"Character": "OLD WOMAN", "Replies": [{"Reply": "Hello. ", "Didascalie": "", "Start": 122970, "End": 122977}, {"Reply": "Fifty cents. ", "Didascalie": "", "Start": 123208, "End": 123221}, {"Reply": "What's it look like? ", "Didascalie": "", "Start": 123628, "End": 123649}, {"Reply": "Was one of 'em sick in them bushes? ", "Didascalie": "", "Start": 123949, "End": 124010}, {"Reply": "Yup.   I seen it. ", "Didascalie": "", "Start": 124243, "End": 124261}]}, {"Character": "MOTORCYCLE COP", "Replies": [{"Reply": "Afternoon. ", "Didascalie": "", "Start": 130495, "End": 130506}, {"Reply": "Oh, it's going fine, thank you. ", "Didascalie": "", "Start": 130854, "End": 130886}, {"Reply": "Well, it is mighty nice around these parts. If you like desert. ", "Didascalie": "", "Start": 131505, "End": 131594}, {"Reply": " And how are things with you today, sir? ", "Didascalie": "(CONT'D) (to Larry)", "Start": 131821, "End": 131912}, {"Reply": "The reason I ask, is that you appear to have driven into one of our road signs. ", "Didascalie": "", "Start": 132319, "End": 132449}, {"Reply": "I'm surprised that you hadn't noticed earlier, as it does appear to be impeding your forward progress. ", "Didascalie": "", "Start": 132815, "End": 132981}, {"Reply": "Thank you. ", "Didascalie": "", "Start": 133260, "End": 133271}, {"Reply": "I wonder if you gentlemen can help me? ", "Didascalie": "", "Start": 133404, "End": 133464}, {"Reply": "I'm looking for some fellows who stole a body back there at the airport. ", "Didascalie": "", "Start": 133626, "End": 133741}, {"Reply": "A body. Rather like the one in the back of your car. ", "Didascalie": "", "Start": 133953, "End": 134027}, {"Reply": "I know it sounds strange. But these guys - there are two of them - they stole a body, loaded it into the back of an old yellow hearse painted with flowers, and they're supposed to be driving out this way. ", "Didascalie": "", "Start": 134385, "End": 134716}, {"Reply": "In the car, please. ", "Didascalie": "", "Start": 135225, "End": 135245}]}, {"Character": "BARMAN", "Replies": [{"Reply": "Out back. ", "Didascalie": "", "Start": 153576, "End": 153586}, {"Reply": "Yup. ", "Didascalie": "", "Start": 153893, "End": 153898}, {"Reply": "In a minute, I do. ", "Didascalie": "", "Start": 154117, "End": 154136}, {"Reply": "Yeah.    Phone's for customers. ", "Didascalie": "", "Start": 154420, "End": 154452}, {"Reply": "Right. ", "Didascalie": "", "Start": 154711, "End": 154718}, {"Reply": "Sure. ", "Didascalie": "", "Start": 157020, "End": 157026}, {"Reply": "Bad day? ", "Didascalie": "", "Start": 157160, "End": 157169}, {"Reply": "What happened? ", "Didascalie": "", "Start": 157407, "End": 157422}, {"Reply": "That's worth a shot on the house. ", "Didascalie": "", "Start": 157823, "End": 157857}, {"Reply": " Why would someone steal a body? ", "Didascalie": "(to Stanley)", "Start": 158593, "End": 158647}, {"Reply": "Who is he? ", "Didascalie": "", "Start": 159119, "End": 159130}, {"Reply": "Gram Parsons? ", "Didascalie": "", "Start": 159358, "End": 159372}]}, {"Character": "STA NLEY", "Replies": [{"Reply": "He was a disappointment to me, because he wouldn't use his brain. He had so much to offer, but he let it trickle away. ", "Didascalie": "", "Start": 183732, "End": 183914}]}, {"Character": "TRAFFIC COP", "Replies": [{"Reply": "Evenin' ma'am. ", "Didascalie": "", "Start": 198716, "End": 198731}, {"Reply": "May I see your driving license please, ma'am? ", "Didascalie": "", "Start": 199197, "End": 199268}, {"Reply": "Please. ", "Didascalie": "", "Start": 199439, "End": 199447}, {"Reply": "Yes it is, ma'am. And yes I am. ", "Didascalie": "", "Start": 200660, "End": 200692}, {"Reply": "Jesus!    What the hell's that? ", "Didascalie": "", "Start": 205798, "End": 205830}, {"Reply": "Get in the car, ma'am.   Now. ", "Didascalie": "", "Start": 205999, "End": 206029}, {"Reply": "How do you know it's your boyfriend? ", "Didascalie": "", "Start": 207921, "End": 207983}, {"Reply": "Be my guest. ", "Didascalie": "", "Start": 208317, "End": 208330}, {"Reply": "Do you want to know what I think, ma'am? ", "Didascalie": "", "Start": 208737, "End": 208803}, {"Reply": "I think it was suicide. He just wanted to get away from you. ", "Didascalie": "", "Start": 209094, "End": 209180}]}, {"Character": "GRAM", "Replies": [{"Reply": "Sure is hot. ", "Didascalie": "", "Start": 209829, "End": 209842}, {"Reply": "Phil. ", "Didascalie": "", "Start": 210009, "End": 210015}, {"Reply": "Not gonna hurt me now, is it? ", "Didascalie": "", "Start": 210380, "End": 210410}, {"Reply": "Nice wheels. Very stylish. ", "Didascalie": "", "Start": 210551, "End": 210578}, {"Reply": "I am dead, then? ", "Didascalie": "", "Start": 210852, "End": 210869}, {"Reply": "Oh, well.    Here's mud in your eye. ", "Didascalie": "", "Start": 211147, "End": 211209}, {"Reply": "You assume I want something. ", "Didascalie": "", "Start": 211468, "End": 211497}, {"Reply": "Well, okay. I just wanted to say thanks. ", "Didascalie": "", "Start": 212057, "End": 212119}, {"Reply": "You don't? ", "Didascalie": "", "Start": 212601, "End": 212612}, {"Reply": "You shooting for a raise? ", "Didascalie": "", "Start": 212905, "End": 212931}, {"Reply": "Well, I s'pose I should be getting along. ", "Didascalie": "", "Start": 213158, "End": 213221}, {"Reply": "What? ", "Didascalie": "", "Start": 213424, "End": 213430}]}]}