{"Title": ["Last Tango in Paris", "   "], "Author": ["\u00a0\u00a0Bernardo Bertolucci\u00a0\u00a0Franco Arcalli"], "Genre": ["\u00a0\u00a0Drama\u00a0\u00a0Romance"], "Characters": [{"Character": "FINAL SHOOTING TRANSCRIPT", "Replies": [{"Reply": "He covers his ears in UTTER DISGUST at the UNBEARABLE NOISE a train makes as it ROARS OVERHEAD. ", "Didascalie": "", "Start": 737, "End": 843}]}, {"Character": "PAUL", "Replies": [{"Reply": " FUCKING GOD!!!! ", "Didascalie": "(ENGLISH)", "Start": 998, "End": 1026}, {"Reply": " Through the door. ", "Didascalie": "(BARELY AUDIBLE)", "Start": 8618, "End": 8648}, {"Reply": "I was already here. ", "Didascalie": "", "Start": 8848, "End": 8868}, {"Reply": "The armchair should go in front of the window. ", "Didascalie": "", "Start": 9329, "End": 9387}, {"Reply": "I don't know. ", "Didascalie": "", "Start": 10160, "End": 10174}, {"Reply": " Hello -- Hello. There's no-one here. There's no-one. I don't know. ", "Didascalie": "(to the caller)", "Start": 11574, "End": 11664}, {"Reply": "I had already decided. But I'm not sure now. Do you like it? ", "Didascalie": "", "Start": 12227, "End": 12299}, {"Reply": "Think fast. ", "Didascalie": "", "Start": 12588, "End": 12600}, {"Reply": "Oh, God. ", "Didascalie": "", "Start": 14194, "End": 14203}, {"Reply": "Turn the tap off now. ", "Didascalie": "", "Start": 22246, "End": 22268}, {"Reply": "Why won't you turn the tap off? ", "Didascalie": "", "Start": 22494, "End": 22526}, {"Reply": "It's not mine. ", "Didascalie": "", "Start": 22805, "End": 22820}, {"Reply": "The armchair goes in front of the window. ", "Didascalie": "", "Start": 27052, "End": 27105}, {"Reply": "Like that. ", "Didascalie": "", "Start": 27268, "End": 27279}, {"Reply": "I don't care about the key. Take your coat off. ", "Didascalie": "", "Start": 27484, "End": 27543}, {"Reply": "Take your coat off and help me. ", "Didascalie": "", "Start": 27709, "End": 27741}, {"Reply": "Get those chairs and bring them here. ", "Didascalie": "", "Start": 27883, "End": 27932}, {"Reply": "Put them on the other side. Take that, too. That's it. ", "Didascalie": "", "Start": 28245, "End": 28311}, {"Reply": "The bed is too big for the room. ", "Didascalie": "", "Start": 29071, "End": 29104}, {"Reply": "I don't have a name. ", "Didascalie": "", "Start": 29273, "End": 29294}, {"Reply": "No, no! I don't. I don't want to know your name. ", "Didascalie": "", "Start": 29458, "End": 29518}, {"Reply": "You don't have a name and I don't have a name either. Not one name. ", "Didascalie": "", "Start": 29684, "End": 29763}, {"Reply": "You and I are gonna meet here without knowing anything that goes on outside here. ", "Didascalie": "", "Start": 30510, "End": 30614}, {"Reply": "OK? ", "Didascalie": "", "Start": 30760, "End": 30764}, {"Reply": "I don't know. Are you scared? ", "Didascalie": "", "Start": 31361, "End": 31391}, {"Reply": "I expected you later. ", "Didascalie": "", "Start": 32540, "End": 32562}, {"Reply": "What are you looking for? ", "Didascalie": "", "Start": 33859, "End": 33885}, {"Reply": "Nothing. I told you, there's nothing, nothing at all. ", "Didascalie": "", "Start": 34091, "End": 34156}, {"Reply": "It's useless to keep on searching. ", "Didascalie": "", "Start": 34539, "End": 34574}, {"Reply": "You need to rest. I think room 12 is free. ", "Didascalie": "", "Start": 34809, "End": 34863}, {"Reply": "I don't know. In the evening. ", "Didascalie": "", "Start": 35771, "End": 35801}, {"Reply": "In one of the rooms. ", "Didascalie": "", "Start": 36967, "End": 36988}, {"Reply": "Ask the Doctors. They're doing the autopsy. ", "Didascalie": "", "Start": 37149, "End": 37204}, {"Reply": "The cards, clothes, relatives, flowers. You've got everything in that suitcase. You didn't forget anything. But I don't want any priests here. ", "Didascalie": "", "Start": 38063, "End": 38250}, {"Reply": "No priests. ", "Didascalie": "", "Start": 38402, "End": 38414}, {"Reply": "Understand? ", "Didascalie": "", "Start": 38571, "End": 38583}, {"Reply": "No!!! ", "Didascalie": "", "Start": 38855, "End": 38861}, {"Reply": "Rosa didn't believe! Nobody believes in the fucking God here! ", "Didascalie": "", "Start": 39011, "End": 39084}, {"Reply": "The priest doesn't want any suicides. The Church doesn't want any suicides, do they? ", "Didascalie": "", "Start": 39406, "End": 39513}, {"Reply": "Heh!? ", "Didascalie": "", "Start": 39766, "End": 39772}, {"Reply": "Why? Why did she commit suicide? ", "Didascalie": "", "Start": 40243, "End": 40276}, {"Reply": "You don't know? You don't know. ", "Didascalie": "", "Start": 40455, "End": 40487}, {"Reply": "Come without touching? OK. ", "Didascalie": "", "Start": 42721, "End": 42748}, {"Reply": "Are you concentrating? Did you come yet? ", "Didascalie": "", "Start": 42955, "End": 43007}, {"Reply": "I didn't either yet. You're not trying hard enough. ", "Didascalie": "", "Start": 43165, "End": 43228}, {"Reply": "A name? Oh, Jesus Christ! Oh, God, I've been called by a million names all my life. I don't want a name. ", "Didascalie": "", "Start": 43535, "End": 43662}, {"Reply": "Yeah. ", "Didascalie": "", "Start": 44123, "End": 44129}, {"Reply": "I didn't get the last name. ", "Didascalie": "", "Start": 44401, "End": 44429}, {"Reply": "All uniforms are bullshit. ", "Didascalie": "", "Start": 61642, "End": 61669}, {"Reply": "Listen, why don't you stop talking about things that don't matter here? What the hell's the difference? ", "Didascalie": "", "Start": 62216, "End": 62353}, {"Reply": "I don't know. Bad memories, I guess. ", "Didascalie": "", "Start": 63387, "End": 63435}, {"Reply": "One time I was all dressed up to go out and take this girl to a basketball game. And I started to go out and my father said, \"You have to milk the cow.\" I said, \"Would you please milk it for me?\" ", "Didascalie": "", "Start": 64383, "End": 64634}, {"Reply": "Yeah. Some. There was a farmer, a very nice guy. Old guy, very poor, and worked real hard. I used to work in a ditch, draining land for farming. And he wore overalls and he smoked a clay pipe. Half the time he wouldn't put tobacco in it. ", "Didascalie": "", "Start": 65193, "End": 65497}, {"Reply": "Oh really? ", "Didascalie": "", "Start": 66908, "End": 66919}, {"Reply": "You think I was telling you the truth? ", "Didascalie": "", "Start": 67119, "End": 67169}, {"Reply": "The better to squeeze a fart out of you! ", "Didascalie": "", "Start": 67995, "End": 68047}, {"Reply": "The better to scratch your ass with. ", "Didascalie": "", "Start": 68273, "End": 68321}, {"Reply": "The better to let your crabs hide in. ", "Didascalie": "", "Start": 68583, "End": 68632}, {"Reply": "Schlong. Wienerwurst. Cazzo. Bitte. ", "Didascalie": "", "Start": 69750, "End": 69786}, {"Reply": "Did you have fun as a kid? ", "Didascalie": "", "Start": 70143, "End": 70170}, {"Reply": "It's beautiful to be made into a tattletale or forced to admire authority or sell yourself for a piece of candy. ", "Didascalie": "", "Start": 70339, "End": 70485}, {"Reply": "No? ", "Didascalie": "", "Start": 70643, "End": 70647}, {"Reply": "Did you ever think about sex? ", "Didascalie": "", "Start": 70894, "End": 70924}, {"Reply": "\"No. No sex.\" ", "Didascalie": "", "Start": 71167, "End": 71181}, {"Reply": "You were probably in love with your teacher. ", "Didascalie": "", "Start": 71401, "End": 71457}, {"Reply": "And she was a lesbian. ", "Didascalie": "", "Start": 71619, "End": 71642}, {"Reply": "No! I'm gonna get a hemorrhoid if you keep telling me names. No names. I don't mind if you tell the truth, but don't give me the names. ", "Didascalie": "", "Start": 72051, "End": 72231}, {"Reply": "Well, go on. Tell the truth. What else? ", "Didascalie": "", "Start": 72383, "End": 72434}, {"Reply": "You mean when he first got into your knickers. ", "Didascalie": "", "Start": 72776, "End": 72834}, {"Reply": "Oh, yeah. Good excuse. What else? ", "Didascalie": "", "Start": 73258, "End": 73292}, {"Reply": "You started grabbing his joint. ", "Didascalie": "", "Start": 73495, "End": 73527}, {"Reply": "Well, he touched you. ", "Didascalie": "", "Start": 73679, "End": 73701}, {"Reply": "Ohhhh. Liar, liar, pants on fire, nose as long as a telephone wire. ", "Didascalie": "", "Start": 73863, "End": 73942}, {"Reply": "Look me straight in the face and say, \"He didn't touch me once.\" ", "Didascalie": "", "Start": 74093, "End": 74169}, {"Reply": "Aha! The way he did it. OK, what did he do? ", "Didascalie": "", "Start": 74461, "End": 74516}, {"Reply": "When did you first come? How old were you? ", "Didascalie": "", "Start": 75185, "End": 75239}, {"Reply": "I came to this hotel a long time ago, to spend one night. And I stayed for five years. ", "Didascalie": "", "Start": 78209, "End": 78318}, {"Reply": "Now, there's all sorts. They can hide, take drugs, play music. ", "Didascalie": "", "Start": 78532, "End": 78606}, {"Reply": "Take your hand away. ", "Didascalie": "", "Start": 78810, "End": 78831}, {"Reply": "Do you want me to make them shut up? OK. I'll make them shut up. ", "Didascalie": "", "Start": 79385, "End": 79461}, {"Reply": "What's the matter, Mother? Are you upset? Don't be. There's nothing to be upset about. It takes so little to make them afraid. I'll tell you what they're afraid of. ", "Didascalie": "", "Start": 79907, "End": 80116}, {"Reply": "They're afraid of the dark. Imagine that! Come on, Mother. Meet my friends. ", "Didascalie": "", "Start": 80268, "End": 80366}, {"Reply": "Say hello, Mom! This is Mom! Oh! ", "Didascalie": "", "Start": 81300, "End": 81333}, {"Reply": "Good evening, Marcel. ", "Didascalie": "", "Start": 82438, "End": 82460}, {"Reply": "Do you like him? He was Rosa's lover. ", "Didascalie": "", "Start": 82902, "End": 82951}, {"Reply": "I think you're a what? A what? A wore? ", "Didascalie": "", "Start": 84347, "End": 84397}, {"Reply": "You mean whore. ", "Didascalie": "", "Start": 84543, "End": 84559}, {"Reply": "Why were you going through my pockets? ", "Didascalie": "", "Start": 85070, "End": 85120}, {"Reply": "To find out OOH you are. ", "Didascalie": "", "Start": 85369, "End": 85394}, {"Reply": "Well, if you look real close, you'll see me hiding behind my zipper. ", "Didascalie": "", "Start": 85537, "End": 85628}, {"Reply": "That's not a beginning, that's a finish. ", "Didascalie": "", "Start": 85855, "End": 85907}, {"Reply": "I'll be 93 this weekend. ", "Didascalie": "", "Start": 86100, "End": 86125}, {"Reply": "Thank you. ", "Didascalie": "", "Start": 86286, "End": 86297}, {"Reply": "Are you telling me that I look like a barber? ", "Didascalie": "", "Start": 86994, "End": 87051}, {"Reply": "That's a barber's razor. ", "Didascalie": "", "Start": 87281, "End": 87306}, {"Reply": "Or a madmans. ", "Didascalie": "", "Start": 87466, "End": 87480}, {"Reply": "No. That would be like writing my name on your face. ", "Didascalie": "", "Start": 87706, "End": 87770}, {"Reply": "Slaves are branded on the ass and I want you free. ", "Didascalie": "", "Start": 87932, "End": 87994}, {"Reply": "Oh, really? ", "Didascalie": "", "Start": 88370, "End": 88382}, {"Reply": "I know it's tough but you're gonna have to bear it. ", "Didascalie": "", "Start": 89246, "End": 89309}, {"Reply": "You know, these sinks are really beautiful. They're very rare, you don't find them any more. I think it's these sinks that let you stay together. ", "Didascalie": "", "Start": 89547, "End": 89737}, {"Reply": "Hmm? Don't you think? ", "Didascalie": "", "Start": 89875, "End": 89897}, {"Reply": "What's that? What's all this? ", "Didascalie": "", "Start": 90042, "End": 90072}, {"Reply": "Mad? ", "Didascalie": "", "Start": 90190, "End": 90195}, {"Reply": "Mad? Mad? Mad? ", "Didascalie": "", "Start": 90402, "End": 90417}, {"Reply": "I think I'm happy with you. ", "Didascalie": "", "Start": 90591, "End": 90619}, {"Reply": "You wanted to talk to me. Go on, then. You know I haven't come to cry with you? ", "Didascalie": "", "Start": 94723, "End": 94825}, {"Reply": "Our bathrobes? You can't tell me anything I don't already know. ", "Didascalie": "", "Start": 95371, "End": 95446}, {"Reply": "Yes, yes, yes. ", "Didascalie": "", "Start": 95611, "End": 95626}, {"Reply": "Your meticulous. I've always wondered why you save newspaper clippings. Is it work? Or a hobby? ", "Didascalie": "", "Start": 95853, "End": 95971}, {"Reply": "Oh, so it's serious. It's a job that makes you read? Very educational. ", "Didascalie": "", "Start": 96217, "End": 96310}, {"Reply": "Marcello, I know everything. ", "Didascalie": "", "Start": 96837, "End": 96866}, {"Reply": "Would you like a shot of bourbon? ", "Didascalie": "", "Start": 97243, "End": 97277}, {"Reply": "Was that a present from Rosa, too? ", "Didascalie": "", "Start": 97678, "End": 97713}, {"Reply": "Together? ", "Didascalie": "", "Start": 98339, "End": 98349}, {"Reply": "Our room is painted white. Rosa wanted it to be different from the other rooms in the hotel. ", "Didascalie": "", "Start": 99356, "End": 99471}, {"Reply": "You've still got all your hair. ", "Didascalie": "", "Start": 100408, "End": 100440}, {"Reply": "Don't you have massages? ", "Didascalie": "", "Start": 100711, "End": 100736}, {"Reply": "You're in good shape. ", "Didascalie": "", "Start": 100924, "End": 100946}, {"Reply": "Tell me! ", "Didascalie": "", "Start": 101577, "End": 101586}, {"Reply": " Really, Marcello, I wonder what she ever saw in you. ", "Didascalie": "(ENGLISH)", "Start": 102592, "End": 102668}, {"Reply": "Go get the butter. ", "Didascalie": "", "Start": 104157, "End": 104176}, {"Reply": "Go get the butter. ", "Didascalie": "", "Start": 104364, "End": 104383}, {"Reply": "Yeah. That's a hiding place. ", "Didascalie": "", "Start": 105642, "End": 105671}, {"Reply": "Why not? ", "Didascalie": "", "Start": 106008, "End": 106017}, {"Reply": "What about that? Can I open that? ", "Didascalie": "", "Start": 106245, "End": 106279}, {"Reply": "Huh? Wait a minute. Maybe there's jewels in it. ", "Didascalie": "", "Start": 106430, "End": 106489}, {"Reply": "Maybe there's gold. ", "Didascalie": "", "Start": 106605, "End": 106625}, {"Reply": "Are you afraid? ", "Didascalie": "", "Start": 106778, "End": 106794}, {"Reply": "No? ", "Didascalie": "", "Start": 106936, "End": 106940}, {"Reply": "You're always afraid. ", "Didascalie": "", "Start": 107093, "End": 107115}, {"Reply": "Family secrets? ", "Didascalie": "", "Start": 107474, "End": 107490}, {"Reply": "I'll tell you about family secrets. ", "Didascalie": "", "Start": 107641, "End": 107677}, {"Reply": "I'm gonna tell you about the family. ", "Didascalie": "", "Start": 107902, "End": 107950}, {"Reply": "That holy institution meant to breed virtue in savages. ", "Didascalie": "", "Start": 108147, "End": 108214}, {"Reply": "I want you to repeat it after me. ", "Didascalie": "", "Start": 108378, "End": 108412}, {"Reply": "Repeat it. Say, \"Holy family.\" ", "Didascalie": "", "Start": 108630, "End": 108661}, {"Reply": "Go on. Holy family. Church of good citizens. ", "Didascalie": "", "Start": 108881, "End": 108937}, {"Reply": "Good citizens. ", "Didascalie": "", "Start": 109178, "End": 109193}, {"Reply": "Say it. Say it! The children are tortured until they tell their first lie. ", "Didascalie": "", "Start": 109508, "End": 109605}, {"Reply": "Where the will is broken by repression. ", "Didascalie": "", "Start": 109830, "End": 109881}, {"Reply": "Huh? ", "Didascalie": "", "Start": 112477, "End": 112482}, {"Reply": "What? ", "Didascalie": "", "Start": 112690, "End": 112696}, {"Reply": "That's good. I like surprises. ", "Didascalie": "", "Start": 112938, "End": 112969}, {"Reply": "What is it? ", "Didascalie": "", "Start": 113206, "End": 113218}, {"Reply": "Do you enjoy that? ", "Didascalie": "", "Start": 113596, "End": 113615}, {"Reply": "Voil\u00c3\u00a0! ", "Didascalie": "", "Start": 131818, "End": 131826}, {"Reply": "Oh, there once was a man And he had an old sow ow! Hi-diddle- ", "Didascalie": "", "Start": 132014, "End": 132087}, {"Reply": "You're wet. ", "Didascalie": "", "Start": 132259, "End": 132271}, {"Reply": "What the hell? ", "Didascalie": "", "Start": 132662, "End": 132677}, {"Reply": "A rat. Only a rat. ", "Didascalie": "", "Start": 132982, "End": 133001}, {"Reply": "There are more rats in Paris than people. Yum, yum, yum. ", "Didascalie": "", "Start": 133191, "End": 133259}, {"Reply": "Wait, wait! Don't you want a bite first? You don't want to run and eat. ", "Didascalie": "", "Start": 133635, "End": 133729}, {"Reply": "What's the matter? You don't dig rat? ", "Didascalie": "", "Start": 134448, "End": 134497}, {"Reply": "Well, we'll fuck on the radiator or standing on the mantel. ", "Didascalie": "", "Start": 134747, "End": 134818}, {"Reply": "Listen, I gotta get some mayonnaise for this. Because, it really is good with mayonnaise. ", "Didascalie": "", "Start": 134999, "End": 135111}, {"Reply": "I'll save the asshole for you. ", "Didascalie": "", "Start": 135272, "End": 135303}, {"Reply": "Quo vadis, baby? ", "Didascalie": "", "Start": 136308, "End": 136325}, {"Reply": "Oh, isn't that wonderful? You know, you're going to have to get out of these wet duds. ", "Didascalie": "", "Start": 136536, "End": 136645}, {"Reply": "And then you know what happens? You get pneumonia, then you know what happens? You die. And then, you know what happens when you die? ", "Didascalie": "", "Start": 137441, "End": 137608}, {"Reply": "Give me the soap. ", "Didascalie": "", "Start": 138103, "End": 138121}, {"Reply": "You're in love? ", "Didascalie": "", "Start": 138292, "End": 138308}, {"Reply": "How delightful. ", "Didascalie": "", "Start": 138457, "End": 138473}, {"Reply": "Fat, is it? How unkind. ", "Didascalie": "", "Start": 139354, "End": 139378}, {"Reply": "In ten years, you'll be playing soccer with your tits. ", "Didascalie": "", "Start": 139684, "End": 139750}, {"Reply": "What do you think of that? You know what I'm gonna be doing? ", "Didascalie": "", "Start": 139891, "End": 139963}, {"Reply": "OK. oblesse oblige. ", "Didascalie": "", "Start": 140473, "End": 140493}, {"Reply": "Oh, really? That's wonderful. Is he a good fucker? ", "Didascalie": "", "Start": 140898, "End": 140960}, {"Reply": "You know, you're a jerk. Cos the best fucking you're gonna get is right here in this apartment. ", "Didascalie": "", "Start": 141199, "End": 141317}, {"Reply": "Give me the soap. Listen, you dumb dodo. All the mysteries that you're ever gonna know in life are right here. ", "Didascalie": "", "Start": 141566, "End": 141710}, {"Reply": "You mean, like everybody. ", "Didascalie": "", "Start": 141953, "End": 141979}, {"Reply": "What is he, your local pimp? ", "Didascalie": "", "Start": 142182, "End": 142211}, {"Reply": "I can't wait. ", "Didascalie": "", "Start": 142462, "End": 142476}, {"Reply": "You want this man you love to protect and take care of you. ", "Didascalie": "", "Start": 142774, "End": 142845}, {"Reply": "Well, you'll never find it. ", "Didascalie": "", "Start": 143443, "End": 143471}, {"Reply": "No, you're alone. You're all alone. ", "Didascalie": "", "Start": 144256, "End": 144292}, {"Reply": "Get me the scissors. ", "Didascalie": "", "Start": 145032, "End": 145053}, {"Reply": "Get me the fingernail scissors. ", "Didascalie": "", "Start": 145197, "End": 145229}, {"Reply": "No. I want you to cut the fingernails on your right hand, these two. ", "Didascalie": "", "Start": 145394, "End": 145485}, {"Reply": "I want you to put your fingers up my ass. ", "Didascalie": "", "Start": 145742, "End": 145795}, {"Reply": "I want the pig to vomit in your face and I want you to swallow the vomit. Are you gonna do that for me? ", "Didascalie": "", "Start": 146187, "End": 146324}, {"Reply": "Huh? ", "Didascalie": "", "Start": 146468, "End": 146473}, {"Reply": "You look ridiculous in that make- ", "Didascalie": "", "Start": 147515, "End": 147549}, {"Reply": "Oh Christ! There are too many fucking flowers in this place. I can't breathe. You know on the top of the closet? ", "Didascalie": "", "Start": 147958, "End": 148104}, {"Reply": " 78. ", "Didascalie": "(CONT'D) (MORE)", "Start": 148136, "End": 148152}, {"Reply": "Go on, tell me something! Smile, you cunt! ", "Didascalie": "", "Start": 150605, "End": 150659}, {"Reply": "What? ", "Didascalie": "", "Start": 151797, "End": 151803}, {"Reply": " I have to go. I have to go, sweetheart, baby. Somebody's calling me. ", "Didascalie": "(back to ROSA)", "Start": 152036, "End": 152139}, {"Reply": "Yeah. I'm coming. ", "Didascalie": "", "Start": 152397, "End": 152415}, {"Reply": "It's four in the morning. ", "Didascalie": "", "Start": 153013, "End": 153039}, {"Reply": "We're full. ", "Didascalie": "", "Start": 153355, "End": 153367}, {"Reply": "I'm very sorry. ", "Didascalie": "", "Start": 154285, "End": 154301}, {"Reply": "Come. Come with me. ", "Didascalie": "", "Start": 155817, "End": 155837}, {"Reply": "Get the fuck out of here! ", "Didascalie": "", "Start": 156409, "End": 156435}, {"Reply": "Faggot! ", "Didascalie": "", "Start": 156607, "End": 156615}, {"Reply": "It's me again. ", "Didascalie": "", "Start": 168614, "End": 168629}, {"Reply": "It's over, then it begins again. ", "Didascalie": "", "Start": 169027, "End": 169060}, {"Reply": "There's nothing to understand. We left the apartment. Now we begin again with love and all the rest of it. ", "Didascalie": "", "Start": 169266, "End": 169406}, {"Reply": "Yeah, listen. ", "Didascalie": "", "Start": 169554, "End": 169568}, {"Reply": "I'm 45. I'm a widower. I've got a little hotel, a kind of a dump. But it's not completely a flophouse. ", "Didascalie": "", "Start": 169765, "End": 169890}, {"Reply": "I'm awfully sorry to intrude but I was so struck with your beauty that I thought I could offer you a glass of champagne. Is this seat taken? ", "Didascalie": "", "Start": 171752, "End": 171937}, {"Reply": "May I? ", "Didascalie": "", "Start": 172120, "End": 172127}, {"Reply": "Garcon! ", "Didascalie": "", "Start": 172362, "End": 172370}, {"Reply": "You know, the tango is a, is a rite. Do you understand \"rite\"? And you must watch the legs of the dancers. ", "Didascalie": "", "Start": 172504, "End": 172644}, {"Reply": "Oh, no! You haven't drunk your champagne because it was warm. And then I ordered you a Scotch and you haven't drunk your Scotch. ", "Didascalie": "", "Start": 173086, "End": 173248}, {"Reply": "Come on. Just a sip for Daddy. ", "Didascalie": "", "Start": 173544, "End": 173575}, {"Reply": "Now, if you love me, you'll drink all of it. ", "Didascalie": "", "Start": 173734, "End": 173790}, {"Reply": "Bravo! ", "Didascalie": "", "Start": 174040, "End": 174047}, {"Reply": "Let's talk about us. ", "Didascalie": "", "Start": 174210, "End": 174231}, {"Reply": "Yes, but I'm here, aren't I? ", "Didascalie": "", "Start": 174455, "End": 174484}, {"Reply": "That's rather nasty. Anyway, you dummy, I love you. And I want to live with you. ", "Didascalie": "", "Start": 174712, "End": 174815}, {"Reply": "In my flophouse. What the hell does that mean? What the hell difference does it make if I have a flophouse or a hotel or a castle? I love you. ", "Didascalie": "", "Start": 174998, "End": 175174}, {"Reply": "Oh, I thought you weren't drinking. ", "Didascalie": "", "Start": 176409, "End": 176445}, {"Reply": "All right. I think that's a good idea. ", "Didascalie": "", "Start": 176642, "End": 176692}, {"Reply": "Wait a minute. Because you're really beautiful. Wait a minute. ", "Didascalie": "", "Start": 176898, "End": 176972}, {"Reply": "No! Fuck all that! Come on. No. ", "Didascalie": "", "Start": 177331, "End": 177363}, {"Reply": "Cows. ", "Didascalie": "", "Start": 178049, "End": 178055}, {"Reply": "What do you mean you hate the country? ", "Didascalie": "", "Start": 178516, "End": 178566}, {"Reply": "No. Let's dance. Come on. Don't you wanna dance? We can start again. ", "Didascalie": "", "Start": 178802, "End": 178882}, {"Reply": "Madame! 'Tis ever love. ", "Didascalie": "", "Start": 179856, "End": 179880}, {"Reply": "Kiss me, sweetheart! ", "Didascalie": "", "Start": 180754, "End": 180775}, {"Reply": "Farewell, you sweet peach blossom. ", "Didascalie": "", "Start": 181010, "End": 181045}, {"Reply": "I could dance for ever. Oh, my hemorrhoid! ", "Didascalie": "", "Start": 181206, "End": 181260}, {"Reply": "Beauty of mine, sit before me. Let me peruse you and remember you always like this. ", "Didascalie": "", "Start": 181456, "End": 181562}, {"Reply": "Garcon! Champagne! If music be the food of love, play on. ", "Didascalie": "", "Start": 181953, "End": 182022}, {"Reply": "What's the matter with you? ", "Didascalie": "", "Start": 182161, "End": 182189}, {"Reply": "What's the matter with you? ", "Didascalie": "", "Start": 182432, "End": 182460}, {"Reply": "What's finished? ", "Didascalie": "", "Start": 182691, "End": 182708}, {"Reply": "That's ridiculous. ", "Didascalie": "", "Start": 182907, "End": 182926}, {"Reply": "That's ridiculous! ", "Didascalie": "", "Start": 183063, "End": 183082}, {"Reply": "Oh, you dirty rat! ", "Didascalie": "", "Start": 183237, "End": 183256}, {"Reply": "Look, when something's finished, it begins again. ", "Didascalie": "", "Start": 183409, "End": 183470}, {"Reply": "Oh, Jesus. Listen, that's not a subway strap, that's me cock! ", "Didascalie": "", "Start": 183806, "End": 183879}, {"Reply": "Shit! Wait a minute. Goddamn it! ", "Didascalie": "", "Start": 184604, "End": 184637}, {"Reply": "Hey, rube! Come here! Come here! ", "Didascalie": "", "Start": 184808, "End": 184841}, {"Reply": "Come heeeeeeeeeerrrrrrrrreeeeee! ", "Didascalie": "", "Start": 184957, "End": 184990}, {"Reply": "I'm gonna get you! Bimbo! ", "Didascalie": "", "Start": 185224, "End": 185250}, {"Reply": "Hold it! ", "Didascalie": "", "Start": 186288, "End": 186297}, {"Reply": "Hey, cool it! ", "Didascalie": "", "Start": 186568, "End": 186582}, {"Reply": "I can't win. Give me a break! ", "Didascalie": "", "Start": 187207, "End": 187237}, {"Reply": "Aha! I smell the henhouse. ", "Didascalie": "", "Start": 187822, "End": 187849}, {"Reply": "Well, shit, I'm not in your way. ", "Didascalie": "", "Start": 188022, "End": 188055}, {"Reply": "After you, mademoiselle! ", "Didascalie": "", "Start": 188220, "End": 188245}, {"Reply": "So long, sister. Besides, you're a crummy-looking broad. I don't give a damn if I never see you again. ", "Didascalie": "", "Start": 188407, "End": 188532}, {"Reply": "Oh, fuck the police. ", "Didascalie": "", "Start": 189147, "End": 189168}, {"Reply": "Oh, man! ", "Didascalie": "", "Start": 190539, "End": 190548}, {"Reply": "This is getting ridiculous. ", "Didascalie": "", "Start": 191012, "End": 191040}, {"Reply": "It's the title shot, baby. We're going all the way. Oh, Christ. ", "Didascalie": "", "Start": 191508, "End": 191583}, {"Reply": "It's a little old, but full of memories, huh? ", "Didascalie": "", "Start": 191989, "End": 192046}, {"Reply": "How do you like your hero? Over easy or sunny-side up? ", "Didascalie": "", "Start": 192677, "End": 192743}, {"Reply": "You ran through Africa and Asia and Indonesia. ", "Didascalie": "", "Start": 192893, "End": 192951}, {"Reply": "And now I've found you. And I love you. ", "Didascalie": "", "Start": 193094, "End": 193145}, {"Reply": "I wanna know your name. ", "Didascalie": "", "Start": 193354, "End": 193378}, {"Reply": "Our children. ", "Didascalie": "", "Start": 193912, "End": 193926}, {"Reply": "Our children. ", "Didascalie": "", "Start": 194094, "End": 194108}]}, {"Character": "JEANNE", "Replies": [{"Reply": "A phone token, please. ", "Didascalie": "", "Start": 2855, "End": 2878}, {"Reply": "Thank you. ", "Didascalie": "", "Start": 3057, "End": 3068}, {"Reply": "Mama? Yes, it's Jeanne. I've found a flat to rent in Passy. I'm going to see it. ", "Didascalie": "", "Start": 3796, "End": 3899}, {"Reply": "Then I've got to go to the station to met Tom. I promised him. OK, see you later. Bye! ", "Didascalie": "", "Start": 4109, "End": 4218}, {"Reply": "I've come to see the flat. I saw the sign. ", "Didascalie": "", "Start": 4591, "End": 4645}, {"Reply": "Yes. ", "Didascalie": "", "Start": 4838, "End": 4843}, {"Reply": "I'd like to see it. ", "Didascalie": "", "Start": 5128, "End": 5148}, {"Reply": "I don't know yet! ", "Didascalie": "", "Start": 5312, "End": 5330}, {"Reply": "Let go of me! ", "Didascalie": "", "Start": 7191, "End": 7205}, {"Reply": "She's crazy! ", "Didascalie": "", "Start": 7396, "End": 7409}, {"Reply": "Who are you? ", "Didascalie": "", "Start": 8097, "End": 8110}, {"Reply": "You gave me a fright. ", "Didascalie": "", "Start": 8238, "End": 8260}, {"Reply": "How did you get in? ", "Didascalie": "", "Start": 8388, "End": 8408}, {"Reply": "Oh yes, I left it open. I didn't hear you come in. ", "Didascalie": "", "Start": 8718, "End": 8780}, {"Reply": "Sorry? Oh it was you who took it. I had to bribe the concierge. These old houses are fascinating. ", "Didascalie": "", "Start": 8938, "End": 9058}, {"Reply": "An armchair by the fireplace would look good. ", "Didascalie": "", "Start": 9204, "End": 9261}, {"Reply": "Are you American? You've got an American accent. ", "Didascalie": "", "Start": 9457, "End": 9517}, {"Reply": "Are you going to take it? Are you? ", "Didascalie": "", "Start": 10057, "End": 10092}, {"Reply": "What are you doing? ", "Didascalie": "", "Start": 10477, "End": 10497}, {"Reply": "So you're going to take it? You've decided? ", "Didascalie": "", "Start": 12104, "End": 12159}, {"Reply": "I don't know. I shall have to think about it. ", "Didascalie": "", "Start": 12463, "End": 12520}, {"Reply": "I thought you'd left. ", "Didascalie": "", "Start": 13028, "End": 13050}, {"Reply": "Have they taken us for someone else? ", "Didascalie": "", "Start": 15803, "End": 15851}, {"Reply": "What's going on? Do you know them? ", "Didascalie": "", "Start": 16501, "End": 16536}, {"Reply": "You're mad! You might have asked me first. ", "Didascalie": "", "Start": 16887, "End": 16941}, {"Reply": "So you kissed me, and you knew it was being filmed. You're a bastard! ", "Didascalie": "", "Start": 17404, "End": 17485}, {"Reply": "I thought of you day and night, and I cried. Darling, I can't live without you! ", "Didascalie": "", "Start": 17765, "End": 17867}, {"Reply": "You could have rung the bell. ", "Didascalie": "", "Start": 24803, "End": 24833}, {"Reply": "In front of the fireplace. ", "Didascalie": "", "Start": 25209, "End": 25236}, {"Reply": "There. ", "Didascalie": "", "Start": 25543, "End": 25550}, {"Reply": "How do I know? He'll decide. ", "Didascalie": "", "Start": 25844, "End": 25873}, {"Reply": "It won't fit! ", "Didascalie": "", "Start": 26153, "End": 26167}, {"Reply": "What a mess! ", "Didascalie": "", "Start": 26481, "End": 26494}, {"Reply": "But I only came to return the key. ", "Didascalie": "", "Start": 27349, "End": 27384}, {"Reply": "OK. ", "Didascalie": "", "Start": 27811, "End": 27815}, {"Reply": "Listen monsieur! I've got to go. ", "Didascalie": "", "Start": 28607, "End": 28640}, {"Reply": "Look, sir! I've got to go! ", "Didascalie": "", "Start": 28775, "End": 28802}, {"Reply": "I don't know what to call you. ", "Didascalie": "", "Start": 29174, "End": 29205}, {"Reply": "Do you want to know mine? ", "Didascalie": "", "Start": 29364, "End": 29390}, {"Reply": "You're crazy! ", "Didascalie": "", "Start": 29901, "End": 29915}, {"Reply": "You scare me. ", "Didascalie": "", "Start": 30327, "End": 30341}, {"Reply": "But why? ", "Didascalie": "", "Start": 30834, "End": 30843}, {"Reply": "But I can't. Can you? ", "Didascalie": "", "Start": 31271, "End": 31293}, {"Reply": "No. ", "Didascalie": "", "Start": 31461, "End": 31465}, {"Reply": "Come? ", "Didascalie": "", "Start": 31630, "End": 31636}, {"Reply": "It's beautiful without knowing anything. ", "Didascalie": "", "Start": 42394, "End": 42446}, {"Reply": "No. It's difficult! ", "Didascalie": "", "Start": 43103, "End": 43123}, {"Reply": "I shall have to invent a name for you. ", "Didascalie": "", "Start": 43417, "End": 43467}, {"Reply": "It's so masculine. ", "Didascalie": "", "Start": 44036, "End": 44055}, {"Reply": "Listen to mine. ", "Didascalie": "", "Start": 44199, "End": 44215}, {"Reply": "It's not a wig, it's my hair. ", "Didascalie": "", "Start": 45576, "End": 45606}, {"Reply": "I'm in a hurry. Let's start. ", "Didascalie": "", "Start": 46521, "End": 46550}, {"Reply": "Tonight we improvise. You follow. ", "Didascalie": "", "Start": 46787, "End": 46821}, {"Reply": "He was my childhood friend. He used to watch me for hours and hours. I think he understood me. ", "Didascalie": "", "Start": 47088, "End": 47205}, {"Reply": "Meet Olympia, my nanny. ", "Didascalie": "", "Start": 47543, "End": 47567}, {"Reply": "Olympia, open the front door. ", "Didascalie": "", "Start": 48107, "End": 48137}, {"Reply": "Go and open it. ", "Didascalie": "", "Start": 48390, "End": 48406}, {"Reply": " Olympia is a compendium of domestic virtues. Faithful, admiring, and racist. ", "Didascalie": "(TO TOM)", "Start": 48440, "End": 48551}, {"Reply": "That's me there. And that's Mademoiselle Sauvage, the teacher. ", "Didascalie": "", "Start": 49524, "End": 49598}, {"Reply": "We're safe here. It's odd looking at the past. ", "Didascalie": "", "Start": 50754, "End": 50812}, {"Reply": "What are you doing? ", "Didascalie": "", "Start": 51917, "End": 51937}, {"Reply": "Papa? ", "Didascalie": "", "Start": 53301, "End": 53307}, {"Reply": "In full uniform. ", "Didascalie": "", "Start": 53560, "End": 53577}, {"Reply": "Papa in Algeria. ", "Didascalie": "", "Start": 53849, "End": 53866}, {"Reply": "My favorite route when I was eight. ", "Didascalie": "", "Start": 54448, "End": 54484}, {"Reply": "My old notebook. ", "Didascalie": "", "Start": 54681, "End": 54698}, {"Reply": "French homework. Theme: the countryside. Exposition: the countryside is cow country. The cow is all dressed in leather. The cow has four sides: the front, the back, the top and the bottom. Isn't that good? ", "Didascalie": "", "Start": 54806, "End": 55078}, {"Reply": "Here are my cultural sources. Le Grand Larousse. ", "Didascalie": "", "Start": 55329, "End": 55389}, {"Reply": " 29. ", "Didascalie": "(MORE)", "Start": 55421, "End": 55437}, {"Reply": "I just copied from it. ", "Didascalie": "", "Start": 55490, "End": 55513}, {"Reply": "Tom! Tom! Tom! Look! ", "Didascalie": "", "Start": 55944, "End": 55965}, {"Reply": "My first love. ", "Didascalie": "", "Start": 56114, "End": 56129}, {"Reply": "My cousin Paul. My first love. ", "Didascalie": "", "Start": 56271, "End": 56302}, {"Reply": "What? ", "Didascalie": "", "Start": 56464, "End": 56470}, {"Reply": "He played the piano divinely. ", "Didascalie": "", "Start": 56602, "End": 56632}, {"Reply": "Aren't my trees beautiful? They were my jungle. ", "Didascalie": "", "Start": 57805, "End": 57864}, {"Reply": "What are you doing? ", "Didascalie": "", "Start": 58090, "End": 58110}, {"Reply": "Shame on you, doing it in my jungle! ", "Didascalie": "", "Start": 58494, "End": 58542}, {"Reply": "Did you get it? ", "Didascalie": "", "Start": 59461, "End": 59477}, {"Reply": "Olympia was great. It'll give a good idea of race relations in the suburbs of Paris. ", "Didascalie": "", "Start": 59626, "End": 59733}, {"Reply": "I thought we'd finished. ", "Didascalie": "", "Start": 59937, "End": 59962}, {"Reply": "I'm meeting someone for work. ", "Didascalie": "", "Start": 60139, "End": 60169}, {"Reply": "The colonel had green eyes and shiny boots. I worshipped him. He was so handsome in his uniform. ", "Didascalie": "", "Start": 60816, "End": 60935}, {"Reply": "What? ", "Didascalie": "", "Start": 61157, "End": 61163}, {"Reply": "58, and don't joke about things like that. ", "Didascalie": "", "Start": 62094, "End": 62148}, {"Reply": "OK. ", "Didascalie": "", "Start": 62488, "End": 62492}, {"Reply": "So what do I have to say? What do I have to do!? ", "Didascalie": "", "Start": 62691, "End": 62751}, {"Reply": "Of what? ", "Didascalie": "", "Start": 63505, "End": 63514}, {"Reply": "You have been had! ", "Didascalie": "", "Start": 66821, "End": 66840}, {"Reply": "I don't wanna know anything about your past, baby! ", "Didascalie": "", "Start": 66989, "End": 67051}, {"Reply": "I'm a Red Riding Hood and you're the wolf. ", "Didascalie": "", "Start": 67596, "End": 67650}, {"Reply": "What strong arms you have! ", "Didascalie": "", "Start": 67826, "End": 67853}, {"Reply": "What long nails you have! ", "Didascalie": "", "Start": 68179, "End": 68205}, {"Reply": "Oh, what a lot of fur you have! ", "Didascalie": "", "Start": 68483, "End": 68515}, {"Reply": "Ooh, what a long tongue you have! ", "Didascalie": "", "Start": 68827, "End": 68861}, {"Reply": "What's this for? ", "Didascalie": "", "Start": 69333, "End": 69350}, {"Reply": "Peanuts? ", "Didascalie": "", "Start": 69544, "End": 69553}, {"Reply": "It's funny. It's like playing grown- ", "Didascalie": "", "Start": 69960, "End": 69997}, {"Reply": "It's the most beautiful thing. ", "Didascalie": "", "Start": 70240, "End": 70271}, {"Reply": "I wasn't like that. ", "Didascalie": "", "Start": 70555, "End": 70575}, {"Reply": "No. No sex. ", "Didascalie": "", "Start": 71035, "End": 71047}, {"Reply": "Tower. ", "Didascalie": "", "Start": 71251, "End": 71258}, {"Reply": "My teacher was a woman. ", "Didascalie": "", "Start": 71527, "End": 71551}, {"Reply": "How did you know? ", "Didascalie": "", "Start": 71712, "End": 71730}, {"Reply": "My first love was my cousin Paul. ", "Didascalie": "", "Start": 71898, "End": 71932}, {"Reply": "Sorry. Sorry. ", "Didascalie": "", "Start": 72301, "End": 72315}, {"Reply": "He was a child prodigy. He was playing with both hands. ", "Didascalie": "", "Start": 72904, "End": 72971}, {"Reply": "We were dying of heat. ", "Didascalie": "", "Start": 73167, "End": 73190}, {"Reply": "In the afternoon, when the grown- ", "Didascalie": "", "Start": 73362, "End": 73396}, {"Reply": "You're crazy! ", "Didascalie": "", "Start": 73597, "End": 73611}, {"Reply": "I never let him! Never! ", "Didascalie": "", "Start": 73771, "End": 73795}, {"Reply": "No, I'm not. ", "Didascalie": "", "Start": 74012, "End": 74025}, {"Reply": "He touched me, but the way he did it. ", "Didascalie": "", "Start": 74303, "End": 74352}, {"Reply": "Behind the house, there were two trees. A plane tree and a chestnut. ", "Didascalie": "", "Start": 74586, "End": 74666}, {"Reply": "Why aren't you listening to me? ", "Didascalie": "", "Start": 75085, "End": 75117}, {"Reply": "The first time? I was really late for school. I started running and it was downhill. All of a sudden, I felt a strong sensation here. ", "Didascalie": "", "Start": 75309, "End": 75476}, {"Reply": "Why aren't you listening to me? ", "Didascalie": "", "Start": 75831, "End": 75863}, {"Reply": "Why do I feel like I'm talking to a brick wall when I talk to you? Your solitude weighs on me. It isn't indulgent. It isn't generous. You are selfish! ", "Didascalie": "", "Start": 76034, "End": 76229}, {"Reply": "I can be by myself, too, you know! ", "Didascalie": "", "Start": 76369, "End": 76404}, {"Reply": "What am I doing in this apartment with you? Love? ", "Didascalie": "", "Start": 83779, "End": 83840}, {"Reply": "So you think I'm a wore. ", "Didascalie": "", "Start": 84168, "End": 84193}, {"Reply": "A wore. ", "Didascalie": "", "Start": 84467, "End": 84475}, {"Reply": "Yes, a whore. Whore. ", "Didascalie": "", "Start": 84629, "End": 84650}, {"Reply": "I prefer to be a whore. ", "Didascalie": "", "Start": 84917, "End": 84941}, {"Reply": "To find out OOH you are. ", "Didascalie": "", "Start": 85190, "End": 85215}, {"Reply": "Yes. ", "Didascalie": "", "Start": 85464, "End": 85469}, {"Reply": "Well, we know that he buys clothes in some big store. That's not much. ", "Didascalie": "", "Start": 85698, "End": 85780}, {"Reply": "Well, OK. Let's forget it. How old are you? ", "Didascalie": "", "Start": 85977, "End": 86032}, {"Reply": "Oh, you don't look it. ", "Didascalie": "", "Start": 86195, "End": 86218}, {"Reply": "Have you been in college? ", "Didascalie": "", "Start": 86456, "End": 86482}, {"Reply": "Wow! ", "Didascalie": "", "Start": 86719, "End": 86724}, {"Reply": "Barbers don't usually go to university. ", "Didascalie": "", "Start": 86875, "End": 86926}, {"Reply": "No, but that's a razor's barber. ", "Didascalie": "", "Start": 87121, "End": 87154}, {"Reply": "Barber's razors, yes. ", "Didascalie": "", "Start": 87376, "End": 87398}, {"Reply": "So you want to cut me up? ", "Didascalie": "", "Start": 87612, "End": 87638}, {"Reply": "Like they do to slaves? ", "Didascalie": "", "Start": 87840, "End": 87864}, {"Reply": " 46. ", "Didascalie": "(MORE)", "Start": 88152, "End": 88168}, {"Reply": "why you don't want to know anything about me? Because you hate women. ", "Didascalie": "", "Start": 88221, "End": 88302}, {"Reply": "What the hell have they ever done to you? ", "Didascalie": "", "Start": 88452, "End": 88505}, {"Reply": "Again! Do it again! Again! ", "Didascalie": "", "Start": 90784, "End": 90811}, {"Reply": "Shall we leave together? ", "Didascalie": "", "Start": 91398, "End": 91423}, {"Reply": "Bastard! He's a git! Not even goodbye! ", "Didascalie": "", "Start": 91594, "End": 91644}, {"Reply": "Tom! ", "Didascalie": "", "Start": 92277, "End": 92282}, {"Reply": "Wait! I've got to talk to you. ", "Didascalie": "", "Start": 92553, "End": 92584}, {"Reply": "You must find someone else. ", "Didascalie": "", "Start": 92778, "End": 92806}, {"Reply": "For your film. ", "Didascalie": "", "Start": 92953, "End": 92968}, {"Reply": "Because you're taking advantage of me! Because you make me do things I've never done! Because you're taking up my time! You make me do whatever you want! The film is over! ", "Didascalie": "", "Start": 93152, "End": 93379}, {"Reply": "I'm tired of being raped! ", "Didascalie": "", "Start": 93568, "End": 93594}, {"Reply": "Are you in? ", "Didascalie": "", "Start": 102970, "End": 102982}, {"Reply": "Is anyone here? ", "Didascalie": "", "Start": 103125, "End": 103141}, {"Reply": "Hi, monster. ", "Didascalie": "", "Start": 103421, "End": 103434}, {"Reply": "Is something wrong? ", "Didascalie": "", "Start": 103654, "End": 103674}, {"Reply": "So you're here? Why didn't you answer? ", "Didascalie": "", "Start": 104039, "End": 104089}, {"Reply": "I have to hurry. I have a cab waiting. ", "Didascalie": "", "Start": 104246, "End": 104296}, {"Reply": "It makes me crazy! ", "Didascalie": "", "Start": 104627, "End": 104646}, {"Reply": "That you're so damned sure that I'm coming back here. ", "Didascalie": "", "Start": 104864, "End": 104929}, {"Reply": "Do you really think that an American sitting on the floor in an empty flat eating cheese and drinking water is interesting? ", "Didascalie": "", "Start": 105102, "End": 105259}, {"Reply": "There's something under here. Can you hear it? It's hollow. Can you hear it? It's hollow. ", "Didascalie": "", "Start": 105462, "End": 105574}, {"Reply": "Don't open it! ", "Didascalie": "", "Start": 105925, "End": 105940}, {"Reply": "I don't know. Don't open it. ", "Didascalie": "", "Start": 106087, "End": 106116}, {"Reply": "No. ", "Didascalie": "", "Start": 106864, "End": 106868}, {"Reply": "What are you doing? ", "Didascalie": "", "Start": 107814, "End": 107834}, {"Reply": "No and no! No! ", "Didascalie": "", "Start": 108547, "End": 108562}, {"Reply": "Shit! ", "Didascalie": "", "Start": 112097, "End": 112103}, {"Reply": "Hey, you! ", "Didascalie": "", "Start": 112245, "End": 112255}, {"Reply": "Yes, you! ", "Didascalie": "", "Start": 112399, "End": 112409}, {"Reply": "I've got a surprise for you. ", "Didascalie": "", "Start": 112552, "End": 112581}, {"Reply": "I've got a surprise for you! ", "Didascalie": "", "Start": 112841, "End": 112870}, {"Reply": "Music. But I don't know how to work it. ", "Didascalie": "", "Start": 113288, "End": 113339}, {"Reply": "Because you're angry, or you want to be alone with me? ", "Didascalie": "", "Start": 114454, "End": 114520}, {"Reply": "You have something really serious to tell me. ", "Didascalie": "", "Start": 114749, "End": 114806}, {"Reply": "Is it happy or sad? ", "Didascalie": "", "Start": 115064, "End": 115084}, {"Reply": "So it's happy. What sort of secret? ", "Didascalie": "", "Start": 115236, "End": 115272}, {"Reply": "Is it dirty or is it about love? ", "Didascalie": "", "Start": 115727, "End": 115760}, {"Reply": "A secret about love, but which isn't love. What is it?! ", "Didascalie": "", "Start": 115955, "End": 116022}, {"Reply": "What? ", "Didascalie": "", "Start": 116281, "End": 116287}, {"Reply": "What?! ", "Didascalie": "", "Start": 116481, "End": 116488}, {"Reply": "You're marrying me? ", "Didascalie": "", "Start": 116641, "End": 116661}, {"Reply": "We're getting married? ", "Didascalie": "", "Start": 116801, "End": 116824}, {"Reply": "No. ", "Didascalie": "", "Start": 116986, "End": 116990}, {"Reply": "No! ", "Didascalie": "", "Start": 117130, "End": 117134}, {"Reply": "Yes? ", "Didascalie": "", "Start": 117274, "End": 117279}, {"Reply": "No. ", "Didascalie": "", "Start": 117393, "End": 117397}, {"Reply": "Yes? ", "Didascalie": "", "Start": 117537, "End": 117542}, {"Reply": "I don't know. ", "Didascalie": "", "Start": 117712, "End": 117726}, {"Reply": "Yes! ", "Didascalie": "", "Start": 117919, "End": 117924}, {"Reply": "Yes! ", "Didascalie": "", "Start": 118065, "End": 118070}, {"Reply": "No. ", "Didascalie": "", "Start": 118212, "End": 118216}, {"Reply": "Olympia will be happy. I went there yesterday with Tom. ", "Didascalie": "", "Start": 119165, "End": 119232}, {"Reply": "She's preparing a family museum. ", "Didascalie": "", "Start": 119407, "End": 119440}, {"Reply": "When I was little, it seemed really heavy when Papa taught me how to shoot. ", "Didascalie": "", "Start": 120206, "End": 120304}, {"Reply": "You don't even know how to use it. ", "Didascalie": "", "Start": 120556, "End": 120591}, {"Reply": "You really kept everything of Papa's. ", "Didascalie": "", "Start": 120811, "End": 120860}, {"Reply": "Who's that? His orderly? ", "Didascalie": "", "Start": 121085, "End": 121110}, {"Reply": "Oh. ", "Didascalie": "", "Start": 121313, "End": 121317}, {"Reply": "Don't worry. You'll soon have all the space you want. ", "Didascalie": "", "Start": 121734, "End": 121799}, {"Reply": "Nothing. ", "Didascalie": "", "Start": 121969, "End": 121978}, {"Reply": "I'm getting married in a week! ", "Didascalie": "", "Start": 122972, "End": 123003}, {"Reply": "To Tom! In a week! ", "Didascalie": "", "Start": 123354, "End": 123373}, {"Reply": "Tom! In a week! ", "Didascalie": "", "Start": 123530, "End": 123546}, {"Reply": "Marriage? ", "Didascalie": "", "Start": 124761, "End": 124771}, {"Reply": "I see it everywhere. All the time. ", "Didascalie": "", "Start": 125032, "End": 125067}, {"Reply": "On walls. On buildings. ", "Didascalie": "", "Start": 125275, "End": 125299}, {"Reply": "Yes, on advertising hoardings. ", "Didascalie": "", "Start": 125457, "End": 125488}, {"Reply": "No. They're all about young couples. Before marriage, no children. Then the same couple, married with children. In short, marriage. The perfect, ideal, successful marriage. It's no longer the preserve of the Church. The husband was burdened with responsibilities and the wife nagged. Now, weddings in advertising smile! ", "Didascalie": "", "Start": 125690, "End": 126120}, {"Reply": "On posters, of course. But why t take poster marriage seriously? ", "Didascalie": "", "Start": 126281, "End": 126357}, {"Reply": "Then you have to fix it like you would a car. The spouses are two workers in overalls bending over an engine to fix it. ", "Didascalie": "", "Start": 126723, "End": 126876}, {"Reply": "In that case, there are three or four workers. ", "Didascalie": "", "Start": 127123, "End": 127181}, {"Reply": "No. That's not. Love isn't pop. ", "Didascalie": "", "Start": 127348, "End": 127380}, {"Reply": "The workers retire to a secret flat, take off their overalls and become men and women again and make love. ", "Didascalie": "", "Start": 127548, "End": 127688}, {"Reply": "It's the dress that makes the bride. ", "Didascalie": "", "Start": 128143, "End": 128191}, {"Reply": "Jeanne! Jeanne! Jeanne! Jeanne! ", "Didascalie": "", "Start": 129751, "End": 129783}, {"Reply": " Forgive me! I wanted to leave you and I couldn't. ", "Didascalie": "(FRENCH)", "Start": 130709, "End": 130782}, {"Reply": " I wanted to leave you and I couldn't. I can't. I can't leave you, do you understand? ", "Didascalie": "(ENGLISH)", "Start": 130817, "End": 130936}, {"Reply": "Do you still want me? ", "Didascalie": "", "Start": 131130, "End": 131152}, {"Reply": "I want to go! ", "Didascalie": "", "Start": 133464, "End": 133478}, {"Reply": "This is the end! ", "Didascalie": "", "Start": 133799, "End": 133816}, {"Reply": "I wanna go! I can't make love in this bed any more. I can't. It's disgusting! Nauseating! ", "Didascalie": "", "Start": 134567, "End": 134679}, {"Reply": "I want to get out of here. I want to go. I can't stand it here any more. Yes. I'm going. ", "Didascalie": "", "Start": 135700, "End": 135811}, {"Reply": "I forgot to tell you something. I fell in love with somebody. ", "Didascalie": "", "Start": 136395, "End": 136468}, {"Reply": "I'm going to make love with him! ", "Didascalie": "", "Start": 136768, "End": 136801}, {"Reply": "I'm in love. ", "Didascalie": "", "Start": 138211, "End": 138224}, {"Reply": "I'm in love! I'm in love, you understand? ", "Didascalie": "", "Start": 138599, "End": 138652}, {"Reply": "I'm in love, I'm in love! ", "Didascalie": "", "Start": 138854, "End": 138880}, {"Reply": "Oh! I'm in love! ", "Didascalie": "", "Start": 139022, "End": 139039}, {"Reply": "You know, you're old! You're getting fat. ", "Didascalie": "", "Start": 139233, "End": 139286}, {"Reply": "Half of your hair is out and the other half is almost white. ", "Didascalie": "", "Start": 139448, "End": 139520}, {"Reply": "How poetic. But please, before you go, wash my feet. ", "Didascalie": "", "Start": 140284, "End": 140348}, {"Reply": "You know, he and I, we make love. ", "Didascalie": "", "Start": 140740, "End": 140774}, {"Reply": "Magnificent. ", "Didascalie": "", "Start": 141030, "End": 141043}, {"Reply": "He is full of mysteries. ", "Didascalie": "", "Start": 141473, "End": 141498}, {"Reply": "He could be. He looks it. You know why I'm in love with him? ", "Didascalie": "", "Start": 142281, "End": 142353}, {"Reply": "Because he know. He know how to make me fall in love with him. ", "Didascalie": "", "Start": 142546, "End": 142620}, {"Reply": "Yeah. ", "Didascalie": "", "Start": 142915, "End": 142921}, {"Reply": "Yes. ", "Didascalie": "", "Start": 143370, "End": 143375}, {"Reply": "But I find this man. ", "Didascalie": "", "Start": 143541, "End": 143562}, {"Reply": "But I find this man! ", "Didascalie": "", "Start": 144056, "End": 144077}, {"Reply": "But I find this man. He's you! You are that man! ", "Didascalie": "", "Start": 144767, "End": 144827}, {"Reply": "What? ", "Didascalie": "", "Start": 145123, "End": 145129}, {"Reply": "That's it. ", "Didascalie": "", "Start": 145575, "End": 145586}, {"Reply": "What? ", "Didascalie": "", "Start": 145865, "End": 145871}, {"Reply": "Yeah. ", "Didascalie": "", "Start": 146394, "End": 146400}, {"Reply": "Yeah! ", "Didascalie": "", "Start": 146543, "End": 146549}, {"Reply": "Yes, and more than that! And worse! ", "Didascalie": "", "Start": 146919, "End": 146955}, {"Reply": "No! ", "Didascalie": "", "Start": 157563, "End": 157567}, {"Reply": "Try and remember! The man from the fourth floor. He moved in a few days ago. ", "Didascalie": "", "Start": 158642, "End": 158741}, {"Reply": "Where did they take the furniture too? It's empty. Where do you send his mail? Give me his address. ", "Didascalie": "", "Start": 159119, "End": 159241}, {"Reply": "Not even his name? ", "Didascalie": "", "Start": 159439, "End": 159458}, {"Reply": "I've found a flat for us. 1 rue Jules Verne. Yes. In Passy. Come quickly! You'll come now? Do you know where it is? I'll wait for you. Come over. ", "Didascalie": "", "Start": 160056, "End": 160246}, {"Reply": "Come in, it's open. ", "Didascalie": "", "Start": 160841, "End": 160861}, {"Reply": "Do you like our flat? It's very light. There's a tiny room, too. ", "Didascalie": "", "Start": 161118, "End": 161194}, {"Reply": "I'm here! ", "Didascalie": "", "Start": 162723, "End": 162733}, {"Reply": "Stop it! Don't start! ", "Didascalie": "", "Start": 162975, "End": 162997}, {"Reply": "By chance. ", "Didascalie": "", "Start": 163162, "End": 163173}, {"Reply": "Everything! We'll change chance to destiny. ", "Didascalie": "", "Start": 163410, "End": 163465}, {"Reply": "What's happening? ", "Didascalie": "", "Start": 164162, "End": 164180}, {"Reply": "Adults? That's awful! ", "Didascalie": "", "Start": 164679, "End": 164701}, {"Reply": "What do adults do? ", "Didascalie": "", "Start": 164855, "End": 164874}, {"Reply": "Where are you going? ", "Didascalie": "", "Start": 166165, "End": 166186}, {"Reply": "What kind of flat? ", "Didascalie": "", "Start": 166413, "End": 166432}, {"Reply": "We can live here. ", "Didascalie": "", "Start": 166647, "End": 166665}, {"Reply": "No, no. I've got to close the windows and return the key. There's a lot to do. ", "Didascalie": "", "Start": 166880, "End": 166981}, {"Reply": "Bye. ", "Didascalie": "", "Start": 167216, "End": 167221}, {"Reply": "It's over. It's over. ", "Didascalie": "", "Start": 168810, "End": 168832}, {"Reply": "What begins again? I don't understand anything any more. ", "Didascalie": "", "Start": 169130, "End": 169198}, {"Reply": "The rest? ", "Didascalie": "", "Start": 169476, "End": 169486}, {"Reply": "No. ", "Didascalie": "", "Start": 172048, "End": 172052}, {"Reply": "If you'd like to. ", "Didascalie": "", "Start": 172197, "End": 172215}, {"Reply": "OK, I love you. ", "Didascalie": "", "Start": 173860, "End": 173876}, {"Reply": "Tell me about your wife. ", "Didascalie": "", "Start": 174117, "End": 174142}, {"Reply": "OK. But this place is so pitiful. ", "Didascalie": "", "Start": 174327, "End": 174361}, {"Reply": "In your flophouse? ", "Didascalie": "", "Start": 174885, "End": 174904}, {"Reply": "Give me some more whisky. ", "Didascalie": "", "Start": 176315, "End": 176341}, {"Reply": "But I'm thirsty now and I want some more drink. ", "Didascalie": "", "Start": 176515, "End": 176574}, {"Reply": "Let's have a toast to our life in the hotel. ", "Didascalie": "", "Start": 177207, "End": 177263}, {"Reply": "You're a nature lover? You didn't tell me that. ", "Didascalie": "", "Start": 177521, "End": 177580}, {"Reply": "Oh, yeah. To the house of the cows. ", "Didascalie": "", "Start": 177838, "End": 177874}, {"Reply": "I will be your cow, too. ", "Didascalie": "", "Start": 178125, "End": 178150}, {"Reply": "I hate the country. ", "Didascalie": "", "Start": 178428, "End": 178448}, {"Reply": "It's finished. ", "Didascalie": "", "Start": 182259, "End": 182274}, {"Reply": "It's finished! ", "Didascalie": "", "Start": 182530, "End": 182545}, {"Reply": "We're never going to see each other again. Never! ", "Didascalie": "", "Start": 182778, "End": 182839}, {"Reply": "It's not a joke. ", "Didascalie": "", "Start": 183152, "End": 183169}, {"Reply": "It's finished. ", "Didascalie": "", "Start": 183326, "End": 183341}, {"Reply": "I'm getting married! I'm going away. It's finished. ", "Didascalie": "", "Start": 183540, "End": 183603}, {"Reply": "It's finished! ", "Didascalie": "", "Start": 184002, "End": 184017}, {"Reply": "Stop! Stop! ", "Didascalie": "", "Start": 186208, "End": 186220}, {"Reply": "It's over! ", "Didascalie": "", "Start": 186428, "End": 186439}, {"Reply": "Stop it! We're finished. ", "Didascalie": "", "Start": 186708, "End": 186733}, {"Reply": "Go away! Go away! Go away! ", "Didascalie": "", "Start": 186872, "End": 186899}, {"Reply": "Let go! Go away! ", "Didascalie": "", "Start": 187049, "End": 187066}, {"Reply": "I'll call the police! ", "Didascalie": "", "Start": 187679, "End": 187701}, {"Reply": "It's over! It's over! ", "Didascalie": "", "Start": 189057, "End": 189079}, {"Reply": "It's over! ", "Didascalie": "", "Start": 189306, "End": 189317}, {"Reply": "Help! ", "Didascalie": "", "Start": 189862, "End": 189868}, {"Reply": "Help! Help! ", "Didascalie": "", "Start": 190040, "End": 190052}, {"Reply": "Please, help! ", "Didascalie": "", "Start": 190194, "End": 190208}, {"Reply": "Help! Help! ", "Didascalie": "", "Start": 190370, "End": 190382}, {"Reply": "Help! Help me! Help! ", "Didascalie": "", "Start": 190858, "End": 190879}, {"Reply": "I don't know who he is. He followed me in the street. He tried to rape me. He's a lunatic. I don't know what he's called. I don't know his name. I don't know who he is. He tried to rape me. I don't know. I don't know him. I don't know who he is. He's a lunatic. I don't know his name. ", "Didascalie": "", "Start": 195276, "End": 195649}]}, {"Character": "BARTENDER", "Replies": [{"Reply": "No tokens. At the end, on the left. ", "Didascalie": "", "Start": 2951, "End": 2987}]}, {"Character": "CONCIERGE", "Replies": [{"Reply": "The sign? ", "Didascalie": "", "Start": 4718, "End": 4728}, {"Reply": "It's always the same! Nobody ever tells me anything. ", "Didascalie": "", "Start": 4994, "End": 5058}, {"Reply": "You want to rent it? ", "Didascalie": "", "Start": 5221, "End": 5242}, {"Reply": "They rent, they leave and I'm the last to know. Do you think that's right? ", "Didascalie": "", "Start": 5403, "End": 5500}, {"Reply": "If you want to go up alone-- ", "Didascalie": "", "Start": 5667, "End": 5696}, {"Reply": "Go on. I'm afraid of spiders. The key is missing. Strange things happen. ", "Didascalie": "", "Start": 5844, "End": 5939}, {"Reply": "They drink six bottles a day. ", "Didascalie": "", "Start": 6133, "End": 6163}, {"Reply": "Wait! Don't go! There must be a duplicate. ", "Didascalie": "", "Start": 6402, "End": 6456}, {"Reply": "Here it is. ", "Didascalie": "", "Start": 6592, "End": 6604}, {"Reply": "You must be very young. ", "Didascalie": "", "Start": 6907, "End": 6931}, {"Reply": "I told you, I don't know anyone. ", "Didascalie": "", "Start": 158840, "End": 158873}, {"Reply": "I don't have it. I don't know these people. ", "Didascalie": "", "Start": 159314, "End": 159369}, {"Reply": "Nothing! ", "Didascalie": "", "Start": 159531, "End": 159540}, {"Reply": "Ma'zelle! ", "Didascalie": "", "Start": 159677, "End": 159687}]}, {"Character": "LIVING ROOM - CONTINUOUS", "Replies": [{"Reply": "But she has followed him. She OPENS THOSE WINDOWS also. He is forced into ANOTHER ROOM. ", "Didascalie": "", "Start": 9704, "End": 9802}, {"Reply": "Jeanne is STARTLED. She hangs up the phone. ", "Didascalie": "", "Start": 11990, "End": 12034}, {"Reply": "Jeanne is sitting in the chair in front of the fire place. ", "Didascalie": "", "Start": 26925, "End": 26984}, {"Reply": "Jeanne stands in SHOCK with PAUL'S CORPSE in the b.g. ", "Didascalie": "", "Start": 194970, "End": 195024}]}, {"Character": "DINING ROOM - CONTINUOUS", "Replies": [{"Reply": "As he studies a WICKER CHAISE LOUNGE, she calls from the other room. ", "Didascalie": "", "Start": 9899, "End": 9978}, {"Reply": "He places the table. She FOLLOWS with the CHAIRS. ", "Didascalie": "", "Start": 28118, "End": 28168}, {"Reply": "Paul opens the curtains. ", "Didascalie": "", "Start": 132447, "End": 132472}, {"Reply": "Jeanne RIPS THE SHEET OFF the piece of furniture that has been COVERED UP all along. We all wondered what was underneath that was so precious. ", "Didascalie": "", "Start": 157865, "End": 158028}]}, {"Character": "BATHROOM - CONTINUOUS", "Replies": [{"Reply": "As the PHONE RINGS, she pulls up her skirt and sits on the toilet for a PEE. She looks around. ", "Didascalie": "", "Start": 10728, "End": 10833}, {"Reply": "He turns off the ANNOYING RUNNING WATER. He looks at himself in the mirror. ", "Didascalie": "", "Start": 37419, "End": 37505}]}, {"Character": "DINING ROOM", "Replies": [{"Reply": "They pick up the phone at the SAME TIME. Paul EAVES DROPS  JEANNE'S VOICE Hello? Hello -- ", "Didascalie": "", "Start": 11339, "End": 11491}, {"Reply": "Paul is REUNITED with his SMALL LAMP SHADE. He puts it over his face and CRIES into it. ", "Didascalie": "", "Start": 76925, "End": 77023}, {"Reply": "Paul is LOST IN GRIEF, crying harder. ", "Didascalie": "", "Start": 77457, "End": 77495}, {"Reply": "54. ", "Didascalie": "", "Start": 103312, "End": 103316}]}, {"Character": "PONT DE BIR-HAKEIM - CONTINUOUS", "Replies": [{"Reply": "They go their SEPARATE WAYS. Jeanne crosses the street while Paul takes the RAISED WALKWAY. ", "Didascalie": "", "Start": 14929, "End": 15031}]}, {"Character": "TOM", "Replies": [{"Reply": "Watch out! ", "Didascalie": "", "Start": 15722, "End": 15733}, {"Reply": "We're in a film. ", "Didascalie": "", "Start": 15918, "End": 15935}, {"Reply": "It's a long story. In short, Portrait of a Girl. It's been accepted for television! And the girl is you. It's you! ", "Didascalie": "", "Start": 16643, "End": 16791}, {"Reply": "my crew. ", "Didascalie": "", "Start": 17325, "End": 17334}, {"Reply": "No, you'll see. It will be a love story. Tell me, Jeanne, darling. ", "Didascalie": "", "Start": 17572, "End": 17650}, {"Reply": "Wonderful! Cut! That was perfect! ", "Didascalie": "", "Start": 17934, "End": 17968}, {"Reply": "You shouldn't have done that to me. ", "Didascalie": "", "Start": 45389, "End": 45425}, {"Reply": "The camera is up high. It descends slowly and follows you. You come forward, and it moves in on you. ", "Didascalie": "", "Start": 46226, "End": 46349}, {"Reply": "Cut! ", "Didascalie": "", "Start": 50879, "End": 50884}, {"Reply": "Why is it odd? It's you! It's fantastic, it's your childhood. ", "Didascalie": "", "Start": 51013, "End": 51086}, {"Reply": "What are you up to? Move it! Move it! ", "Didascalie": "", "Start": 51324, "End": 51373}, {"Reply": " Who are these zombies who are always following you around? ", "Didascalie": "(CONT'D) (to the lead crewman)", "Start": 51405, "End": 51487}, {"Reply": "I'm opening the door. I'm opening all the doors. ", "Didascalie": "", "Start": 51761, "End": 51821}, {"Reply": "Setting up my shot. There it is! ", "Didascalie": "", "Start": 52004, "End": 52037}, {"Reply": "What are you doing there? Beat it! ", "Didascalie": "", "Start": 52394, "End": 52429}, {"Reply": "That's it. Into reverse. Yes! Do you see? Like a car, you go into reverse gear. That's it. Close your eyes. ", "Didascalie": "", "Start": 52620, "End": 52761}, {"Reply": "Start reversing. Close your eyes. ", "Didascalie": "", "Start": 52964, "End": 52998}, {"Reply": "You're soaring. Take off and return to your childhood. ", "Didascalie": "", "Start": 53374, "End": 53440}, {"Reply": "Don't be afraid. Overcome the obstacles. ", "Didascalie": "", "Start": 53685, "End": 53737}, {"Reply": "We're there. ", "Didascalie": "", "Start": 54288, "End": 54301}, {"Reply": "Beastly. ", "Didascalie": "", "Start": 55145, "End": 55154}, {"Reply": "Who's that? ", "Didascalie": "", "Start": 56032, "End": 56044}, {"Reply": "Who? ", "Didascalie": "", "Start": 56196, "End": 56201}, {"Reply": "But his eyes are closed. ", "Didascalie": "", "Start": 56369, "End": 56394}, {"Reply": "His eyes are closed! ", "Didascalie": "", "Start": 56537, "End": 56558}, {"Reply": "Keep filming. Keep filming! Don't stop, whatever you do! ", "Didascalie": "", "Start": 59174, "End": 59242}, {"Reply": "Everything. ", "Didascalie": "", "Start": 59544, "End": 59556}, {"Reply": "It's a real jungle here. So, tell me about your father. ", "Didascalie": "", "Start": 59800, "End": 59867}, {"Reply": "Five minutes. ", "Didascalie": "", "Start": 60055, "End": 60069}, {"Reply": "Jeanne! What are you doing there? ", "Didascalie": "", "Start": 92349, "End": 92383}, {"Reply": "Why didn't you speak on the phone? ", "Didascalie": "", "Start": 92651, "End": 92686}, {"Reply": "For what? ", "Didascalie": "", "Start": 92873, "End": 92883}, {"Reply": "Why. ", "Didascalie": "", "Start": 93035, "End": 93040}, {"Reply": "Do you know why I sent the others away? ", "Didascalie": "", "Start": 114333, "End": 114384}, {"Reply": "And why do I want to be alone with you? ", "Didascalie": "", "Start": 114628, "End": 114679}, {"Reply": "I have something really very serious to tell you. ", "Didascalie": "", "Start": 114933, "End": 114994}, {"Reply": "It's a secret. ", "Didascalie": "", "Start": 115151, "End": 115166}, {"Reply": "About love. But that's not all. ", "Didascalie": "", "Start": 115827, "End": 115859}, {"Reply": "Voila. That in a week I'm marrying you. ", "Didascalie": "", "Start": 116160, "End": 116211}, {"Reply": "I'm marrying you. ", "Didascalie": "", "Start": 116394, "End": 116412}, {"Reply": "I'm marrying you! ", "Didascalie": "", "Start": 116554, "End": 116572}, {"Reply": "Yes! ", "Didascalie": "", "Start": 116727, "End": 116732}, {"Reply": "Yes we're getting married. ", "Didascalie": "", "Start": 116890, "End": 116917}, {"Reply": "Yes. ", "Didascalie": "", "Start": 117056, "End": 117061}, {"Reply": "Yes. ", "Didascalie": "", "Start": 117200, "End": 117205}, {"Reply": "Yes. ", "Didascalie": "", "Start": 117319, "End": 117324}, {"Reply": "Yes. ", "Didascalie": "", "Start": 117463, "End": 117468}, {"Reply": "No. Are we getting married or not? ", "Didascalie": "", "Start": 117608, "End": 117643}, {"Reply": "So, yes, then? ", "Didascalie": "", "Start": 117834, "End": 117849}, {"Reply": "No! ", "Didascalie": "", "Start": 117991, "End": 117995}, {"Reply": "Yes. ", "Didascalie": "", "Start": 118137, "End": 118142}, {"Reply": "Yes or no? ", "Didascalie": "", "Start": 118283, "End": 118294}, {"Reply": "Move into shot! We're shooting! ", "Didascalie": "", "Start": 124290, "End": 124322}, {"Reply": "Yes. ", "Didascalie": "", "Start": 124838, "End": 124843}, {"Reply": "What do you mean, everywhere? ", "Didascalie": "", "Start": 125175, "End": 125205}, {"Reply": "Walls and buildings? ", "Didascalie": "", "Start": 125366, "End": 125387}, {"Reply": "What are they selling? Cars. Tinned meat. Cigarettes. ", "Didascalie": "", "Start": 125555, "End": 125620}, {"Reply": "They smile. On posters. ", "Didascalie": "", "Start": 126187, "End": 126211}, {"Reply": "And in case of adultery what happens to the pop marriage? ", "Didascalie": "", "Start": 126943, "End": 127012}, {"Reply": "What about love? Is love pop? ", "Didascalie": "", "Start": 127248, "End": 127278}, {"Reply": "Love isn't pop. So what is it? ", "Didascalie": "", "Start": 127447, "End": 127478}, {"Reply": "You're wonderful. ", "Didascalie": "", "Start": 128055, "End": 128073}, {"Reply": "You're better than Rita Hayworth. ", "Didascalie": "", "Start": 128258, "End": 128292}, {"Reply": "What are you doing? Stop! Stop, but keep filming! Why aren't you filming in the rain? ", "Didascalie": "", "Start": 128736, "End": 128844}, {"Reply": "You're all fired! ", "Didascalie": "", "Start": 129238, "End": 129256}, {"Reply": "Where's Jeanne? ", "Didascalie": "", "Start": 129394, "End": 129410}, {"Reply": "When? ln the rain? ", "Didascalie": "", "Start": 129573, "End": 129592}, {"Reply": "But I'd like a girl, too. Rosa. As in Rosa Luxemburg. Less famous, but I like it. You know, I wanted to film you every day. In the morning, when you wake up, in the evening, when you sleep. When you first smile, and I didn't film any of that. Here. ", "Didascalie": "", "Start": 161452, "End": 161778}, {"Reply": "Today is the last day of shooting. ", "Didascalie": "", "Start": 161965, "End": 162000}, {"Reply": "This flat is huge! ", "Didascalie": "", "Start": 162463, "End": 162482}, {"Reply": "Where are you? ", "Didascalie": "", "Start": 162638, "End": 162653}, {"Reply": "It's too big! We'll get lost! ", "Didascalie": "", "Start": 162875, "End": 162905}, {"Reply": "How did you find this flat? ", "Didascalie": "", "Start": 163064, "End": 163092}, {"Reply": "We'll change everything! ", "Didascalie": "", "Start": 163240, "End": 163265}, {"Reply": "Go on, Jeanne. Take off! ", "Didascalie": "", "Start": 163532, "End": 163557}, {"Reply": "Fly away, you're in heaven! You're soaring, you're in heaven! Come down, take a nose dive, come down! ", "Didascalie": "", "Start": 163794, "End": 163918}, {"Reply": "The patches of turbulence are over. ", "Didascalie": "", "Start": 164288, "End": 164324}, {"Reply": "We're adults. ", "Didascalie": "", "Start": 164595, "End": 164609}, {"Reply": "Yes. It's awful. ", "Didascalie": "", "Start": 164768, "End": 164785}, {"Reply": "But there's one thing I do know. ", "Didascalie": "", "Start": 165304, "End": 165337}, {"Reply": "You see, Jeanne, this flat won't work for us. This flat, it won't work for us, Jeanne. ", "Didascalie": "", "Start": 165986, "End": 166095}, {"Reply": "To look for a flat. ", "Didascalie": "", "Start": 166253, "End": 166273}, {"Reply": "A flat we can live in. ", "Didascalie": "", "Start": 166554, "End": 166577}, {"Reply": "It's squalid. It smells. It makes me sick. Are you coming with me? ", "Didascalie": "", "Start": 166732, "End": 166810}, {"Reply": "OK. ", "Didascalie": "", "Start": 167048, "End": 167052}, {"Reply": "Bye. ", "Didascalie": "", "Start": 167288, "End": 167293}]}, {"Character": "CATHERINE", "Replies": [{"Reply": "I'd have finished by now, but the police wouldn't let me touch anything. They didn't believe it was suicide. ", "Didascalie": "", "Start": 18809, "End": 18951}, {"Reply": "There was so much blood everywhere. ", "Didascalie": "", "Start": 19089, "End": 19125}, {"Reply": "\"She came through here.\" ", "Didascalie": "", "Start": 19360, "End": 19385}, {"Reply": "\"She opened the curtain.\" ", "Didascalie": "", "Start": 19581, "End": 19607}, {"Reply": "I copied all her actions. The guests were awake all night! The hotel was crawling with cops! They enjoy playing around with blood. ", "Didascalie": "", "Start": 19833, "End": 19997}, {"Reply": "They were all spies! Asking if she was sad, if she was happy, if you fought, how long you'd been married, why you didn't have any children. Pigs! ", "Didascalie": "", "Start": 20135, "End": 20325}, {"Reply": "They got familiar right away! They said, \"Your boss is a bit unstable.\" \"Do you know that he was a boxer?\" So? ", "Didascalie": "", "Start": 20618, "End": 20762}, {"Reply": " 11. ", "Didascalie": "(CONT'D) (MORE)", "Start": 20794, "End": 20810}, {"Reply": "\"It didn't work out, so he became an actor.\" \"Bongo player, revolutionary in South America, journalist in Japan.\" ", "Didascalie": "", "Start": 20866, "End": 21013}, {"Reply": "I say, \"Can I clean up now?\" \"No! ", "Didascalie": "", "Start": 21777, "End": 21811}, {"Reply": "They'll be doing the autopsy right now. ", "Didascalie": "", "Start": 22315, "End": 22366}, {"Reply": "They told me to give you your razor back. ", "Didascalie": "", "Start": 22599, "End": 22652}, {"Reply": "They said they don't need it any more. The investigation is over. ", "Didascalie": "", "Start": 22934, "End": 23011}]}, {"Character": "MOVER", "Replies": [{"Reply": "Excuse me, where shall I put this? ", "Didascalie": "", "Start": 24698, "End": 24733}, {"Reply": "The door was open. I'll put it there. ", "Didascalie": "", "Start": 24943, "End": 24992}, {"Reply": "What about the table? ", "Didascalie": "", "Start": 25702, "End": 25724}, {"Reply": "Thank you. ", "Didascalie": "", "Start": 26645, "End": 26656}]}, {"Character": "BEDROOM - CONTINUOUS", "Replies": [{"Reply": "Jeanne REGARDS the room. ", "Didascalie": "", "Start": 25992, "End": 26017}, {"Reply": "She walks across the mattresses with her BOOTS ON. Paul leans against the wall STUDYING THE ROOM. ", "Didascalie": "", "Start": 28895, "End": 29003}, {"Reply": "Jeanne screams BLOODY MURDER and points to a DEAD RAT on the STILL UNMADE MATTRESS. ", "Didascalie": "", "Start": 132770, "End": 132864}]}, {"Character": "STAIRS - CONTINUOUS", "Replies": [{"Reply": "They pass some GUESTS coming down. ", "Didascalie": "", "Start": 35046, "End": 35081}]}, {"Character": "GUEST", "Replies": [{"Reply": "Hi. ", "Didascalie": "", "Start": 35150, "End": 35154}]}, {"Character": "HALLWAY - CONTINUOUS", "Replies": [{"Reply": "Some of the OTHER GUESTS pop their heads out to see what the COMMOTION IS. He gently CLOSES THEIR DOORS in a \"mind your own business\" sort of way. ", "Didascalie": "", "Start": 40636, "End": 40803}, {"Reply": "Jeanne is on the ELEVATOR. She sticks her head out. ", "Didascalie": "", "Start": 122850, "End": 122902}]}, {"Character": "LIVING ROOM -", "Replies": [{"Reply": "Paul has decided his BED FITS BETTER in here. The BOTTOM MATTRESS is on the floor in the MIDDLE OF THE ROOM. He LEANS AGAINST THE WALL and top mattress, WAITING FOR JEANNE. He knew she'd be there. ", "Didascalie": "", "Start": 41430, "End": 41657}]}, {"Character": "DIALOGUE IS FRENCH", "Replies": [{"Reply": "JEANNE'S VOICE I'm coming! I'm ready. ", "Didascalie": "", "Start": 91212, "End": 91261}, {"Reply": "102. ", "Didascalie": "", "Start": 195175, "End": 195180}]}, {"Character": "FAMILY PET GRAVE-YARD - CONTINUOUS", "Replies": [{"Reply": "Jeanne kneels in front of a HEAD STONE that reads \"Mustapha\". ", "Didascalie": "", "Start": 46973, "End": 47035}]}, {"Character": "OLYMPIA", "Replies": [{"Reply": "Mustapha could always tell the poor from the rich. ", "Didascalie": "", "Start": 47638, "End": 47700}, {"Reply": " 25. ", "Didascalie": "(MORE)", "Start": 47732, "End": 47748}, {"Reply": "If someone well-dressed came in, he never stirred. But if someone scruffy came in, you should have seen him! What a dog! ", "Didascalie": "", "Start": 47802, "End": 47956}, {"Reply": "Give me a kiss. ", "Didascalie": "", "Start": 48208, "End": 48224}, {"Reply": "She was too good. She spoilt you. ", "Didascalie": "", "Start": 49864, "End": 49898}, {"Reply": "I couldn't live in Paris. ", "Didascalie": "", "Start": 50576, "End": 50602}, {"Reply": "Oh, these dirty little Arabs! Go and shit in your own country! ", "Didascalie": "", "Start": 58898, "End": 58972}]}, {"Character": "STUDY - CONTINUOUS", "Replies": [{"Reply": "She reads on. ", "Didascalie": "", "Start": 55245, "End": 55259}]}, {"Character": "LIVING ROOM", "Replies": [{"Reply": "Jeanne has CUM. She ROLLS OFF THE MATTRESSES onto the floor, SPENT. ", "Didascalie": "", "Start": 77122, "End": 77200}, {"Reply": "Jeanne stands with her back turned staring down into the GUN DRAWER. ", "Didascalie": "", "Start": 191754, "End": 191833}]}, {"Character": "HOTEL ENTRANCE", "Replies": [{"Reply": "Rosa's LOVER. ", "Didascalie": "(60's)", "Start": 82038, "End": 82053}]}, {"Character": "MARCEL", "Replies": [{"Reply": "Good evening, madame. ", "Didascalie": "", "Start": 82163, "End": 82185}, {"Reply": "Goodnight, Paul. ", "Didascalie": "", "Start": 82687, "End": 82704}, {"Reply": "Come in! ", "Didascalie": "", "Start": 94555, "End": 94564}, {"Reply": "Do you mind if I carry on working? ", "Didascalie": "", "Start": 94895, "End": 94930}, {"Reply": "It helps me a lot after what has happened. ", "Didascalie": "", "Start": 95078, "End": 95132}, {"Reply": "Identical. Rosa wanted them identical. ", "Didascalie": "", "Start": 95253, "End": 95303}, {"Reply": "Same colour, same pattern. ", "Didascalie": "", "Start": 95516, "End": 95543}, {"Reply": "Hobby? I don't like that word. ", "Didascalie": "", "Start": 96041, "End": 96072}, {"Reply": "Be honest. You didn't know we had the same bathrobes. ", "Didascalie": "", "Start": 96380, "End": 96445}, {"Reply": "We've got a lot of things in common. ", "Didascalie": "", "Start": 96721, "End": 96769}, {"Reply": "Hold on. Here's the bourbon. ", "Didascalie": "", "Start": 97401, "End": 97430}, {"Reply": "I don't really like bourbon, but Rosa wanted me to keep a bottle here in my room. ", "Didascalie": "", "Start": 97849, "End": 97953}, {"Reply": "I was asking myself this question. ", "Didascalie": "", "Start": 98087, "End": 98122}, {"Reply": "For example, a while ago, something happened that I still don't understand. Do you see there, on the wall? ", "Didascalie": "", "Start": 98728, "End": 98868}, {"Reply": "She had climbed onto the bed and she was trying to tear at the walls with her hands. I stopped her because she was breaking her nails. ", "Didascalie": "", "Start": 99027, "End": 99195}, {"Reply": "A cold sore. I don't know. Shit. ", "Didascalie": "", "Start": 99983, "End": 100016}, {"Reply": "Not as much as you. ", "Didascalie": "", "Start": 100320, "End": 100340}, {"Reply": "Yes, I do. ", "Didascalie": "", "Start": 100845, "End": 100856}, {"Reply": "I have a secret. ", "Didascalie": "", "Start": 101377, "End": 101394}, {"Reply": "This is my secret! Thirty times every morning. ", "Didascalie": "", "Start": 102382, "End": 102440}]}, {"Character": "HIPPIE MUSIC CONTINUES", "Replies": [{"Reply": "Tom and Jeanne sit, ROMANTICALLY ENTWINED on a SEA WALL while his FILM CREW films in the b.g. ", "Didascalie": "", "Start": 114044, "End": 114148}]}, {"Character": "SOUND PERSON", "Replies": [{"Reply": "Speak up! I can't hear anything. ", "Didascalie": "", "Start": 115553, "End": 115586}]}, {"Character": "ELEVATOR", "Replies": [{"Reply": "As it ascends, Jeanne slowly RAISES HER DRESS, revealing NO UNDERWEAR and her AMPLE BUSH to Paul. ", "Didascalie": "", "Start": 131364, "End": 131472}]}, {"Character": "FRONT DOOR", "Replies": [{"Reply": "Paul is there, WAITING, NONCHALANT. ", "Didascalie": "", "Start": 136204, "End": 136240}]}, {"Character": "PROSTITUTE", "Replies": [{"Reply": " Here he is. ", "Didascalie": "(TO JOHN)", "Start": 152826, "End": 152850}, {"Reply": " Hurry up! Wake up! Open up! Open up! ", "Didascalie": "(TO PAUL)", "Start": 152885, "End": 152945}, {"Reply": "I need room four for a while. ", "Didascalie": "", "Start": 153113, "End": 153143}, {"Reply": " Half an hour? ", "Didascalie": "(TO JOHN)", "Start": 153178, "End": 153204}, {"Reply": " Yes, that'll do. Yes, half an hour. ", "Didascalie": "(TO PAUL)", "Start": 153239, "End": 153287}, {"Reply": "That's not true. When you're full, you put a sign outside. I know the hotel. I'm sick of arguing out on the street. Call the owner. What are you waiting for? The owner has never made a fuss. Rosa and I are old friends. Open up. ", "Didascalie": "", "Start": 153513, "End": 153807}, {"Reply": "Don't make any trouble or I'll tell your boss. ", "Didascalie": "", "Start": 153915, "End": 153973}, {"Reply": "You've won. He's taken off. ", "Didascalie": "", "Start": 154189, "End": 154217}, {"Reply": "Hurry up! He can't be far away. ", "Didascalie": "", "Start": 154375, "End": 154407}, {"Reply": "Make him come back. Tell him he can't just walk off. ", "Didascalie": "", "Start": 154601, "End": 154665}]}, {"Character": "JOHN", "Replies": [{"Reply": "You're crazy! Let go of me! Let go! ", "Didascalie": "", "Start": 156180, "End": 156216}]}, {"Character": "DANCE FLOOR", "Replies": [{"Reply": "We watch one of the DANCE COUPLES DANCE THE TANGO. We focus on their LEGS and FEET. ", "Didascalie": "", "Start": 172829, "End": 172923}, {"Reply": "We watch a DIFFERENT COUPLE DANCE. ", "Didascalie": "", "Start": 173347, "End": 173382}, {"Reply": "We watch a COUPLE as the MUSIC STOPS. All the PATRONS CLAP as the DANCE floor clears. ", "Didascalie": "", "Start": 175432, "End": 175528}]}, {"Character": "PRESIDENT", "Replies": [{"Reply": " 92. ", "Didascalie": "(MORE)", "Start": 175853, "End": 175869}, {"Reply": "And now, ladies and gentlemen, good luck for the last tango! ", "Didascalie": "", "Start": 175925, "End": 175997}, {"Reply": "That's the limit! What are you doing? ", "Didascalie": "", "Start": 179242, "End": 179291}, {"Reply": "You'll have to leave, sir. ", "Didascalie": "", "Start": 179637, "End": 179664}, {"Reply": "Go to the circus if you want to see love! Go on! Get out of here! ", "Didascalie": "", "Start": 180089, "End": 180166}]}, {"Character": "PARKING LOT", "Replies": [{"Reply": "She tries to GET THROUGH TO HIM. ", "Didascalie": "", "Start": 186105, "End": 186138}]}, {"Character": "SIDE STREET", "Replies": [{"Reply": "98. ", "Didascalie": "", "Start": 187391, "End": 187395}]}, {"Character": "PORCH - CONTINUOUS", "Replies": [{"Reply": "He LOOKS OUT upon the city, and UP TO THE SKY. He takes his gum out of his mouth and STICKS IT UNDER THE RAILING. ", "Didascalie": "", "Start": 194489, "End": 194613}]}]}