{
	"Title": [
		"Wall-E",
		"   "
	],
	"Author": [
		"\u00a0\u00a0Andrew Stanton\u00a0\u00a0Pete Docter"
	],
	"Genre": [
		"\u00a0\u00a0Animation\u00a0\u00a0Adventure\u00a0\u00a0Comedy\u00a0\u00a0Drama\u00a0\u00a0Family\u00a0\u00a0Romance\u00a0\u00a0Sci-Fi"
	],
	"Characters": [
		{
			"Character": "WALL-E",
			"Replies": [
				{
					"Reply": "Wall-E opens his cooler. ",
					"Didascalie": "",
					"Start": 7670,
					"End": 7695
				},
				{
					"Reply": "14. ",
					"Didascalie": "",
					"Start": 25573,
					"End": 25577
				},
				{
					"Reply": "She scans his CHEST LOGO. ",
					"Didascalie": "",
					"Start": 26364,
					"End": 26390
				},
				{
					"Reply": "Eeeaaah? ",
					"Didascalie": "",
					"Start": 27486,
					"End": 27495
				},
				{
					"Reply": "Eee--vah! ",
					"Didascalie": "",
					"Start": 27666,
					"End": 27676
				},
				{
					"Reply": "Eee-vah! Ee -- ",
					"Didascalie": "",
					"Start": 27837,
					"End": 27852
				},
				{
					"Reply": "She drifts through the sea of knickknacks. ",
					"Didascalie": "",
					"Start": 29470,
					"End": 29513
				},
				{
					"Reply": "He grabs it back. Protective. ",
					"Didascalie": "",
					"Start": 30124,
					"End": 30154
				},
				{
					"Reply": "Mimics the dancing for Eve. ",
					"Didascalie": "",
					"Start": 30491,
					"End": 30519
				},
				{
					"Reply": "Spins in a circle. Arms out. ",
					"Didascalie": "",
					"Start": 30862,
					"End": 30891
				},
				{
					"Reply": "Feels his way to the rack of shelves. ",
					"Didascalie": "",
					"Start": 31497,
					"End": 31535
				},
				{
					"Reply": "Ee-vah! ",
					"Didascalie": "",
					"Start": 32762,
					"End": 32770
				},
				{
					"Reply": "Ee-vah? ",
					"Didascalie": "",
					"Start": 33843,
					"End": 33851
				},
				{
					"Reply": "Ee-vah? ",
					"Didascalie": "",
					"Start": 34057,
					"End": 34065
				},
				{
					"Reply": "EE-VAH!! EE-VAH!! ",
					"Didascalie": "",
					"Start": 37854,
					"End": 37872
				},
				{
					"Reply": "The insect mopes. ",
					"Didascalie": "",
					"Start": 38412,
					"End": 38430
				},
				{
					"Reply": "E-vah! ",
					"Didascalie": "",
					"Start": 40275,
					"End": 40282
				},
				{
					"Reply": "Ee-vah! ",
					"Didascalie": "",
					"Start": 46851,
					"End": 46859
				},
				{
					"Reply": "The ELEVATOR DOORS suddenly open. ",
					"Didascalie": "",
					"Start": 47912,
					"End": 47946
				},
				{
					"Reply": "EE-VAH! ",
					"Didascalie": "",
					"Start": 49179,
					"End": 49187
				},
				{
					"Reply": "Wall-E! ",
					"Didascalie": "",
					"Start": 54799,
					"End": 54807
				},
				{
					"Reply": "Ee-vah? ",
					"Didascalie": "",
					"Start": 55094,
					"End": 55102
				},
				{
					"Reply": "Ee-vah! ",
					"Didascalie": "",
					"Start": 55463,
					"End": 55471
				},
				{
					"Reply": "Whoa. ",
					"Didascalie": "",
					"Start": 58044,
					"End": 58050
				},
				{
					"Reply": "Wall-E. ",
					"Didascalie": "",
					"Start": 59908,
					"End": 59916
				},
				{
					"Reply": "Ee-vah. ",
					"Didascalie": "",
					"Start": 60124,
					"End": 60132
				},
				{
					"Reply": " Ee-vah! ",
					"Didascalie": "(tiny wave)",
					"Start": 78453,
					"End": 78486
				},
				{
					"Reply": "Ee-vah? ",
					"Didascalie": "",
					"Start": 81845,
					"End": 81853
				},
				{
					"Reply": "Wall-E. ",
					"Didascalie": "",
					"Start": 84307,
					"End": 84315
				},
				{
					"Reply": "Ee-vah? ",
					"Didascalie": "",
					"Start": 84960,
					"End": 84968
				},
				{
					"Reply": "The orderly-arms now start on Wall-E. ",
					"Didascalie": "",
					"Start": 88629,
					"End": 88667
				},
				{
					"Reply": "Ee-vah! ",
					"Didascalie": "",
					"Start": 89961,
					"End": 89969
				},
				{
					"Reply": "Ee-vah! ",
					"Didascalie": "",
					"Start": 90804,
					"End": 90812
				},
				{
					"Reply": "EEEEEEVAAAAHH!! ",
					"Didascalie": "",
					"Start": 92113,
					"End": 92129
				},
				{
					"Reply": "His hands tremble, Don Knotts-style. ",
					"Didascalie": "",
					"Start": 92547,
					"End": 92584
				},
				{
					"Reply": "Eve aims her gun at the screen. ",
					"Didascalie": "",
					"Start": 97943,
					"End": 97975
				},
				{
					"Reply": "Eve shakes her head. ",
					"Didascalie": "",
					"Start": 100280,
					"End": 100301
				},
				{
					"Reply": " Ee-vah! ",
					"Didascalie": "(loud whisper)",
					"Start": 102651,
					"End": 102684
				},
				{
					"Reply": "He clambers up into the pilot's seat. ",
					"Didascalie": "",
					"Start": 104313,
					"End": 104351
				},
				{
					"Reply": "Ee-vaaaaaah! ",
					"Didascalie": "",
					"Start": 106227,
					"End": 106240
				},
				{
					"Reply": "Eve waits. ",
					"Didascalie": "",
					"Start": 106811,
					"End": 106822
				},
				{
					"Reply": "Kicks on the extinguisher. ",
					"Didascalie": "",
					"Start": 108927,
					"End": 108954
				},
				{
					"Reply": "Eve giggles. ",
					"Didascalie": "",
					"Start": 109376,
					"End": 109389
				},
				{
					"Reply": "E-vah -- ",
					"Didascalie": "",
					"Start": 118275,
					"End": 118284
				},
				{
					"Reply": "EE-VAHH?! ",
					"Didascalie": "",
					"Start": 125347,
					"End": 125357
				},
				{
					"Reply": "Ee-vah? ",
					"Didascalie": "",
					"Start": 137968,
					"End": 137976
				},
				{
					"Reply": "70. ",
					"Didascalie": "",
					"Start": 138454,
					"End": 138458
				},
				{
					"Reply": "Auto flips open one of his handles. ",
					"Didascalie": "",
					"Start": 139309,
					"End": 139345
				},
				{
					"Reply": " Wall-E. ",
					"Didascalie": "(weak)",
					"Start": 146670,
					"End": 146703
				},
				{
					"Reply": "M-O? ",
					"Didascalie": "",
					"Start": 147070,
					"End": 147075
				},
				{
					"Reply": " M-O. ",
					"Didascalie": "(Got it.)",
					"Start": 147260,
					"End": 147290
				},
				{
					"Reply": "Earth. ",
					"Didascalie": "",
					"Start": 148997,
					"End": 149004
				},
				{
					"Reply": "M-O? ",
					"Didascalie": "",
					"Start": 149637,
					"End": 149642
				},
				{
					"Reply": "Wall-E's meter fully charges. ",
					"Didascalie": "",
					"Start": 179344,
					"End": 179374
				},
				{
					"Reply": "Ee-vah? ",
					"Didascalie": "",
					"Start": 183278,
					"End": 183286
				},
				{
					"Reply": " Ee-vah!! ",
					"Didascalie": "(amazed)",
					"Start": 183554,
					"End": 183589
				}
			]
		},
		{
			"Character": "ON TRASH HEAP HORIZON",
			"Replies": [
				{
					"Reply": "The sun sets through the smoggy haze. ",
					"Didascalie": "",
					"Start": 2372,
					"End": 2410
				}
			]
		},
		{
			"Character": "BILLBOARD ANNOUNCER",
			"Replies": [
				{
					"Reply": "Too much garbage in your face? ",
					"Didascalie": "",
					"Start": 4449,
					"End": 4480
				},
				{
					"Reply": "The jewel of the BNL fleet: \"The Axiom\". ",
					"Didascalie": "",
					"Start": 5384,
					"End": 5425
				}
			]
		},
		{
			"Character": "BUY N LARGE CEO",
			"Replies": [
				{
					"Reply": "Because, at BNL, space is the final \"fun\"- ",
					"Didascalie": "",
					"Start": 6161,
					"End": 6204
				},
				{
					"Reply": "Greetings and congratulations, Captain! ",
					"Didascalie": "",
					"Start": 73819,
					"End": 73859
				},
				{
					"Reply": "That's right, it means it's time to go back home! ",
					"Didascalie": "",
					"Start": 74436,
					"End": 74510
				},
				{
					"Reply": "Now that Earth has been restored to a life-sustaining status, by golly, we can begin \"Operation Recolonize\"! ",
					"Didascalie": "",
					"Start": 74853,
					"End": 75010
				},
				{
					"Reply": "Simply follow this manual's instructions to place the plant in your ship's holo- ",
					"Didascalie": "",
					"Start": 75575,
					"End": 75680
				},
				{
					"Reply": "Now, due to the effects of micro-gravity, you and your passengers may have suffered some slight bone loss. But I'm sure a few laps around your ship's jogging track will get you back in shape in no time. ",
					"Didascalie": "",
					"Start": 76610,
					"End": 76909
				},
				{
					"Reply": "If you have any further questions just consult your operation manual. See you back home real soon. ",
					"Didascalie": "",
					"Start": 77268,
					"End": 77415
				},
				{
					"Reply": " Just cut it off, will ya?! ",
					"Didascalie": "(to O.S.)",
					"Start": 130771,
					"End": 130823
				},
				{
					"Reply": "Darn it all, we're going to have to cancel Operation Recolonize. ",
					"Didascalie": "",
					"Start": 131363,
					"End": 131452
				}
			]
		},
		{
			"Character": "ON COLLAPSED BRIDGE RAMP",
			"Replies": [
				{
					"Reply": "Near its edge rests a WALL-E UNIT TRANSPORT TRUCK. ",
					"Didascalie": "",
					"Start": 6533,
					"End": 6584
				}
			]
		},
		{
			"Character": "ON TV SCREEN",
			"Replies": [
				{
					"Reply": "Two lovers sing gently to one another. ",
					"Didascalie": "",
					"Start": 8454,
					"End": 8493
				}
			]
		},
		{
			"Character": "A RED DOT",
			"Replies": [
				{
					"Reply": "quivers on the dirt. ",
					"Didascalie": "",
					"Start": 13547,
					"End": 13568
				},
				{
					"Reply": "appears on the ground. ",
					"Didascalie": "",
					"Start": 175420,
					"End": 175443
				}
			]
		},
		{
			"Character": "MANY LASER POINTS",
			"Replies": [
				{
					"Reply": "coming from every direction. ",
					"Didascalie": "",
					"Start": 14012,
					"End": 14041
				}
			]
		},
		{
			"Character": "ON OTHER SIDE OF BOULDER CRATER",
			"Replies": [
				{
					"Reply": "Wall-E boxed up behind what little remains of the rock. ",
					"Didascalie": "",
					"Start": 18516,
					"End": 18572
				}
			]
		},
		{
			"Character": "HIS COCKROACH",
			"Replies": [
				{
					"Reply": "innocently approaching Eve from behind. ",
					"Didascalie": "",
					"Start": 19109,
					"End": 19149
				}
			]
		},
		{
			"Character": "EVE",
			"Replies": [
				{
					"Reply": "Wall-E relaxes. ",
					"Didascalie": "",
					"Start": 19750,
					"End": 19766
				},
				{
					"Reply": "She slowly approaches Wall-E's box. ",
					"Didascalie": "",
					"Start": 20490,
					"End": 20526
				},
				{
					"Reply": "Wall-E peeks out from his box. ",
					"Didascalie": "",
					"Start": 20741,
					"End": 20772
				},
				{
					"Reply": "Wall-E falls backwards with surprise. ",
					"Didascalie": "",
					"Start": 24755,
					"End": 24793
				},
				{
					"Reply": " Directive? ",
					"Didascalie": "(English)",
					"Start": 25325,
					"End": 25361
				},
				{
					"Reply": "Directive? ",
					"Didascalie": "",
					"Start": 25677,
					"End": 25688
				},
				{
					"Reply": "Directive? ",
					"Didascalie": "",
					"Start": 26077,
					"End": 26088
				},
				{
					"Reply": "Classified. ",
					"Didascalie": "",
					"Start": 26200,
					"End": 26212
				},
				{
					"Reply": "Name? ",
					"Didascalie": "",
					"Start": 26468,
					"End": 26474
				},
				{
					"Reply": "Wall-E. ",
					"Didascalie": "",
					"Start": 26960,
					"End": 26968
				},
				{
					"Reply": " Eve. ",
					"Didascalie": "(giggles)",
					"Start": 27010,
					"End": 27040
				},
				{
					"Reply": " Eve. ",
					"Didascalie": "(slower)",
					"Start": 27273,
					"End": 27303
				},
				{
					"Reply": "Eeeve. Eeeve. ",
					"Didascalie": "",
					"Start": 27571,
					"End": 27585
				},
				{
					"Reply": "Eve. ",
					"Didascalie": "",
					"Start": 27930,
					"End": 27935
				},
				{
					"Reply": "She draws her gun on him. ",
					"Didascalie": "",
					"Start": 28332,
					"End": 28358
				},
				{
					"Reply": "Wall-E? Wall-E? ",
					"Didascalie": "",
					"Start": 28663,
					"End": 28679
				},
				{
					"Reply": "and four other probes slide out of the ship's side. ",
					"Didascalie": "",
					"Start": 42148,
					"End": 42200
				},
				{
					"Reply": "Wall-E?! ",
					"Didascalie": "",
					"Start": 78347,
					"End": 78356
				},
				{
					"Reply": "Makes a flurry of clandestine gestures at him. ",
					"Didascalie": "",
					"Start": 78884,
					"End": 78931
				},
				{
					"Reply": " Wall-E! ",
					"Didascalie": "(turns on him)",
					"Start": 81568,
					"End": 81601
				},
				{
					"Reply": "Wall-E scared of her. ",
					"Didascalie": "",
					"Start": 82019,
					"End": 82041
				},
				{
					"Reply": "  46. ",
					"Didascalie": "(Giggles)",
					"Start": 91052,
					"End": 91136
				},
				{
					"Reply": "WALL-E! ",
					"Didascalie": "",
					"Start": 93337,
					"End": 93345
				},
				{
					"Reply": "WALL-E! ",
					"Didascalie": "",
					"Start": 94071,
					"End": 94079
				},
				{
					"Reply": " Wall-E! ",
					"Didascalie": "(stern)",
					"Start": 95418,
					"End": 95451
				},
				{
					"Reply": "Earth. ",
					"Didascalie": "",
					"Start": 99328,
					"End": 99335
				},
				{
					"Reply": "Earth. ",
					"Didascalie": "",
					"Start": 99514,
					"End": 99521
				},
				{
					"Reply": "Directive. ",
					"Didascalie": "",
					"Start": 99949,
					"End": 99960
				},
				{
					"Reply": " Wall-E. ",
					"Didascalie": "(gentle, but firm)",
					"Start": 100517,
					"End": 100551
				},
				{
					"Reply": " Wall-E. ",
					"Didascalie": "(frustrated)",
					"Start": 100857,
					"End": 100891
				},
				{
					"Reply": " Plant! ",
					"Didascalie": "(excited whisper)",
					"Start": 101942,
					"End": 101975
				},
				{
					"Reply": " Wall-E? ",
					"Didascalie": "(whisper)",
					"Start": 102406,
					"End": 102439
				},
				{
					"Reply": " Wall-E! ",
					"Didascalie": "(louder whisper)",
					"Start": 102787,
					"End": 102820
				},
				{
					"Reply": "Wall-E can't believe his luck. ",
					"Didascalie": "",
					"Start": 108067,
					"End": 108098
				},
				{
					"Reply": "She reaches for his hand. ",
					"Didascalie": "",
					"Start": 108663,
					"End": 108689
				},
				{
					"Reply": "She places a stack of towels on his head. ",
					"Didascalie": "",
					"Start": 118554,
					"End": 118596
				},
				{
					"Reply": "Directive. ",
					"Didascalie": "",
					"Start": 118758,
					"End": 118769
				},
				{
					"Reply": "  65. ",
					"Didascalie": "(MORE)",
					"Start": 127504,
					"End": 127588
				},
				{
					"Reply": " Wall-E! ",
					"Didascalie": "(CONT'D) (remembers)",
					"Start": 127695,
					"End": 127728
				},
				{
					"Reply": "It's over. ",
					"Didascalie": "",
					"Start": 137576,
					"End": 137587
				},
				{
					"Reply": "Wall-E! ",
					"Didascalie": "",
					"Start": 141470,
					"End": 141478
				},
				{
					"Reply": "Wall-E! ",
					"Didascalie": "",
					"Start": 142123,
					"End": 142131
				},
				{
					"Reply": "Wall-E! ",
					"Didascalie": "",
					"Start": 143050,
					"End": 143058
				},
				{
					"Reply": "Directive. ",
					"Didascalie": "",
					"Start": 148154,
					"End": 148165
				},
				{
					"Reply": "Earth? ",
					"Didascalie": "",
					"Start": 148874,
					"End": 148881
				},
				{
					"Reply": "Earth! Earth! ",
					"Didascalie": "",
					"Start": 149309,
					"End": 149323
				},
				{
					"Reply": "PLANT! PLANT! ",
					"Didascalie": "",
					"Start": 171876,
					"End": 171890
				},
				{
					"Reply": "No! WALL-E!! ",
					"Didascalie": "",
					"Start": 173536,
					"End": 173549
				},
				{
					"Reply": "appears out of the crowd. ",
					"Didascalie": "",
					"Start": 177121,
					"End": 177147
				},
				{
					"Reply": "Eve! ",
					"Didascalie": "",
					"Start": 179977,
					"End": 179982
				},
				{
					"Reply": "She grabs the RUBIK'S CUBE and LIGHT BULB from the shelf. ",
					"Didascalie": "",
					"Start": 180225,
					"End": 180283
				},
				{
					"Reply": "Wall-E? ",
					"Didascalie": "",
					"Start": 180509,
					"End": 180517
				},
				{
					"Reply": "She hovers over to the video player. ",
					"Didascalie": "",
					"Start": 180735,
					"End": 180772
				},
				{
					"Reply": " No. ",
					"Didascalie": "(somber)",
					"Start": 181619,
					"End": 181648
				},
				{
					"Reply": "She touches her forehead to his. ",
					"Didascalie": "",
					"Start": 182468,
					"End": 182501
				},
				{
					"Reply": "Wall-E! ",
					"Didascalie": "",
					"Start": 183365,
					"End": 183373
				}
			]
		},
		{
			"Character": "SONG ENDS",
			"Replies": [
				{
					"Reply": "Eve scans the Axiom for a way in. ",
					"Didascalie": "",
					"Start": 115115,
					"End": 115149
				}
			]
		},
		{
			"Character": "MONTAGE OF EVE SEARCHING",
			"Replies": [
				{
					"Reply": "- Scans a car engine. ",
					"Didascalie": "",
					"Start": 23281,
					"End": 23303
				}
			]
		},
		{
			"Character": "ON WALL-E",
			"Replies": [
				{
					"Reply": "It's the closest he's ever been to Eve. ",
					"Didascalie": "",
					"Start": 31947,
					"End": 31987
				},
				{
					"Reply": "He looks over his shoulder. ",
					"Didascalie": "",
					"Start": 50551,
					"End": 50579
				},
				{
					"Reply": "He eyes Eve on the transport across the room. ",
					"Didascalie": "",
					"Start": 68708,
					"End": 68754
				},
				{
					"Reply": "He glances down at EVE'S HAND. ",
					"Didascalie": "",
					"Start": 98692,
					"End": 98723
				},
				{
					"Reply": "He points the extinguisher the other way. ",
					"Didascalie": "",
					"Start": 106455,
					"End": 106497
				},
				{
					"Reply": "He stares at EVE'S HAND. ",
					"Didascalie": "",
					"Start": 117866,
					"End": 117891
				},
				{
					"Reply": "The holo-detector's hydraulics fight against him. ",
					"Didascalie": "",
					"Start": 168692,
					"End": 168742
				}
			]
		},
		{
			"Character": "BASE OF RECON SHIP",
			"Replies": [
				{
					"Reply": "The engines blast a WALL OF SMOKE. ",
					"Didascalie": "",
					"Start": 38580,
					"End": 38615
				}
			]
		},
		{
			"Character": "HUNDREDS OF BNL SATELLITES",
			"Replies": [
				{
					"Reply": "litter the outer atmosphere. ",
					"Didascalie": "",
					"Start": 39625,
					"End": 39654
				}
			]
		},
		{
			"Character": "MONTAGE OF CELESTIAL SPECTACLES",
			"Replies": [
				{
					"Reply": "- The ship flies past the MOON. ",
					"Didascalie": "",
					"Start": 40556,
					"End": 40588
				}
			]
		},
		{
			"Character": "M-O",
			"Replies": [
				{
					"Reply": "23. ",
					"Didascalie": "",
					"Start": 42811,
					"End": 42815
				},
				{
					"Reply": "They file out on the line. ",
					"Didascalie": "",
					"Start": 43077,
					"End": 43104
				},
				{
					"Reply": "He scrubs Wall-E full force. ",
					"Didascalie": "",
					"Start": 44266,
					"End": 44295
				},
				{
					"Reply": "24. ",
					"Didascalie": "",
					"Start": 44671,
					"End": 44675
				},
				{
					"Reply": "Wall-E wipes the bottom of his tread on M-O's face. ",
					"Didascalie": "",
					"Start": 45501,
					"End": 45553
				},
				{
					"Reply": "BACK IN THE CAPTAIN'S QUARTERS  The Captain at his wet bar. ",
					"Didascalie": "",
					"Start": 126149,
					"End": 126229
				},
				{
					"Reply": "M-O speeds towards the airlock. ",
					"Didascalie": "",
					"Start": 144388,
					"End": 144420
				},
				{
					"Reply": "Whoa. ",
					"Didascalie": "",
					"Start": 145565,
					"End": 145571
				},
				{
					"Reply": "M-O. ",
					"Didascalie": "",
					"Start": 146880,
					"End": 146885
				},
				{
					"Reply": "M-O. ",
					"Didascalie": "",
					"Start": 147156,
					"End": 147161
				},
				{
					"Reply": "Wall-E! ",
					"Didascalie": "",
					"Start": 149775,
					"End": 149783
				},
				{
					"Reply": "Ee-vah! ",
					"Didascalie": "",
					"Start": 172366,
					"End": 172374
				},
				{
					"Reply": "The Captain respectfully removes his hat. ",
					"Didascalie": "",
					"Start": 177884,
					"End": 177926
				},
				{
					"Reply": "Go! Go, go go! ",
					"Didascalie": "",
					"Start": 184168,
					"End": 184183
				}
			]
		},
		{
			"Character": "ON FAR WALL",
			"Replies": [
				{
					"Reply": "Two STEWARD ROBOTS come out of the wall. ",
					"Didascalie": "",
					"Start": 44857,
					"End": 44898
				}
			]
		},
		{
			"Character": "BACK ON M-O AND WALL-E",
			"Replies": [
				{
					"Reply": "M-O just finishes cleaning the floor. ",
					"Didascalie": "",
					"Start": 45205,
					"End": 45243
				}
			]
		},
		{
			"Character": "A HUMAN PASSENGER",
			"Replies": [
				{
					"Reply": "sitting, reclined, in the chair. ",
					"Didascalie": "",
					"Start": 49539,
					"End": 49572
				}
			]
		},
		{
			"Character": "ECONOMY CLASS COURTYARD",
			"Replies": [
				{
					"Reply": "Wall-E is in awe. ",
					"Didascalie": "",
					"Start": 51145,
					"End": 51163
				}
			]
		},
		{
			"Character": "JOHN",
			"Replies": [
				{
					"Reply": "Hey, Drink-bot. ",
					"Didascalie": "",
					"Start": 53422,
					"End": 53438
				},
				{
					"Reply": "Here, take the cup. Take the cup -- Whoa! ",
					"Didascalie": "",
					"Start": 53604,
					"End": 53646
				},
				{
					"Reply": "Stewards? Hello? Uhh, help. ",
					"Didascalie": "",
					"Start": 54181,
					"End": 54209
				},
				{
					"Reply": "Uh no, John. ",
					"Didascalie": "",
					"Start": 55187,
					"End": 55200
				},
				{
					"Reply": "Hey! What the -- ",
					"Didascalie": "",
					"Start": 110654,
					"End": 110671
				},
				{
					"Reply": " Wall-E! Hey Wall-E! It's your buddy, John! ",
					"Didascalie": "(snaps fingers)",
					"Start": 111338,
					"End": 111406
				},
				{
					"Reply": "Hi. ",
					"Didascalie": "",
					"Start": 112001,
					"End": 112005
				},
				{
					"Reply": "I didn't know we had a pool. ",
					"Didascalie": "",
					"Start": 116706,
					"End": 116735
				}
			]
		},
		{
			"Character": "STEWARD",
			"Replies": [
				{
					"Reply": "Please remain stationary. A service-bot will be here to assist you momentarily. ",
					"Didascalie": "",
					"Start": 54289,
					"End": 54393
				},
				{
					"Reply": "Halt. ",
					"Didascalie": "",
					"Start": 95135,
					"End": 95141
				},
				{
					"Reply": "Wrong. ",
					"Didascalie": "",
					"Start": 150583,
					"End": 150590
				},
				{
					"Reply": "Please hold. We are currently having technical difficul -- ! ",
					"Didascalie": "",
					"Start": 151762,
					"End": 151847
				}
			]
		},
		{
			"Character": "ON MONORAIL",
			"Replies": [
				{
					"Reply": "It pulls out of the station. ",
					"Didascalie": "",
					"Start": 55669,
					"End": 55698
				},
				{
					"Reply": "Wall-E takes in the overstimulating scenery. ",
					"Didascalie": "",
					"Start": 56473,
					"End": 56518
				},
				{
					"Reply": "It stops at the BRIDGE PLAZA. ",
					"Didascalie": "",
					"Start": 61135,
					"End": 61165
				}
			]
		},
		{
			"Character": "NANNY-BOT",
			"Replies": [
				{
					"Reply": "Remain calm. Remain calm. ",
					"Didascalie": "",
					"Start": 164032,
					"End": 164058
				}
			]
		},
		{
			"Character": "OUT THE WINDOW",
			"Replies": [
				{
					"Reply": "Wall-E's monorail glides past. ",
					"Didascalie": "",
					"Start": 56388,
					"End": 56419
				}
			]
		},
		{
			"Character": "MARY",
			"Replies": [
				{
					"Reply": "31. ",
					"Didascalie": "",
					"Start": 59304,
					"End": 59308
				},
				{
					"Reply": " M-mary. ",
					"Didascalie": "(beat)",
					"Start": 60009,
					"End": 60042
				},
				{
					"Reply": "Huh? Oh, uh, sure go ahead. ",
					"Didascalie": "",
					"Start": 60351,
					"End": 60379
				},
				{
					"Reply": "I didn't know we had a pool! ",
					"Didascalie": "",
					"Start": 61814,
					"End": 61843
				},
				{
					"Reply": " So many stars. ",
					"Didascalie": "(sigh)",
					"Start": 110191,
					"End": 110231
				},
				{
					"Reply": "Look! Look at THAT! ",
					"Didascalie": "",
					"Start": 110871,
					"End": 110891
				},
				{
					"Reply": "Right, Wall-E! Hi Wall-E! ",
					"Didascalie": "",
					"Start": 111591,
					"End": 111617
				},
				{
					"Reply": "Hi. ",
					"Didascalie": "",
					"Start": 112084,
					"End": 112088
				},
				{
					"Reply": "John, get ready to have some kids! ",
					"Didascalie": "",
					"Start": 166699,
					"End": 166734
				},
				{
					"Reply": " LOOK OUT! ",
					"Didascalie": "(Gasp)",
					"Start": 167325,
					"End": 167363
				}
			]
		},
		{
			"Character": "POOLSIDE PASSENGER",
			"Replies": [
				{
					"Reply": "Shade. ",
					"Didascalie": "",
					"Start": 61074,
					"End": 61081
				}
			]
		},
		{
			"Character": "ON MARY",
			"Replies": [
				{
					"Reply": "She is the last to exit the car. ",
					"Didascalie": "",
					"Start": 61558,
					"End": 61591
				}
			]
		},
		{
			"Character": "AUTOPILOT",
			"Replies": [
				{
					"Reply": "Captain. You are needed on the bridge. ",
					"Didascalie": "",
					"Start": 64683,
					"End": 64722
				},
				{
					"Reply": "Sir -- ",
					"Didascalie": "",
					"Start": 67198,
					"End": 67205
				},
				{
					"Reply": "Sir, the annual -- ",
					"Didascalie": "",
					"Start": 67758,
					"End": 67777
				},
				{
					"Reply": "Sir, the annual reconnaissance has -- ",
					"Didascalie": "",
					"Start": 69321,
					"End": 69359
				},
				{
					"Reply": "Captain? ",
					"Didascalie": "",
					"Start": 72499,
					"End": 72508
				},
				{
					"Reply": "Probe One has returned positive. ",
					"Didascalie": "",
					"Start": 72733,
					"End": 72766
				},
				{
					"Reply": "Plant. ",
					"Didascalie": "",
					"Start": 80847,
					"End": 80854
				},
				{
					"Reply": "Contains no specimen. Probe's memory is faulty. ",
					"Didascalie": "",
					"Start": 82390,
					"End": 82462
				},
				{
					"Reply": " Negative. ",
					"Didascalie": "(shakes his wheel)",
					"Start": 82686,
					"End": 82721
				},
				{
					"Reply": "Correct, Captain. ",
					"Didascalie": "",
					"Start": 82954,
					"End": 82972
				},
				{
					"Reply": "Good night, Captain. ",
					"Didascalie": "",
					"Start": 113956,
					"End": 113977
				},
				{
					"Reply": "Not necessary, Captain. You may give it to me. ",
					"Didascalie": "",
					"Start": 128224,
					"End": 128295
				},
				{
					"Reply": "Captain! ",
					"Didascalie": "",
					"Start": 128589,
					"End": 128598
				},
				{
					"Reply": "Sir, I insist you give me the plant. ",
					"Didascalie": "",
					"Start": 128820,
					"End": 128857
				},
				{
					"Reply": "Sir, we cannot go home. ",
					"Didascalie": "",
					"Start": 129044,
					"End": 129068
				},
				{
					"Reply": "That is classified. Captain, give me the plant. ",
					"Didascalie": "",
					"Start": 129267,
					"End": 129339
				},
				{
					"Reply": "Give me the plant. ",
					"Didascalie": "",
					"Start": 129760,
					"End": 129779
				},
				{
					"Reply": "The plant. ",
					"Didascalie": "",
					"Start": 129968,
					"End": 129979
				},
				{
					"Reply": "Aye-aye, sir. ",
					"Didascalie": "",
					"Start": 130229,
					"End": 130243
				},
				{
					"Reply": "Now, the plant. ",
					"Didascalie": "",
					"Start": 132918,
					"End": 132934
				},
				{
					"Reply": "Sir, orders are: \"Do not return to Earth\". ",
					"Didascalie": "",
					"Start": 133728,
					"End": 133795
				},
				{
					"Reply": "Irrelevant, Captain. ",
					"Didascalie": "",
					"Start": 134105,
					"End": 134126
				},
				{
					"Reply": "On the Axiom you will survive. ",
					"Didascalie": "",
					"Start": 134789,
					"End": 134820
				},
				{
					"Reply": "Must follow my directive. ",
					"Didascalie": "",
					"Start": 135023,
					"End": 135049
				},
				{
					"Reply": "Give me the plant. ",
					"Didascalie": "",
					"Start": 138888,
					"End": 138907
				},
				{
					"Reply": "All communications are terminated. You are confined to quarters. ",
					"Didascalie": "",
					"Start": 140170,
					"End": 140259
				}
			]
		},
		{
			"Character": "CAPTAIN",
			"Replies": [
				{
					"Reply": "-- All hands on deck!! ",
					"Didascalie": "",
					"Start": 65739,
					"End": 65762
				},
				{
					"Reply": "  Lines light on the floor. ",
					"Didascalie": "(Giggles)",
					"Start": 66465,
					"End": 66513
				},
				{
					"Reply": "Coffee. ",
					"Didascalie": "",
					"Start": 67288,
					"End": 67296
				},
				{
					"Reply": "Protocol, Auto. First things first. ",
					"Didascalie": "",
					"Start": 67938,
					"End": 67974
				},
				{
					"Reply": " Computer, status report. ",
					"Didascalie": "(to the room)",
					"Start": 68018,
					"End": 68068
				},
				{
					"Reply": "Okay, Auto. ",
					"Didascalie": "",
					"Start": 69227,
					"End": 69239
				},
				{
					"Reply": "12:30?! ",
					"Didascalie": "",
					"Start": 69490,
					"End": 69498
				},
				{
					"Reply": " Auto, why didn't you wake me for the morning announcements? ",
					"Didascalie": "(disappointed sigh)",
					"Start": 69548,
					"End": 69657
				},
				{
					"Reply": "Honestly, it's the one thing I get to do on this ship. ",
					"Didascalie": "",
					"Start": 70010,
					"End": 70089
				},
				{
					"Reply": "Positive? ",
					"Didascalie": "",
					"Start": 72845,
					"End": 72855
				},
				{
					"Reply": " Home? W-w-we're going back? ",
					"Didascalie": "(nervous)",
					"Start": 74712,
					"End": 74765
				},
				{
					"Reply": "We have a jogging track? ",
					"Didascalie": "",
					"Start": 77155,
					"End": 77180
				},
				{
					"Reply": " Well, let's open her up. Step One. Voice command, \"Confirm Acquisition.\" ",
					"Didascalie": "(reads aloud)",
					"Start": 79449,
					"End": 79577
				},
				{
					"Reply": "Where's the thingie? ",
					"Didascalie": "",
					"Start": 80739,
					"End": 80760
				},
				{
					"Reply": "Plant. Right. Right. Where is it? ",
					"Didascalie": "",
					"Start": 80940,
					"End": 80974
				},
				{
					"Reply": "Why don't you scan her to be sure. ",
					"Didascalie": "",
					"Start": 82156,
					"End": 82191
				},
				{
					"Reply": "So, uh, I guess things go back to normal, huh? ",
					"Didascalie": "",
					"Start": 82801,
					"End": 82872
				},
				{
					"Reply": " Well, false alarm! ",
					"Didascalie": "(privately relieved)",
					"Start": 83079,
					"End": 83123
				},
				{
					"Reply": "The probe must be defective. Gopher, send her to the Repair Ward. ",
					"Didascalie": "",
					"Start": 83581,
					"End": 83671
				},
				{
					"Reply": "Have them run diagnostics on her. Make sure she's not malfunctioning -- EEYAH!! ",
					"Didascalie": "",
					"Start": 83931,
					"End": 84035
				},
				{
					"Reply": "Have \"Wall-E\" cleaned. ",
					"Didascalie": "",
					"Start": 84513,
					"End": 84536
				},
				{
					"Reply": "Analyze. ",
					"Didascalie": "",
					"Start": 85363,
					"End": 85372
				},
				{
					"Reply": "Earth? ",
					"Didascalie": "",
					"Start": 86080,
					"End": 86087
				},
				{
					"Reply": "Define \"hoe-down\". ",
					"Didascalie": "",
					"Start": 112764,
					"End": 112783
				},
				{
					"Reply": "Auto! Earth is amazing! ",
					"Didascalie": "",
					"Start": 113554,
					"End": 113578
				},
				{
					"Reply": " These are called \"farms\". Humans would put seeds in the ground, pour water on them, and they'd grow food, like, pizza -- ",
					"Didascalie": "(points to images)",
					"Start": 113627,
					"End": 113821
				},
				{
					"Reply": "  Auto rises back up to the bridge. ",
					"Didascalie": "(annoyed grunt)",
					"Start": 114072,
					"End": 114128
				},
				{
					"Reply": "Psst! Computer. ",
					"Didascalie": "",
					"Start": 114353,
					"End": 114369
				},
				{
					"Reply": "to do it. It's all about you people -- ",
					"Didascalie": "",
					"Start": 119825,
					"End": 119864
				},
				{
					"Reply": " What's it like now? ",
					"Didascalie": "(laughs)",
					"Start": 120659,
					"End": 120706
				},
				{
					"Reply": "No, no! Don't tell me! I want to see for myself! ",
					"Didascalie": "",
					"Start": 120861,
					"End": 120936
				},
				{
					"Reply": " Wait a minute. ",
					"Didascalie": "(remembers)",
					"Start": 123287,
					"End": 123327
				},
				{
					"Reply": " We have to go back. ",
					"Didascalie": "(to himself)",
					"Start": 126807,
					"End": 126852
				},
				{
					"Reply": "Auto, come down here! ",
					"Didascalie": "",
					"Start": 126988,
					"End": 127010
				},
				{
					"Reply": "Auto, Eve found the plant. Fire up the Holo-detector. ",
					"Didascalie": "",
					"Start": 128064,
					"End": 128142
				},
				{
					"Reply": " You know what? I should do it myself. ",
					"Didascalie": "(not listening)",
					"Start": 128397,
					"End": 128460
				},
				{
					"Reply": "Auto, get out of my way. ",
					"Didascalie": "",
					"Start": 128937,
					"End": 128962
				},
				{
					"Reply": "What are you talking about? Why not? ",
					"Didascalie": "",
					"Start": 129148,
					"End": 129185
				},
				{
					"Reply": " What do you mean, \"classified\"? You don't keep secrets from the Captain! ",
					"Didascalie": "(holds plant out of reach)",
					"Start": 129452,
					"End": 129574
				},
				{
					"Reply": "Tell me what's classified! ",
					"Didascalie": "",
					"Start": 129859,
					"End": 129886
				},
				{
					"Reply": "Tell me, Auto! That's an order! ",
					"Didascalie": "",
					"Start": 130059,
					"End": 130091
				},
				{
					"Reply": "Unsustainable? What? ",
					"Didascalie": "",
					"Start": 131254,
					"End": 131275
				},
				{
					"Reply": " Easier? ",
					"Didascalie": "(offended)",
					"Start": 131821,
					"End": 131854
				},
				{
					"Reply": "No, wait a minute. Computer, when was that message sent to the Axiom? ",
					"Didascalie": "",
					"Start": 133014,
					"End": 133108
				},
				{
					"Reply": "That's -- that's nearly 700 years ago!! ",
					"Didascalie": "",
					"Start": 133509,
					"End": 133549
				},
				{
					"Reply": "But life is sustainable now! Look at this plant, green and growing! It's living proof he was wrong. ",
					"Didascalie": "",
					"Start": 133875,
					"End": 134023
				},
				{
					"Reply": "What?! It's completely relevant! ",
					"Didascalie": "",
					"Start": 134312,
					"End": 134345
				},
				{
					"Reply": "I DON'T WANT TO SURVIVE! I WANT TO LIVE! ",
					"Didascalie": "",
					"Start": 134900,
					"End": 134941
				},
				{
					"Reply": "DAAAARGH!! ",
					"Didascalie": "",
					"Start": 135129,
					"End": 135140
				},
				{
					"Reply": "I'm the Captain of the Axiom. We are going home today! ",
					"Didascalie": "",
					"Start": 135799,
					"End": 135878
				},
				{
					"Reply": "Gopher? ",
					"Didascalie": "",
					"Start": 136329,
					"End": 136337
				},
				{
					"Reply": "Hey! That's my plant. This is mutiny! ",
					"Didascalie": "",
					"Start": 136640,
					"End": 136678
				},
				{
					"Reply": " Eve, arrest him! ",
					"Didascalie": "(to Eve)",
					"Start": 136720,
					"End": 136765
				},
				{
					"Reply": "Eve, you are to put this plant straight in the Holo-detector. ",
					"Didascalie": "",
					"Start": 137080,
					"End": 137169
				},
				{
					"Reply": "No! ",
					"Didascalie": "",
					"Start": 137416,
					"End": 137420
				},
				{
					"Reply": "NO! MUTINY! MUTINY! MUTINEEEEE!! ",
					"Didascalie": "",
					"Start": 140692,
					"End": 140725
				},
				{
					"Reply": "The plant! ",
					"Didascalie": "",
					"Start": 154720,
					"End": 154731
				},
				{
					"Reply": "We'll see who's powerless now. ",
					"Didascalie": "(Laughs)",
					"Start": 155028,
					"End": 155060
				},
				{
					"Reply": "Ah-Ha! ",
					"Didascalie": "",
					"Start": 155290,
					"End": 155297
				},
				{
					"Reply": "Ha ha! ",
					"Didascalie": "",
					"Start": 159526,
					"End": 159533
				},
				{
					"Reply": "What too heavy for ya, huh?! ",
					"Didascalie": "",
					"Start": 160804,
					"End": 160833
				},
				{
					"Reply": "You're not getting away from me, one-eye! ",
					"Didascalie": "",
					"Start": 161188,
					"End": 161230
				},
				{
					"Reply": "Gotcha! Ha ha! ",
					"Didascalie": "",
					"Start": 162617,
					"End": 162632
				},
				{
					"Reply": "Ladies and Gentlemen! This is your Captain speaking! We're having a slight malfunction with the Autopilot! Please remain calm! ",
					"Didascalie": "",
					"Start": 164595,
					"End": 164797
				},
				{
					"Reply": "NO!! ",
					"Didascalie": "",
					"Start": 169191,
					"End": 169196
				},
				{
					"Reply": "Auto! ",
					"Didascalie": "",
					"Start": 170243,
					"End": 170249
				},
				{
					"Reply": " Auto, you are relieved of duty. ",
					"Didascalie": "(grits his teeth)",
					"Start": 170991,
					"End": 171051
				},
				{
					"Reply": "This is called \"farming\"! You kids are going to grow all kinds of plants: vegetable plants, pizza plants! ",
					"Didascalie": "",
					"Start": 184943,
					"End": 185097
				}
			]
		},
		{
			"Character": "BEAUTICIAN-BOT",
			"Replies": [
				{
					"Reply": "Morning! Just a trim? ",
					"Didascalie": "",
					"Start": 66246,
					"End": 66268
				},
				{
					"Reply": "Just a trim? Uh huh. ",
					"Didascalie": "",
					"Start": 88960,
					"End": 88981
				},
				{
					"Reply": "You look gorgeous. ",
					"Didascalie": "",
					"Start": 89303,
					"End": 89322
				}
			]
		},
		{
			"Character": "ON THE BRIDGE",
			"Replies": [
				{
					"Reply": "Elevator doors swish open. ",
					"Didascalie": "",
					"Start": 66681,
					"End": 66708
				}
			]
		},
		{
			"Character": "OUT ON LIDO DECK",
			"Replies": [
				{
					"Reply": "- The FAKE NOON SUN reverses at high speed to a SUNRISE. ",
					"Didascalie": "",
					"Start": 70280,
					"End": 70337
				}
			]
		},
		{
			"Character": "BACK ON THE BRIDGE",
			"Replies": [
				{
					"Reply": "The Captain stares at a FLASHING BUTTON on the console. ",
					"Didascalie": "",
					"Start": 72195,
					"End": 72251
				},
				{
					"Reply": "Auto watches the deck plan display. ",
					"Didascalie": "",
					"Start": 153663,
					"End": 153699
				}
			]
		},
		{
			"Character": "ON EVE",
			"Replies": [
				{
					"Reply": "Wall-E taps her shoulder. ",
					"Didascalie": "",
					"Start": 78205,
					"End": 78231
				},
				{
					"Reply": "She races through space after him. ",
					"Didascalie": "",
					"Start": 105717,
					"End": 105752
				},
				{
					"Reply": "Amazed at Wall-E's selfless dedication to her. ",
					"Didascalie": "",
					"Start": 124488,
					"End": 124535
				},
				{
					"Reply": "Tugs on Wall-E. ",
					"Didascalie": "",
					"Start": 144469,
					"End": 144485
				},
				{
					"Reply": "She fights to keep the machine from crushing Wall-E further. ",
					"Didascalie": "",
					"Start": 172221,
					"End": 172282
				},
				{
					"Reply": "She holds tightly to Wall-E. ",
					"Didascalie": "",
					"Start": 174867,
					"End": 174896
				}
			]
		},
		{
			"Character": "ON THE CAPTAIN",
			"Replies": [
				{
					"Reply": "He manages to turn to the FIRST PAGE OF INSTRUCTIONS. ",
					"Didascalie": "",
					"Start": 79289,
					"End": 79343
				}
			]
		},
		{
			"Character": "OUT IN THE REPAIR WARD",
			"Replies": [
				{
					"Reply": "Wall-E stares at the frosted glass doors. ",
					"Didascalie": "",
					"Start": 90591,
					"End": 90633
				}
			]
		},
		{
			"Character": "BACK ON WALL-E",
			"Replies": [
				{
					"Reply": "It looks as if Eve is being beheaded. ",
					"Didascalie": "",
					"Start": 91692,
					"End": 91730
				},
				{
					"Reply": "The holo-detector reverses full force. ",
					"Didascalie": "",
					"Start": 169253,
					"End": 169292
				}
			]
		},
		{
			"Character": "ALL AROUND THE SHIP",
			"Replies": [
				{
					"Reply": "Alarms sound. ",
					"Didascalie": "",
					"Start": 95740,
					"End": 95754
				}
			]
		},
		{
			"Character": "BACK WITH EVE AND WALL-E",
			"Replies": [
				{
					"Reply": "Eve realizes what's about to happen. ",
					"Didascalie": "",
					"Start": 96329,
					"End": 96366
				}
			]
		},
		{
			"Character": "STEWARDS",
			"Replies": [
				{
					"Reply": "Halt. Halt. ",
					"Didascalie": "",
					"Start": 96508,
					"End": 96520
				},
				{
					"Reply": "Halt. ",
					"Didascalie": "",
					"Start": 157100,
					"End": 157106
				}
			]
		},
		{
			"Character": "ON VARIOUS HALLWAYS",
			"Replies": [
				{
					"Reply": "Robots recognize Eve and Wall-E as they fly past. ",
					"Didascalie": "",
					"Start": 96716,
					"End": 96766
				},
				{
					"Reply": "REJECTS come out of hiding as they hear the music. ",
					"Didascalie": "",
					"Start": 152215,
					"End": 152266
				}
			]
		},
		{
			"Character": "AN ESCAPE POD",
			"Replies": [
				{
					"Reply": "is revealed at the end of the room. ",
					"Didascalie": "",
					"Start": 99080,
					"End": 99116
				}
			]
		},
		{
			"Character": "GOPHER",
			"Replies": [
				{
					"Reply": "Eve and Wall-E look at each other. ",
					"Didascalie": "",
					"Start": 101572,
					"End": 101607
				},
				{
					"Reply": "shoots out of a pneumatic tube. ",
					"Didascalie": "",
					"Start": 136089,
					"End": 136121
				}
			]
		},
		{
			"Character": "CLOSER ON LOWER HULL",
			"Replies": [
				{
					"Reply": "Eve and Wall-E fly into the open hatch behind him. ",
					"Didascalie": "",
					"Start": 115331,
					"End": 115382
				}
			]
		},
		{
			"Character": "LIFEGUARD-BOT",
			"Replies": [
				{
					"Reply": "No splashing, no diving. ",
					"Didascalie": "",
					"Start": 116955,
					"End": 116980
				},
				{
					"Reply": " Ahh! Go on! ",
					"Didascalie": "(annoyed)",
					"Start": 117084,
					"End": 117123
				}
			]
		},
		{
			"Character": "ON UPPER DECK",
			"Replies": [
				{
					"Reply": "Eve and Wall-E sneak onto the deck. ",
					"Didascalie": "",
					"Start": 117250,
					"End": 117286
				}
			]
		},
		{
			"Character": "ON TRASH CAN",
			"Replies": [
				{
					"Reply": "NOISES. Eve bursts out from it, like an angel. ",
					"Didascalie": "",
					"Start": 119919,
					"End": 119966
				}
			]
		},
		{
			"Character": "HIS FOOT",
			"Replies": [
				{
					"Reply": "It's tapping in time to the music. ",
					"Didascalie": "",
					"Start": 122731,
					"End": 122766
				}
			]
		},
		{
			"Character": "OUT ON THE UPPER DECK",
			"Replies": [
				{
					"Reply": "A monorail pulls up. ",
					"Didascalie": "",
					"Start": 125750,
					"End": 125771
				}
			]
		},
		{
			"Character": "AUTO",
			"Replies": [
				{
					"Reply": "lowering in front of her. ",
					"Didascalie": "",
					"Start": 127863,
					"End": 127889
				},
				{
					"Reply": "Not possible. ",
					"Didascalie": "",
					"Start": 152920,
					"End": 152934
				},
				{
					"Reply": "Not possible. ",
					"Didascalie": "",
					"Start": 158827,
					"End": 158841
				},
				{
					"Reply": "No. ",
					"Didascalie": "",
					"Start": 159110,
					"End": 159114
				},
				{
					"Reply": "Let go. Let go. ",
					"Didascalie": "",
					"Start": 160563,
					"End": 160579
				},
				{
					"Reply": "Enough. ",
					"Didascalie": "",
					"Start": 165272,
					"End": 165280
				},
				{
					"Reply": "No. ",
					"Didascalie": "",
					"Start": 168576,
					"End": 168580
				},
				{
					"Reply": "Noo -- ",
					"Didascalie": "",
					"Start": 171133,
					"End": 171140
				}
			]
		},
		{
			"Character": "CEO ADVISOR",
			"Replies": [
				{
					"Reply": "Mr. President, sir, it's time to go. ",
					"Didascalie": "",
					"Start": 132050,
					"End": 132087
				}
			]
		},
		{
			"Character": "DOWN SHOT THROUGH BRIDGE FLOOR APERTURE",
			"Replies": [
				{
					"Reply": "The Captain looks up. ",
					"Didascalie": "",
					"Start": 140553,
					"End": 140575
				}
			]
		},
		{
			"Character": "TWO GIANT COMPACTOR ROBOTS",
			"Replies": [
				{
					"Reply": "as they rumble up behind her. ",
					"Didascalie": "",
					"Start": 142397,
					"End": 142427
				}
			]
		},
		{
			"Character": "BACK IN THE GARBAGE DEPOT",
			"Replies": [
				{
					"Reply": "M-O suddenly drops from a ceiling chute. ",
					"Didascalie": "",
					"Start": 143693,
					"End": 143734
				}
			]
		},
		{
			"Character": "ON M-O",
			"Replies": [
				{
					"Reply": "Racing towards the doors. ",
					"Didascalie": "",
					"Start": 144716,
					"End": 144742
				},
				{
					"Reply": "He searches the crowd for the plant. ",
					"Didascalie": "",
					"Start": 171939,
					"End": 171976
				}
			]
		},
		{
			"Character": "A YELLOW LINE",
			"Replies": [
				{
					"Reply": "painted haphazardly on the floor. ",
					"Didascalie": "",
					"Start": 150416,
					"End": 150450
				}
			]
		},
		{
			"Character": "ON SCREENS AROUND THE AXIOM",
			"Replies": [
				{
					"Reply": "Eve and Wall-E's \"Wanted\" image instantly circulates. ",
					"Didascalie": "",
					"Start": 152436,
					"End": 152490
				}
			]
		},
		{
			"Character": "ALL AROUND THE AXIOM",
			"Replies": [
				{
					"Reply": "All screens display the Captain's live feed. ",
					"Didascalie": "",
					"Start": 156028,
					"End": 156073
				}
			]
		},
		{
			"Character": "BACK ON EVE AND WALL-E",
			"Replies": [
				{
					"Reply": "Psssst! Hey! Hey! This is the Captain I'm locked in my room. Eve, Wall-E, bring the plant to the Lido Deck. I'll have activated the holo-detector. Now hurry! ",
					"Didascalie": "",
					"Start": 156512,
					"End": 156742
				}
			]
		},
		{
			"Character": "BEHIND THE UMBRELLA-BOT",
			"Replies": [
				{
					"Reply": "A weak Wall-E activates his welding beam. ",
					"Didascalie": "",
					"Start": 157896,
					"End": 157938
				}
			]
		},
		{
			"Character": "UP ON THE BRIDGE",
			"Replies": [
				{
					"Reply": "Auto watches steward blips disappear from his screen. ",
					"Didascalie": "",
					"Start": 158396,
					"End": 158450
				}
			]
		},
		{
			"Character": "ON LIDO DECK",
			"Replies": [
				{
					"Reply": "82. ",
					"Didascalie": "",
					"Start": 161608,
					"End": 161612
				},
				{
					"Reply": "Eve and Wall-E slam into the holo-detector's side. ",
					"Didascalie": "",
					"Start": 165488,
					"End": 165539
				},
				{
					"Reply": "85. ",
					"Didascalie": "",
					"Start": 167854,
					"End": 167858
				},
				{
					"Reply": "The passengers all spill across the deck. ",
					"Didascalie": "",
					"Start": 171370,
					"End": 171412
				}
			]
		},
		{
			"Character": "ON WALL-E AND EVE",
			"Replies": [
				{
					"Reply": "We PAN OVER the smoking wreckage of the stewards. ",
					"Didascalie": "",
					"Start": 161852,
					"End": 161902
				}
			]
		},
		{
			"Character": "ON JOHN AND MARY",
			"Replies": [
				{
					"Reply": "They arrive together at the Lido Deck. ",
					"Didascalie": "",
					"Start": 163795,
					"End": 163834
				}
			]
		},
		{
			"Character": "ON THE REAR OF THE DECK",
			"Replies": [
				{
					"Reply": "Eve and Wall-E fly out of the transport tunnel. ",
					"Didascalie": "",
					"Start": 164982,
					"End": 165030
				}
			]
		},
		{
			"Character": "ON BRIDGE",
			"Replies": [
				{
					"Reply": "Auto keeps the ship tilted. ",
					"Didascalie": "",
					"Start": 167632,
					"End": 167660
				},
				{
					"Reply": "The holo-detector button buzzes and flashes. ",
					"Didascalie": "",
					"Start": 168316,
					"End": 168361
				},
				{
					"Reply": "The Captain watches Wall-E's heroic rise on screen. ",
					"Didascalie": "",
					"Start": 168951,
					"End": 169003
				},
				{
					"Reply": "Auto hears the distant cheering. ",
					"Didascalie": "",
					"Start": 170089,
					"End": 170122
				}
			]
		},
		{
			"Character": "BACK ON BRIDGE",
			"Replies": [
				{
					"Reply": "The Captain watches Wall-E being crushed. ",
					"Didascalie": "",
					"Start": 169538,
					"End": 169580
				}
			]
		},
		{
			"Character": "ON JUMBOTRON SCREEN",
			"Replies": [
				{
					"Reply": "The passengers collectively GASP. ",
					"Didascalie": "",
					"Start": 169864,
					"End": 169898
				}
			]
		},
		{
			"Character": "WIDE ON DOME CEILING",
			"Replies": [
				{
					"Reply": "It converts into a GIANT STAR CHART. ",
					"Didascalie": "",
					"Start": 173188,
					"End": 173225
				}
			]
		},
		{
			"Character": "ON SPACE",
			"Replies": [
				{
					"Reply": "The Axiom zooms through hyperspace. ",
					"Didascalie": "",
					"Start": 175008,
					"End": 175044
				}
			]
		},
		{
			"Character": "ON CLOUD COVER",
			"Replies": [
				{
					"Reply": "A DARK PATCH grows behind the clouds. ",
					"Didascalie": "",
					"Start": 175665,
					"End": 175703
				}
			]
		},
		{
			"Character": "ON AXIOM",
			"Replies": [
				{
					"Reply": "The city-size starliner lowers gracefully from the sky. ",
					"Didascalie": "",
					"Start": 176035,
					"End": 176091
				}
			]
		},
		{
			"Character": "ON BELLY OF THE AXIOM",
			"Replies": [
				{
					"Reply": "A ROW OF GIANT DOORS open on the side of the ship. ",
					"Didascalie": "",
					"Start": 176601,
					"End": 176652
				}
			]
		},
		{
			"Character": "OUT ON THE EMPTY BAY",
			"Replies": [
				{
					"Reply": "The rejects stop. ",
					"Didascalie": "",
					"Start": 178806,
					"End": 178824
				}
			]
		},
		{
			"Character": "BACK IN THE TRUCK",
			"Replies": [
				{
					"Reply": "A shaft of sunlight beams down on Wall-E. ",
					"Didascalie": "",
					"Start": 178951,
					"End": 178993
				}
			]
		},
		{
			"Character": "CLOSE UP OF THE PLANT",
			"Replies": [
				{
					"Reply": "94. ",
					"Didascalie": "",
					"Start": 184544,
					"End": 184548
				}
			]
		}
	]
}